Workbook

Sheet 00_LEIA-ME
B2: APP — Agro Peças Padrão | Master de Produtos Shopify
B3: Documento de referência única (single source of truth) para subida e atualização de produtos.
B5: 📋 OBJETIVO
B6: Padronizar o cadastro de produtos antes de subir para o Shopify (via CSV import, Admin API ou Shopify CLI/MCP). Esta planilha consolida custo, frete inbound, embalagem (peso+dimensões), margem, taxa Mercado Pago e pesquisa de mercado por SKU — eliminando re-trabalho e divergência entre planilha e loja.
B8: 🗂️ ESTRUTURA DAS ABAS
B9: • 00_LEIA-ME — este guia • 01_CONFIG_GLOBAL — parâmetros globais (taxa MP, margem padrão, frete padrão) usados como referência em todas as abas • 02_SOHIPREN — bombas hidráulicas (1.005 SKUs já pré-carregados) • 03_AGRAL — peças plásticas injetadas (35 SKUs pré-carregados) • 04_GRECO — sensores agrícolas (11 SKUs pré-carregados) • 05_AGCO — peças plásticas (22 SKUs pré-carregados) • 06_ADG — estrutura vazia (aguardando definição da parceria) • 08_RESUMO_GERAL — dashboard de status • 09_PESQUISA_MERCADO — consolidação dos preços de concorrência
B11: 🎨 CONVENÇÃO DE CORES
B12: • Verde Campo (#1B4332) — cabeçalhos primários • Dourado (#D4AF37) — agrupamentos • Texto azul — célula de INPUT do operador • Fundo cinza claro — célula CALCULADA (não editar) • Fundo amarelo — FALTA dado, pesquisar / preencher • Fundo verde claro — Posicionamento abaixo da concorrência (oportunidade) • Fundo vermelho claro — Posicionamento acima ou cadastro divergente
B14: 🔑 CHAVE DE MATCH COM SHOPIFY
B15: A coluna 'SKU / Código' (coluna A) é a chave única que liga esta planilha ao Shopify. • SOHIPREN → coluna 'Codigo' da MACRO (ex: 5.1621.0620002.0) • AGRAL → coluna 'Referencia' da MACRO (ex: 6424-4005) • GRECO → coluna 'Código' da MACRO (ex: GR141207) • AGCO → coluna 'Código' da MACRO (ex: ACX3266690) Todos esses códigos devem ser gravados no campo 'SKU' do variant do Shopify.
B17: ⚙️ FÓRMULAS AUTOMÁTICAS
B18: • Handle (Shopify) — slug gerado do Title • Peso cubado (kg) = (C × L × A em cm) / 6000 • Peso considerado = MAX(peso real, peso cubado) — é o que a transportadora cobra • Custo + frete inbound = Custo unitário + Frete fábrica→eCom • Preço c/ margem = (Custo+frete) / (1 − %margem) • Taxa MP () = Preço c/ margem × Taxa MP global • Preço final site = Preço c/ margem / (1 − Taxa MP) • Posicionamento = compara preço final vs média concorrência
... B1006: Dashboard executivo de integrações: acompanhe fotos, descrições e divergências (link enviado à parte).

Sheet 01_CONFIG_GLOBAL
B1: Parâmetros Globais — APP
B2: Parâmetro | C2: Valor | D2: Observação
B3: Margem padrão (referência) | C3: 0.3 | D3: Usada como sugestão inicial — cada SKU pode ter sua margem
B4: Taxa Mercado Pago (%) | C4: 0.05 | D4: Cartão à vista padrão (4,99%) — ajustar se mudar de plano
B5: Taxa MP (parcelado 12x s/ juros) | C5: 0.1682 | D5: Referência para análise — não aplicada automaticamente
B6: Frete inbound padrão () | C6: 25 | D6: Estimativa default por volume — substituir por valor real
B7: ICMS-ST aplicável | C7: verificar | D7: Conforme NCM/CFOP da peça — consultar contador
B8: IPI aplicável | C8: verificar | D8: Conforme classificação fiscal
B9: Markup mínimo aceitável (%) | C9: 0.25 | D9: Threshold para alerta — abaixo disso, revisar
B10: ROAS mínimo Google Ads | C10: 4 | D10: Meta para campanhas pagas — abaixo disso, pausar criativo
B11: Frete grátis (acima de ) | C11: 800 | D11: Política comercial — ajustar conforme caixa
B12: CNPJ APP | D12: Razão social: Agro Peças Padrão
B13: WhatsApp comercial | C13: +55 41 98415-1085 | D13: CTA padrão de todos os produtos
B14: Taxa MP efetiva (5% cartão + parcelado 12x 16,82%) | C14: 0.2082 | D14: FONTE ÚNICA da taxa usada no Preço final de TODAS as abas. Decisão 21/07/2026.
B16: Glossario
B17: Campo | C17: Exemplo | D17: Descrição
A18: IDENTIFICAÇÃO | B18: SKU / Código | C18: 5.1302.0565122.0 | D18: Codigo ou SKU da Peça ideal q seja igual de fabrica para ajudar a "Linkar" na nota
B19: Part Number | C19: 565122 | D19: Part Number ou OEM da Peça isso ajuda na aplicacao da peça
B20: Handle (Shopify) | C20: =IFERROR(LOWER(SUBSTITUTE(SUBSTITUTE(SUBSTITUTE(SUBSTITUTE(C21," ","-"),"/","-"),".",""),",","")),"") | D20: Se não souber preencher o Robozinho preenche para subir para o Ecommerce
B21: Title (PT-BR) | C21: BOMBA HIDRÁULICA - APLICAÇÃO MF A-028 (ACX5148180) GIRO I (PROTOTIPO) | D21: Titulo descritivo ideal para ir ao ecomerce (usar catalo ou pesquisa para ter uma melhor nome )
B22: Product Type | C22: Bombas Hidráulicas | D22: Tipo/Categora de produto veriricar os tipos que hoje temos cadastradas no site antes de criar se criar informar para replicar nos sistemas
B23: Vendor (Fabricante) | C23: SOHIPREN | D23: Fabricante
B24: Tags (vírgula) | D24: Indicadores que ajuda na BUSCA ou pesquisa (Ex: "Produto novo 2026", "Promoçao de Natal","Negociacao Fabio")
B25: Status | C25: active | D25: "activo" para subir ao ecommerce -"Draft" Somente castro na planilha não sobe - "Archived" Produdo não vendido mais no ecom (histórico)
A26: APLICAÇÃO TÉCNICA | B26: Montadora compatível | C26: AGCO | D26: Montadora compativo (ex: AGCO, JOHN DEERE, VOLO ) add todoas as marcas separadas por ","
B27: Equipamento / Modelo | C27: TRATOR | D27: Modelo específico do equipamento onde a peça é aplicada (ex: TRATOR, COLHEITADEIRA, CBT 2500 — quanto mais específico melhor para o cliente encontrar)
B28: Função / Aplicação | C28: PRINCIPAL E DIREÇÃO | D28: Sistema ou função que a peça exerce no equipamento (ex: DIREÇÃO, LEVANTE, PRINCIPAL — baseado no catálogo do fabricante)
B29: Códigos cruzados | C29: R979107777/ACW4000800/ACX5148180 | D29: Outros códigos OEM ou referências cruzadas que identificam a mesma peça em outros fabricantes/montadoras — separar por "/" (ex: R979107777/ACW4000800)
A30: LOGÍSTICA E EMBALAGEM | B30: Peso (kg) | C30: 5.75 | D30: Peso bruto real da peça em kg — pesar fisicamente ou consultar fornecedor. Essencial para calcular frete
B31: Comprimento (cm) | C31: 30 | D31: Comprimento (cm) → Maior dimensão da embalagem em centímetros
B32: Largura (cm) | C32: 12.5 | D32: Largura (cm) → Segunda dimensão da embalagem em centímetros
B33: Altura (cm) | C33: 12.5 | D33: Altura (cm) → Terceira dimensão (espessura) da embalagem em centímetros
B34: Peso cubado (kg) | C34: =IFERROR(IF(AND(C31>0,C32>0,C33>0),(C31*C32*C33)/6000,""),"") | D34: Calculado automaticamente: (C × L × A em cm) ÷ 6.000 — fórmula padrão das transportadoras
B35: Peso considerado (kg) | C35: =IFERROR(IF(AND(C30>0,C34>0),MAX(C30,C34),IF(C30>0,C30,IF(C34>0,C34,""))),"") | D35: Calculado automaticamente: MAX(peso real, peso cubado) — é o valor que a transportadora efetivamente cobra
B36: Frete fábrica → eCom () | C36: 100 | D36: Custo de frete do fabricante até o nosso estoque (inbound). Usar 25,00 como estimativa padrão quando não tiver o valor real
B37: Origem do dado embalagem | C37: fornecedor | D37: Indica de onde vieram as dimensões/peso: "fornecedor" = dado oficial, "FALTA" = pendente de preenchimento, "estimado" = valor aproximado por família de produto
A38: CUSTO E PRECIFICAÇÃO | B38: Custo unitário () | C38: 1290 | D38: Preço de compra da peça junto ao fornecedor (sem frete). Base de todo o cálculo de precificação
B39: % Margem de lucro | C39: 0.3 | D39: Percentual de margem desejado para este SKU. Padrão global: 30% — pode ser ajustado por produto conforme concorrência
B40: Custo + frete inbound () | C40: =IFERROR(C38+C36,"") | D40: Calculado: Custo unitário + Frete fábrica → eCom. Representa o custo total de aquisição da peça no estoque
B41: Preço c/ margem () | C41: =IFERROR(IF(C39<1,C40/(1-C39),""),"") | D41: Calculado: (Custo + frete) ÷ (1 − % margem). Preço mínimo antes de aplicar taxa do Mercado Pago
B42: Taxa Mercado Pago (%) | C42: ='01_CONFIG_GLOBAL'!$C$4 | D42: Taxa do Mercado Pago (cartao , debito ) Para pix é de 0,05 para fins de calculo usar sempre o maior Valor
B43: Taxa MP () | C43: =IFERROR(C41*C42,"") | D43: Calculado: Preço c/ margem × Taxa MP (%). Valor em reais que o Mercado Pago desconta por transação
B44: Preço final site () | C44: =IFERROR(IF(C42<1,C41/(1-C42),""),"") | D44: Calculado: Preço c/ margem ÷ (1 − Taxa MP%). Preço de venda final que o cliente vê no e-commerce, já absorvendo todas as taxas
A45: PESQUISA DE MERCADO | B45: Concorrente 1 — Nome | D45: Concorrente 1 / 2 / 3 — Nome → Nome do concorrente pesquisado (ex: Mercado Livre Vendedor X, Site OEM, Agriparts). Registrar para rastreabilidade da pesquisa
B46: Concorrente 1 — Preço () | D46: Concorrente 1 / 2 / 3 — Preço () → Preço encontrado nesse concorrente. Preencher também na aba 09_PESQUISA_MERCADO com link/print para referência
B47: Concorrente 2 — Nome
B48: Concorrente 2 — Preço ()
B49: Concorrente 3 — Nome
B50: Concorrente 3 — Preço ()
B51: Preço médio concorrência () | C51: =IFERROR(AVERAGE(C46,C48,C50),"") | D51: Preço médio concorrência () → Calculado automaticamente: média dos preços dos concorrentes preenchidos. Referência para posicionamento
B52: Posicionamento | C52: =IFERROR(IF(C51="","sem dados",IF(C44<C51*0.95,"abaixo",IF(C44>C51*1.05,"acima","em linha"))),"") | D52: Calculado: compara nosso Preço final site vs média da concorrência. Resultado: "abaixo" (oportunidade — fundo verde), "acima" (revisar margem — fundo vermelho) ou "sem dados" (pesquisa pendente)
A53: WORKFLOW | B53: Cadastrado Shopify? | C53: sim | D53: Preencher "sim", "não" ou "divergente". "Divergente" = SKU existe no Shopify mas com dados diferentes da planilha — priorizar correção
B54: Última atualização | D54: Data da última alteração nesta linha (formato DD/MM/AAAA). Atualizar sempre que editar custo, preço ou dados de embalagem
B55: Operador responsável | D55: Nome ou iniciais de quem preencheu ou atualizou o SKU por último. Facilita rastreabilidade e cobrança de pendências
B56: Observações | D56: Campo livre para notas relevantes: caminho de fotos (assets/...), substituições de código, pendências específicas, instruções para o agente Claude Code/MCP

Sheet 02_SOHIPREN
A1: APP — Agro Peças Padrão | Master 02_SOHIPREN
A2: Total de SKUs: | B2: =COUNTA(A6:A100002) | D2: Faltando embalagem: | E2: =COUNTIF(U6:U100002,"FALTA") | G2: Cadastrados Shopify: | H2: =COUNTIF(AK6:AK100002,"sim") | J2: Divergentes: | K2: =COUNTIF(AK6:AK100002,"divergente")
A4: IDENTIFICAÇÃO | I4: APLICAÇÃO TÉCNICA | N4: LOGÍSTICA E EMBALAGEM | V4: CUSTO E PRECIFICAÇÃO | AC4: PESQUISA DE MERCADO | AK4: WORKFLOW | AO4: Campos Adicionais
A5: SKU / Código | B5: Part Number | C5: Handle (Shopify) | D5: Title (PT-BR) | E5: Product Type | F5: Vendor (Fabricante) | G5: Tags (vírgula) | H5: Status | I5: Montadora compatível | J5: Equipamento / Modelo | K5: Função / Aplicação | L5: Códigos cruzados | M5: Lead Time | N5: Peso (kg) | O5: Comprimento (cm) | P5: Largura (cm) | Q5: Altura (cm) | R5: Peso cubado (kg) | S5: Peso considerado (kg) | T5: Frete fábrica → eCom () | U5: Origem do dado embalagem | V5: Custo unitário () | W5: % Margem de lucro | X5: Custo + frete inbound () | Y5: Preço c/ margem () | Z5: Taxa Mercado Pago (%) | AA5: Taxa MP () | AB5: Preço final site () | AC5: Concorrente 1 — Nome | AD5: Concorrente 1 — Preço () | AE5: Concorrente 2 — Nome | AF5: Concorrente 2 — Preço () | AG5: Concorrente 3 — Nome | AH5: Concorrente 3 — Preço () | AI5: Preço médio concorrência () | AJ5: Posicionamento | AK5: Cadastrado Shopify? | AL5: Última atualização | AM5: Operador responsável | AN5: Observações | AO5: SKU Shopify (derivado) | AP5: Título Shopify (derivado) | AQ5: Imagens site (assets)
A6: 5.0202.0540008.0 | B6: 540008 | C6: =IFERROR(LOWER(SUBSTITUTE(SUBSTITUTE(SUBSTITUTE(SUBSTITUTE(D6," ","-"),"/","-"),".",""),",","")),"") | D6: BOMBA HIDRÁULICA - APLICAÇÃO 4 B1.P1.A.L | E6: Bombas Hidráulicas | F6: SOHIPREN | H6: draft | I6: BERTHOUD | J6: CANHÇAO DE PULVERIZAÇÃO | K6: PRINCIPAL | R6: =IFERROR(IF(AND(O6>0,P6>0,Q6>0),(O6*P6*Q6)/6000,""),"") | S6: =IFERROR(IF(AND(N6>0,R6>0),MAX(N6,R6),IF(N6>0,N6,IF(R6>0,R6,""))),"") | U6: FALTA | V6: 517 | W6: 0.3 | X6: =IFERROR(V6+T6,"") | Y6: =IFERROR(IF(W6<1,X6/(1-W6),""),"") | Z6: ='01_CONFIG_GLOBAL'!$C$14 | AA6: =IFERROR(Y6*Z6,"") | AB6: =IFERROR(IF(Z6<1,Y6/(1-Z6),""),"") | AI6: =IFERROR(AVERAGE(AD6,AF6,AH6),"") | AJ6: =IFERROR(IF(AI6="","sem dados",IF(AB6<AI6*0.95,"abaixo",IF(AB6>AI6*1.05,"acima","em linha"))),"") | AK6: não | AO6: =A6 | AP6: =D6
A7: 5.1621.0620002.0 | C7: =IFERROR(LOWER(SUBSTITUTE(SUBSTITUTE(SUBSTITUTE(SUBSTITUTE(D7," ","-"),"/","-"),".",""),",","")),"") | D7: BPBS2-100-A12-Y4 | F7: SOHIPREN | H7: draft | I7: CBT - COMPANHIA BRASILEIRA DE TRATORES | J7: TRATOR | K7: HIDROSTÁTICO | L7: 2100802053 | R7: =IFERROR(IF(AND(O7>0,P7>0,Q7>0),(O7*P7*Q7)/6000,""),"") | S7: =IFERROR(IF(AND(N7>0,R7>0),MAX(N7,R7),IF(N7>0,N7,IF(R7>0,R7,""))),"") | U7: FALTA | V7: 826.55 | W7: 0.3 | X7: =IFERROR(V7+T7,"") | Y7: =IFERROR(IF(W7<1,X7/(1-W7),""),"") | Z7: ='01_CONFIG_GLOBAL'!$C$14 | AA7: =IFERROR(Y7*Z7,"") | AB7: =IFERROR(IF(Z7<1,Y7/(1-Z7),""),"") | AI7: =IFERROR(AVERAGE(AD7,AF7,AH7),"") | AJ7: =IFERROR(IF(AI7="","sem dados",IF(AB7<AI7*0.95,"abaixo",IF(AB7>AI7*1.05,"acima","em linha"))),"") | AK7: não | AO7: =A7 | AP7: =D7
A8: 5.0207.0544003.0 | B8: 544003 | C8: =IFERROR(LOWER(SUBSTITUTE(SUBSTITUTE(SUBSTITUTE(SUBSTITUTE(D8," ","-"),"/","-"),".",""),",","")),"") | D8: BOMBA HIDRÁULICA - APLICAÇÃO 14 C5.C4.B1.C5 12-100 BAR | E8: Bombas Hidráulicas | F8: SOHIPREN | H8: draft | I8: CBT - COMPANHIA BRASILEIRA DE TRATORES | J8: CBT 2500 - 8260 PERKINS - ZF | K8: DIREÇÃO | L8: 7673955928 | R8: =IFERROR(IF(AND(O8>0,P8>0,Q8>0),(O8*P8*Q8)/6000,""),"") | S8: =IFERROR(IF(AND(N8>0,R8>0),MAX(N8,R8),IF(N8>0,N8,IF(R8>0,R8,""))),"") | U8: FALTA | V8: 427.9 | W8: 0.3 | X8: =IFERROR(V8+T8,"") | Y8: =IFERROR(IF(W8<1,X8/(1-W8),""),"") | Z8: ='01_CONFIG_GLOBAL'!$C$14 | AA8: =IFERROR(Y8*Z8,"") | AB8: =IFERROR(IF(Z8<1,Y8/(1-Z8),""),"") | AI8: =IFERROR(AVERAGE(AD8,AF8,AH8),"") | AJ8: =IFERROR(IF(AI8="","sem dados",IF(AB8<AI8*0.95,"abaixo",IF(AB8>AI8*1.05,"acima","em linha"))),"") | AK8: não | AO8: =A8 | AP8: =D8
A9: 5.0207.0544001.0 | B9: 544001 | C9: =IFERROR(LOWER(SUBSTITUTE(SUBSTITUTE(SUBSTITUTE(SUBSTITUTE(D9," ","-"),"/","-"),".",""),",","")),"") | D9: BOD 14 C5.C4.B1.C5 12-100 BAR | E9: Bombas Hidráulicas | F9: SOHIPREN | H9: draft | I9: CBT - COMPANHIA BRASILEIRA DE TRATORES | J9: CBT 2500 - 8260 MERCEDEZ -ZF | K9: DIREÇÃO | L9: 7673955928 | R9: =IFERROR(IF(AND(O9>0,P9>0,Q9>0),(O9*P9*Q9)/6000,""),"") | S9: =IFERROR(IF(AND(N9>0,R9>0),MAX(N9,R9),IF(N9>0,N9,IF(R9>0,R9,""))),"") | U9: FALTA | V9: 665 | W9: 0.3 | X9: =IFERROR(V9+T9,"") | Y9: =IFERROR(IF(W9<1,X9/(1-W9),""),"") | Z9: ='01_CONFIG_GLOBAL'!$C$14 | AA9: =IFERROR(Y9*Z9,"") | AB9: =IFERROR(IF(Z9<1,Y9/(1-Z9),""),"") | AI9: =IFERROR(AVERAGE(AD9,AF9,AH9),"") | AJ9: =IFERROR(IF(AI9="","sem dados",IF(AB9<AI9*0.95,"abaixo",IF(AB9>AI9*1.05,"acima","em linha"))),"") | AK9: não | AO9: =A9 | AP9: =D9
A10: 5.0208.0544811.0 | B10: 544811 | C10: =IFERROR(LOWER(SUBSTITUTE(SUBSTITUTE(SUBSTITUTE(SUBSTITUTE(D10," ","-"),"/","-"),".",""),",","")),"") | D10: BOMBA HIDRÁULICA - APLICAÇÃO 16 F4.A2.A42.L | E10: Bombas Hidráulicas | F10: SOHIPREN | H10: draft | I10: CBT - COMPANHIA BRASILEIRA DE TRATORES | J10: TRATOR DE PNEUS | K10: LEVANTE 3 PONTO | L10: 103345-90-9510080608-99061002-90611257-11111016014 | R10: =IFERROR(IF(AND(O10>0,P10>0,Q10>0),(O10*P10*Q10)/6000,""),"") | S10: =IFERROR(IF(AND(N10>0,R10>0),MAX(N10,R10),IF(N10>0,N10,IF(R10>0,R10,""))),"") | U10: FALTA | V10: 786.5 | W10: 0.3 | X10: =IFERROR(V10+T10,"") | Y10: =IFERROR(IF(W10<1,X10/(1-W10),""),"") | Z10: ='01_CONFIG_GLOBAL'!$C$14 | AA10: =IFERROR(Y10*Z10,"") | AB10: =IFERROR(IF(Z10<1,Y10/(1-Z10),""),"") | AI10: =IFERROR(AVERAGE(AD10,AF10,AH10),"") | AJ10: =IFERROR(IF(AI10="","sem dados",IF(AB10<AI10*0.95,"abaixo",IF(AB10>AI10*1.05,"acima","em linha"))),"") | AK10: não | AO10: =A10 | AP10: =D10
A11: 5.0205.0542421.0 | B11: 542421 | C11: =IFERROR(LOWER(SUBSTITUTE(SUBSTITUTE(SUBSTITUTE(SUBSTITUTE(D11," ","-"),"/","-"),".",""),",","")),"") | D11: BOD 8 F4.A2.A.L | E11: Bombas Hidráulicas | F11: SOHIPREN | H11: draft | I11: DYNAPAC | J11: COMPACTADOR | K11: DIREÇÃO | L11: 300480606-9510080403-11101008011-9906003-41082905 | R11: =IFERROR(IF(AND(O11>0,P11>0,Q11>0),(O11*P11*Q11)/6000,""),"") | S11: =IFERROR(IF(AND(N11>0,R11>0),MAX(N11,R11),IF(N11>0,N11,IF(R11>0,R11,""))),"") | U11: FALTA | V11: 605 | W11: 0.3 | X11: =IFERROR(V11+T11,"") | Y11: =IFERROR(IF(W11<1,X11/(1-W11),""),"") | Z11: ='01_CONFIG_GLOBAL'!$C$14 | AA11: =IFERROR(Y11*Z11,"") | AB11: =IFERROR(IF(Z11<1,Y11/(1-Z11),""),"") | AI11: =IFERROR(AVERAGE(AD11,AF11,AH11),"") | AJ11: =IFERROR(IF(AI11="","sem dados",IF(AB11<AI11*0.95,"abaixo",IF(AB11>AI11*1.05,"acima","em linha"))),"") | AK11: não | AO11: =A11 | AP11: =D11
A12: 5.0906.0580532.0 | B12: 580532 | C12: =IFERROR(LOWER(SUBSTITUTE(SUBSTITUTE(SUBSTITUTE(SUBSTITUTE(D12," ","-"),"/","-"),".",""),",","")),"") | D12: APR 50 201.1.37.83 | F12: SOHIPREN | H12: draft | I12: FORD | J12: PÁ COM RETRO ESCAVADEIRA | | K12: PRINCIPAL | L12: VB-300 | R12: =IFERROR(IF(AND(O12>0,P12>0,Q12>0),(O12*P12*Q12)/6000,""),"") | S12: =IFERROR(IF(AND(N12>0,R12>0),MAX(N12,R12),IF(N12>0,N12,IF(R12>0,R12,""))),"") | U12: FALTA | V12: 1018.22 | W12: 0.3 | X12: =IFERROR(V12+T12,"") | Y12: =IFERROR(IF(W12<1,X12/(1-W12),""),"") | Z12: ='01_CONFIG_GLOBAL'!$C$14 | AA12: =IFERROR(Y12*Z12,"") | AB12: =IFERROR(IF(Z12<1,Y12/(1-Z12),""),"") | AI12: =IFERROR(AVERAGE(AD12,AF12,AH12),"") | AJ12: =IFERROR(IF(AI12="","sem dados",IF(AB12<AI12*0.95,"abaixo",IF(AB12>AI12*1.05,"acima","em linha"))),"") | AK12: não | AO12: =A12 | AP12: =D12
A13: 5.1621.0680005.0 | B13: 680005 | C13: =IFERROR(LOWER(SUBSTITUTE(SUBSTITUTE(SUBSTITUTE(SUBSTITUTE(D13," ","-"),"/","-"),".",""),",","")),"") | D13: Motor Hidráulico MLR 160 - Plantadeira AGCO (C3.C2.P5) | E13: MOTOR | F13: SOHIPREN | H13: active | I13: AGCO | J13: PLANTANDEIRA | L13: ACX3995300 | N13: 6.2 | O13: 30 | P13: 12.5 | Q13: 12.5 | R13: =IFERROR(IF(AND(O13>0,P13>0,Q13>0),(O13*P13*Q13)/6000,""),"") | S13: =IFERROR(IF(AND(N13>0,R13>0),MAX(N13,R13),IF(N13>0,N13,IF(R13>0,R13,""))),"") | T13: 100 | U13: fornecedor | V13: 767.55 | W13: 0.2 | X13: =IFERROR(V13+T13,"") | Y13: =IFERROR(IF(W13<1,X13/(1-W13),""),"") | Z13: ='01_CONFIG_GLOBAL'!$C$14 | AA13: =IFERROR(Y13*Z13,"") | AB13: =IFERROR(IF(Z13<1,Y13/(1-Z13),""),"") | AI13: =IFERROR(AVERAGE(AD13,AF13,AH13),"") | AJ13: =IFERROR(IF(AI13="","sem dados",IF(AB13<AI13*0.95,"abaixo",IF(AB13>AI13*1.05,"acima","em linha"))),"") | AK13: sim | AO13: =A13 | AP13: =D13 | AQ13: SEM IMAGEM
A14: 5.1302.0565122.0 | B14: 565122 | C14: =IFERROR(LOWER(SUBSTITUTE(SUBSTITUTE(SUBSTITUTE(SUBSTITUTE(D14," ","-"),"/","-"),".",""),",","")),"") | D14: Bomba de Aplicação Massey Ferguson A-028 (ACX5148180) Giro I - 5.1302.0565122.0 | E14: Bombas Hidráulicas | F14: SOHIPREN | H14: active | I14: AGCO | J14: TRATOR | K14: PRINCIPAL E DIREÇÃO | L14: R979107777/ACW4000800/ACX5148180 | N14: 5.75 | O14: 30 | P14: 12.5 | Q14: 12.5 | R14: =IFERROR(IF(AND(O14>0,P14>0,Q14>0),(O14*P14*Q14)/6000,""),"") | S14: =IFERROR(IF(AND(N14>0,R14>0),MAX(N14,R14),IF(N14>0,N14,IF(R14>0,R14,""))),"") | T14: 100 | U14: fornecedor | V14: 1096.5 | W14: 0.2 | X14: =IFERROR(V14+T14,"") | Y14: =IFERROR(IF(W14<1,X14/(1-W14),""),"") | Z14: ='01_CONFIG_GLOBAL'!$C$14 | AA14: =IFERROR(Y14*Z14,"") | AB14: =IFERROR(IF(Z14<1,Y14/(1-Z14),""),"") | AI14: =IFERROR(AVERAGE(AD14,AF14,AH14),"") | AJ14: =IFERROR(IF(AI14="","sem dados",IF(AB14<AI14*0.95,"abaixo",IF(AB14>AI14*1.05,"acima","em linha"))),"") | AK14: sim | AO14: =A14 | AP14: =D14 | AQ14: bomba_generica.png (genérica)
A15: 5.1302.0565120.0 | B15: 565120 | C15: =IFERROR(LOWER(SUBSTITUTE(SUBSTITUTE(SUBSTITUTE(SUBSTITUTE(D15," ","-"),"/","-"),".",""),",","")),"") | D15: Motor de Aplicação Massey Ferguson A-026 (ACX4630870) Giro D - 5.1302.0565120.0 | E15: MOTOR | F15: SOHIPREN | H15: active | I15: AGCO | J15: PLANTADEIRA | K15: MOTOR DA TURNINA | L15: ACX4630870 SUBISTITUI ACW9357690 | N15: 5.98 | O15: 30 | P15: 12.5 | Q15: 12.5 | R15: =IFERROR(IF(AND(O15>0,P15>0,Q15>0),(O15*P15*Q15)/6000,""),"") | S15: =IFERROR(IF(AND(N15>0,R15>0),MAX(N15,R15),IF(N15>0,N15,IF(R15>0,R15,""))),"") | T15: 100 | U15: fornecedor | V15: 1147.5 | W15: 0.2 | X15: =IFERROR(V15+T15,"") | Y15: =IFERROR(IF(W15<1,X15/(1-W15),""),"") | Z15: ='01_CONFIG_GLOBAL'!$C$14 | AA15: =IFERROR(Y15*Z15,"") | AB15: =IFERROR(IF(Z15<1,Y15/(1-Z15),""),"") | AI15: =IFERROR(AVERAGE(AD15,AF15,AH15),"") | AJ15: =IFERROR(IF(AI15="","sem dados",IF(AB15<AI15*0.95,"abaixo",IF(AB15>AI15*1.05,"acima","em linha"))),"") | AK15: sim | AO15: =A15 | AP15: =D15 | AQ15: SEM IMAGEM
A16: 5.0208.L025883.0 | B16: L025883 | C16: =IFERROR(LOWER(SUBSTITUTE(SUBSTITUTE(SUBSTITUTE(SUBSTITUTE(D16," ","-"),"/","-"),".",""),",","")),"") | D16: BOMBA HIDRÁULICA - APLICAÇÃO 16 E18.C.A.L | E16: Bombas Hidráulicas | F16: SOHIPREN | H16: draft | I16: AGCO | J16: TRATOR | L16: 86664800/0510625329 | R16: =IFERROR(IF(AND(O16>0,P16>0,Q16>0),(O16*P16*Q16)/6000,""),"") | S16: =IFERROR(IF(AND(N16>0,R16>0),MAX(N16,R16),IF(N16>0,N16,IF(R16>0,R16,""))),"") | U16: FALTA | V16: 665 | W16: 0.3 | X16: =IFERROR(V16+T16,"") | Y16: =IFERROR(IF(W16<1,X16/(1-W16),""),"") | Z16: ='01_CONFIG_GLOBAL'!$C$14 | AA16: =IFERROR(Y16*Z16,"") | AB16: =IFERROR(IF(Z16<1,Y16/(1-Z16),""),"") | AI16: =IFERROR(AVERAGE(AD16,AF16,AH16),"") | AJ16: =IFERROR(IF(AI16="","sem dados",IF(AB16<AI16*0.95,"abaixo",IF(AB16>AI16*1.05,"acima","em linha"))),"") | AK16: não | AO16: =A16 | AP16: =D16
A17: 5.0220.0548836.0 | B17: 548836 | C17: =IFERROR(LOWER(SUBSTITUTE(SUBSTITUTE(SUBSTITUTE(SUBSTITUTE(D17," ","-"),"/","-"),".",""),",","")),"") | D17: Bomba de Direção Massey Ferguson 194-4F/362/365/372/390 | E17: Bombas Hidráulicas | F17: SOHIPREN | H17: active | I17: AGCO - MASSEY FERGUNSON | J17: TRATOR | K17: DIREÇÃO E AUXILIAR | L17: 3774612/3701005/6214827/3597692/3595202/3597706/F800510536 - 42603990020 | N17: 5.33 | O17: 30 | P17: 12.5 | Q17: 12.5 | R17: =IFERROR(IF(AND(O17>0,P17>0,Q17>0),(O17*P17*Q17)/6000,""),"") | S17: =IFERROR(IF(AND(N17>0,R17>0),MAX(N17,R17),IF(N17>0,N17,IF(R17>0,R17,""))),"") | T17: 100 | U17: fornecedor | V17: 1207 | W17: 0.2 | X17: =IFERROR(V17+T17,"") | Y17: =IFERROR(IF(W17<1,X17/(1-W17),""),"") | Z17: ='01_CONFIG_GLOBAL'!$C$14 | AA17: =IFERROR(Y17*Z17,"") | AB17: =IFERROR(IF(Z17<1,Y17/(1-Z17),""),"") | AI17: =IFERROR(AVERAGE(AD17,AF17,AH17),"") | AJ17: =IFERROR(IF(AI17="","sem dados",IF(AB17<AI17*0.95,"abaixo",IF(AB17>AI17*1.05,"acima","em linha"))),"") | AK17: sim | AN17: Fotos: assets/livenza_5.0220.0548836-CT_REV._0_p1.png | AO17: =A17 | AP17: =D17 | AQ17: 0012_548836_Livenza_5_0220_0548836-CT_0_att101_p1_foto_3d_ecommerce.png | 0012_548836_Livenza_5_0220_0548836-CT_0_att101_p1_desenho_tec.png | livenza_5.0220.0548836-CT_REV._0_p1.png
A18: 5.0220.0548817.0 | B18: 548817 | C18: =IFERROR(LOWER(SUBSTITUTE(SUBSTITUTE(SUBSTITUTE(SUBSTITUTE(D18," ","-"),"/","-"),".",""),",","")),"") | D18: Bomba Hidráulica Massey Ferguson 283/290/292/L5000 - Direção e Levante | E18: Bombas Hidráulicas | F18: SOHIPREN | H18: active | I18: AGCO - MASSEY FERGUNSON | J18: TRATOR | K18: DIREÇÃO E LEVANTE | L18: 052107T1 | N18: 5.69 | O18: 30 | P18: 12.5 | Q18: 12.5 | R18: =IFERROR(IF(AND(O18>0,P18>0,Q18>0),(O18*P18*Q18)/6000,""),"") | S18: =IFERROR(IF(AND(N18>0,R18>0),MAX(N18,R18),IF(N18>0,N18,IF(R18>0,R18,""))),"") | T18: 100 | U18: fornecedor | V18: 913.75 | W18: 0.2 | X18: =IFERROR(V18+T18,"") | Y18: =IFERROR(IF(W18<1,X18/(1-W18),""),"") | Z18: ='01_CONFIG_GLOBAL'!$C$14 | AA18: =IFERROR(Y18*Z18,"") | AB18: =IFERROR(IF(Z18<1,Y18/(1-Z18),""),"") | AI18: =IFERROR(AVERAGE(AD18,AF18,AH18),"") | AJ18: =IFERROR(IF(AI18="","sem dados",IF(AB18<AI18*0.95,"abaixo",IF(AB18>AI18*1.05,"acima","em linha"))),"") | AK18: sim | AO18: =A18 | AP18: =D18 | AQ18: LIVENZA_5.0220.0548817_ecommerce.jpg
A19: 5.1302.0565053.0 | B19: 565053 | C19: =IFERROR(LOWER(SUBSTITUTE(SUBSTITUTE(SUBSTITUTE(SUBSTITUTE(D19," ","-"),"/","-"),".",""),",","")),"") | D19: Bomba Hidráulica Massey Ferguson MF A-016 - Trator 4299 | E19: Bombas Hidráulicas | F19: SOHIPREN | H19: active | I19: AGCO - MASSEY FERGUNSON | J19: TRATOR DE PNEUS | K19: PRINCIPAL - 22,5+11 | L19: 6262009 - R979017550 - 11112022040 - 9033102550 | N19: 9.33 | O19: 30 | P19: 12.5 | Q19: 12.5 | R19: =IFERROR(IF(AND(O19>0,P19>0,Q19>0),(O19*P19*Q19)/6000,""),"") | S19: =IFERROR(IF(AND(N19>0,R19>0),MAX(N19,R19),IF(N19>0,N19,IF(R19>0,R19,""))),"") | T19: 100 | U19: fornecedor | V19: 1632 | W19: 0.2 | X19: =IFERROR(V19+T19,"") | Y19: =IFERROR(IF(W19<1,X19/(1-W19),""),"") | Z19: ='01_CONFIG_GLOBAL'!$C$14 | AA19: =IFERROR(Y19*Z19,"") | AB19: =IFERROR(IF(Z19<1,Y19/(1-Z19),""),"") | AI19: =IFERROR(AVERAGE(AD19,AF19,AH19),"") | AJ19: =IFERROR(IF(AI19="","sem dados",IF(AB19<AI19*0.95,"abaixo",IF(AB19>AI19*1.05,"acima","em linha"))),"") | AK19: sim | AN19: Fotos: assets/livenza_5.1302.0565053-1_p1.png | AO19: =A19 | AP19: =D19 | AQ19: 0014_565053_Livenza_5_1302_0565053_att143_p1_foto_3d_ecommerce.png | 0014_565053_Livenza_5_1302_0565053_att143_p1_desenho_tec.png
A20: 5.0239.L012800.0 | B20: L012800 | C20: =IFERROR(LOWER(SUBSTITUTE(SUBSTITUTE(SUBSTITUTE(SUBSTITUTE(D20," ","-"),"/","-"),".",""),",","")),"") | D20: KIT.BO.22,5.E2TD.B20 | F20: SOHIPREN | H20: draft | I20: AGCO - MASSEY FERGUSON | J20: TRATOR | K20: BX200 - 4292 - 4297 - 4299 | L20: R979017553 | R20: =IFERROR(IF(AND(O20>0,P20>0,Q20>0),(O20*P20*Q20)/6000,""),"") | S20: =IFERROR(IF(AND(N20>0,R20>0),MAX(N20,R20),IF(N20>0,N20,IF(R20>0,R20,""))),"") | U20: FALTA | V20: 396 | W20: 0.3 | X20: =IFERROR(V20+T20,"") | Y20: =IFERROR(IF(W20<1,X20/(1-W20),""),"") | Z20: ='01_CONFIG_GLOBAL'!$C$14 | AA20: =IFERROR(Y20*Z20,"") | AB20: =IFERROR(IF(Z20<1,Y20/(1-Z20),""),"") | AI20: =IFERROR(AVERAGE(AD20,AF20,AH20),"") | AJ20: =IFERROR(IF(AI20="","sem dados",IF(AB20<AI20*0.95,"abaixo",IF(AB20>AI20*1.05,"acima","em linha"))),"") | AK20: não | AO20: =A20 | AP20: =D20
A21: 5.0220.0548851.0 | B21: 548851 | C21: =IFERROR(LOWER(SUBSTITUTE(SUBSTITUTE(SUBSTITUTE(SUBSTITUTE(D21," ","-"),"/","-"),".",""),",","")),"") | D21: BOMBA HIDRÁULICA - APLICAÇÃO 16 E5.P.A42/14 A42.L1 (PLACA H15) | E21: Bombas Hidráulicas | F21: SOHIPREN | H21: draft | I21: AGCO - VALTRA | J21: TRATOR | K21: PRINCIPAL | L21: 83410200-9510080642 | R21: =IFERROR(IF(AND(O21>0,P21>0,Q21>0),(O21*P21*Q21)/6000,""),"") | S21: =IFERROR(IF(AND(N21>0,R21>0),MAX(N21,R21),IF(N21>0,N21,IF(R21>0,R21,""))),"") | U21: FALTA | V21: 1317 | W21: 0.3 | X21: =IFERROR(V21+T21,"") | Y21: =IFERROR(IF(W21<1,X21/(1-W21),""),"") | Z21: ='01_CONFIG_GLOBAL'!$C$14 | AA21: =IFERROR(Y21*Z21,"") | AB21: =IFERROR(IF(Z21<1,Y21/(1-Z21),""),"") | AI21: =IFERROR(AVERAGE(AD21,AF21,AH21),"") | AJ21: =IFERROR(IF(AI21="","sem dados",IF(AB21<AI21*0.95,"abaixo",IF(AB21>AI21*1.05,"acima","em linha"))),"") | AK21: não | AO21: =A21 | AP21: =D21
A22: 5.0220.0548824-2 | B22: 548824 | C22: =IFERROR(LOWER(SUBSTITUTE(SUBSTITUTE(SUBSTITUTE(SUBSTITUTE(D22," ","-"),"/","-"),".",""),",","")),"") | D22: Bomba Hidráulica Dupla Valtra-Valmet BH160 | E22: Bombas Hidráulicas | F22: SOHIPREN | H22: active | I22: AGCO - VALTRA | J22: TRATOR | K22: PRINCIPAL | L22: 836659742-836640234-9510080758-R979106433-81341100 | N22: 7.97 | O22: 30 | P22: 12.5 | Q22: 12.5 | R22: =IFERROR(IF(AND(O22>0,P22>0,Q22>0),(O22*P22*Q22)/6000,""),"") | S22: =IFERROR(IF(AND(N22>0,R22>0),MAX(N22,R22),IF(N22>0,N22,IF(R22>0,R22,""))),"") | T22: 100 | U22: fornecedor | V22: 1130.5 | W22: 0.2 | X22: =IFERROR(V22+T22,"") | Y22: =IFERROR(IF(W22<1,X22/(1-W22),""),"") | Z22: ='01_CONFIG_GLOBAL'!$C$14 | AA22: =IFERROR(Y22*Z22,"") | AB22: =IFERROR(IF(Z22<1,Y22/(1-Z22),""),"") | AI22: =IFERROR(AVERAGE(AD22,AF22,AH22),"") | AJ22: =IFERROR(IF(AI22="","sem dados",IF(AB22<AI22*0.95,"abaixo",IF(AB22>AI22*1.05,"acima","em linha"))),"") | AK22: sim | AN22: Fotos: assets/livenza_5.0220.0548824-2_p1.png | AO22: =A22 | AP22: =D22 | AQ22: 0017_548824_Livenza_5_0220_0548951-CT_REV__0_att135_p1_foto_3d_ecommerce.png | 0017_548824_Livenza_5_0220_0548951-CT_REV__0_att135_p1_desenho_tec.png | 5.0220.0548824-2_p1.png
A23: 5.0220.0548917.0 | B23: 548917 | C23: =IFERROR(LOWER(SUBSTITUTE(SUBSTITUTE(SUBSTITUTE(SUBSTITUTE(D23," ","-"),"/","-"),".",""),",","")),"") | D23: Bomba Hidráulica 16 Principal e Direção - Trator Valtra (E2.B8.B2/14, Placa H15) | E23: Bombas Hidráulicas | F23: SOHIPREN | H23: active | I23: AGCO - VALTRA | J23: TRATOR | K23: PRINCIPAL E DIREÇAO | L23: 31851700/9510080542/F000510609 | M23: 10 dias úteis | N23: 7.65 | O23: 30 | P23: 12.5 | Q23: 12.5 | R23: =IFERROR(IF(AND(O23>0,P23>0,Q23>0),(O23*P23*Q23)/6000,""),"") | S23: =IFERROR(IF(AND(N23>0,R23>0),MAX(N23,R23),IF(N23>0,N23,IF(R23>0,R23,""))),"") | T23: 100 | U23: fornecedor | V23: 1130.5 | W23: 0.2 | X23: =IFERROR(V23+T23,"") | Y23: =IFERROR(IF(W23<1,X23/(1-W23),""),"") | Z23: ='01_CONFIG_GLOBAL'!$C$14 | AA23: =IFERROR(Y23*Z23,"") | AB23: =IFERROR(IF(Z23<1,Y23/(1-Z23),""),"") | AI23: =IFERROR(AVERAGE(AD23,AF23,AH23),"") | AJ23: =IFERROR(IF(AI23="","sem dados",IF(AB23<AI23*0.95,"abaixo",IF(AB23>AI23*1.05,"acima","em linha"))),"") | AK23: sim | AO23: =A23 | AP23: =D23 | AQ23: bomba_generica.png (genérica)
A24: 5.0220.L026997.0 | B24: L026997 | C24: =IFERROR(LOWER(SUBSTITUTE(SUBSTITUTE(SUBSTITUTE(SUBSTITUTE(D24," ","-"),"/","-"),".",""),",","")),"") | D24: Bomba Hidráulica 22,5 Principal - Trator Valtra (E2.B8.B112/16.B4/16) | E24: Bombas Hidráulicas | F24: SOHIPREN | H24: active | I24: AGCO - VALTRA | J24: TRATORES | K24: PRINCIPAL | L24: R979003762 - 11113022004 - 84068400 | N24: 9.89 | O24: 35 | P24: 31 | Q24: 20 | R24: =IFERROR(IF(AND(O24>0,P24>0,Q24>0),(O24*P24*Q24)/6000,""),"") | S24: =IFERROR(IF(AND(N24>0,R24>0),MAX(N24,R24),IF(N24>0,N24,IF(R24>0,R24,""))),"") | T24: 100 | U24: fornecedor | V24: 1759.5 | W24: 0.2 | X24: =IFERROR(V24+T24,"") | Y24: =IFERROR(IF(W24<1,X24/(1-W24),""),"") | Z24: ='01_CONFIG_GLOBAL'!$C$14 | AA24: =IFERROR(Y24*Z24,"") | AB24: =IFERROR(IF(Z24<1,Y24/(1-Z24),""),"") | AI24: =IFERROR(AVERAGE(AD24,AF24,AH24),"") | AJ24: =IFERROR(IF(AI24="","sem dados",IF(AB24<AI24*0.95,"abaixo",IF(AB24>AI24*1.05,"acima","em linha"))),"") | AK24: sim | AO24: =A24 | AP24: =D24 | AQ24: bomba_generica.png (genérica)
A25: 5.0220.0547201.0 | B25: 547201 | C25: =IFERROR(LOWER(SUBSTITUTE(SUBSTITUTE(SUBSTITUTE(SUBSTITUTE(D25," ","-"),"/","-"),".",""),",","")),"") | D25: Bomba Hidráulica Principal Valtra-Valmet 885/985/1280 | E25: Bombas Hidráulicas | F25: SOHIPREN | H25: active | I25: AGCO - VALTRA | J25: TRATOR | K25: PRINCIPAL | L25: 81131100/9510080756 | N25: 8.86 | O25: 30 | P25: 12.5 | Q25: 12.5 | R25: =IFERROR(IF(AND(O25>0,P25>0,Q25>0),(O25*P25*Q25)/6000,""),"") | S25: =IFERROR(IF(AND(N25>0,R25>0),MAX(N25,R25),IF(N25>0,N25,IF(R25>0,R25,""))),"") | T25: 100 | U25: fornecedor | V25: 1130.5 | W25: 0.2 | X25: =IFERROR(V25+T25,"") | Y25: =IFERROR(IF(W25<1,X25/(1-W25),""),"") | Z25: ='01_CONFIG_GLOBAL'!$C$14 | AA25: =IFERROR(Y25*Z25,"") | AB25: =IFERROR(IF(Z25<1,Y25/(1-Z25),""),"") | AI25: =IFERROR(AVERAGE(AD25,AF25,AH25),"") | AJ25: =IFERROR(IF(AI25="","sem dados",IF(AB25<AI25*0.95,"abaixo",IF(AB25>AI25*1.05,"acima","em linha"))),"") | AK25: sim | AN25: Fotos: assets/livenza_5.0220.0547201-CT_REV._0_p1.png | AO25: =A25 | AP25: =D25 | AQ25: 0020_547201_Livenza_5_0220_0547201-CT_0_att84_p1_foto_3d_ecommerce.png | 0020_547201_Livenza_5_0220_0547201-CT_0_att84_p1_desenho_tec.png | livenza_5.0220.0547201-CT_REV._0_p1.png
A26: 5.0220.0547202.0 | B26: 547202 | C26: =IFERROR(LOWER(SUBSTITUTE(SUBSTITUTE(SUBSTITUTE(SUBSTITUTE(D26," ","-"),"/","-"),".",""),",","")),"") | D26: Bomba Hidráulica Valtra-Valmet 62/65/68/85/86/88/78EL - Principal | E26: Bombas Hidráulicas | F26: SOHIPREN | H26: active | I26: AGCO - VALTRA | J26: TRATOR DE PNEUS | K26: PRINCIPAL | L26: 159400-1 | M26: 10 dias úteis | N26: 7.98 | O26: 30 | P26: 12.5 | Q26: 12.5 | R26: =IFERROR(IF(AND(O26>0,P26>0,Q26>0),(O26*P26*Q26)/6000,""),"") | S26: =IFERROR(IF(AND(N26>0,R26>0),MAX(N26,R26),IF(N26>0,N26,IF(R26>0,R26,""))),"") | T26: 100 | U26: fornecedor | V26: 1038.7 | W26: 0.2 | X26: =IFERROR(V26+T26,"") | Y26: =IFERROR(IF(W26<1,X26/(1-W26),""),"") | Z26: ='01_CONFIG_GLOBAL'!$C$14 | AA26: =IFERROR(Y26*Z26,"") | AB26: =IFERROR(IF(Z26<1,Y26/(1-Z26),""),"") | AI26: =IFERROR(AVERAGE(AD26,AF26,AH26),"") | AJ26: =IFERROR(IF(AI26="","sem dados",IF(AB26<AI26*0.95,"abaixo",IF(AB26>AI26*1.05,"acima","em linha"))),"") | AK26: sim | AN26: Fotos: assets/livenza_5.0220.0547202-CT_REV._0_p1.png | AO26: =A26 | AP26: =D26 | AQ26: 0021_547202_Livenza_5_0220_0547202-CT_0_att85_p1_foto_3d_ecommerce.png | 0021_547202_Livenza_5_0220_0547202-CT_0_att85_p1_desenho_tec.png
A27: 5.0220.0547791.0 | B27: 547791 | C27: =IFERROR(LOWER(SUBSTITUTE(SUBSTITUTE(SUBSTITUTE(SUBSTITUTE(D27," ","-"),"/","-"),".",""),",","")),"") | D27: BOMBA HIDRÁULICA - APLICAÇÃO 11 E5.P.A42/14 A42.L (CPO DELANTERO - TRASERO INVERTIDO) | E27: Bombas Hidráulicas | F27: SOHIPREN | H27: draft | I27: AGCO - VALTRA | J27: TARTOR | K27: PRINCIPAL E DIREÇÃO | L27: 83431900-9510080542-2122011002 | R27: =IFERROR(IF(AND(O27>0,P27>0,Q27>0),(O27*P27*Q27)/6000,""),"") | S27: =IFERROR(IF(AND(N27>0,R27>0),MAX(N27,R27),IF(N27>0,N27,IF(R27>0,R27,""))),"") | U27: FALTA | V27: 1034 | W27: 0.3 | X27: =IFERROR(V27+T27,"") | Y27: =IFERROR(IF(W27<1,X27/(1-W27),""),"") | Z27: ='01_CONFIG_GLOBAL'!$C$14 | AA27: =IFERROR(Y27*Z27,"") | AB27: =IFERROR(IF(Z27<1,Y27/(1-Z27),""),"") | AI27: =IFERROR(AVERAGE(AD27,AF27,AH27),"") | AJ27: =IFERROR(IF(AI27="","sem dados",IF(AB27<AI27*0.95,"abaixo",IF(AB27>AI27*1.05,"acima","em linha"))),"") | AK27: não | AO27: =A27 | AP27: =D27
A28: 5.0401.0575023.0 | B28: 575023 | C28: =IFERROR(LOWER(SUBSTITUTE(SUBSTITUTE(SUBSTITUTE(SUBSTITUTE(D28," ","-"),"/","-"),".",""),",","")),"") | D28: BND 22 E4.C3.F2.L | F28: SOHIPREN | H28: draft | I28: AGRALE | J28: TRATOR | K28: PRINCIPAL | L28: R979018701/R979018705 | R28: =IFERROR(IF(AND(O28>0,P28>0,Q28>0),(O28*P28*Q28)/6000,""),"") | S28: =IFERROR(IF(AND(N28>0,R28>0),MAX(N28,R28),IF(N28>0,N28,IF(R28>0,R28,""))),"") | U28: FALTA | V28: 665 | W28: 0.3 | X28: =IFERROR(V28+T28,"") | Y28: =IFERROR(IF(W28<1,X28/(1-W28),""),"") | Z28: ='01_CONFIG_GLOBAL'!$C$14 | AA28: =IFERROR(Y28*Z28,"") | AB28: =IFERROR(IF(Z28<1,Y28/(1-Z28),""),"") | AI28: =IFERROR(AVERAGE(AD28,AF28,AH28),"") | AJ28: =IFERROR(IF(AI28="","sem dados",IF(AB28<AI28*0.95,"abaixo",IF(AB28>AI28*1.05,"acima","em linha"))),"") | AK28: não | AO28: =A28 | AP28: =D28
A29: 5.0208.L025260.0 | B29: L02526 | C29: =IFERROR(LOWER(SUBSTITUTE(SUBSTITUTE(SUBSTITUTE(SUBSTITUTE(D29," ","-"),"/","-"),".",""),",","")),"") | D29: BOD 19 E.C.C3.L | E29: Bombas Hidráulicas | F29: SOHIPREN | H29: draft | I29: AGRALE | J29: TRATOR | K29: PRINCIPAL E DIREÇÃO | L29: 8013108327003-8009108575005-F000510708 | R29: =IFERROR(IF(AND(O29>0,P29>0,Q29>0),(O29*P29*Q29)/6000,""),"") | S29: =IFERROR(IF(AND(N29>0,R29>0),MAX(N29,R29),IF(N29>0,N29,IF(R29>0,R29,""))),"") | U29: FALTA | V29: 626 | W29: 0.3 | X29: =IFERROR(V29+T29,"") | Y29: =IFERROR(IF(W29<1,X29/(1-W29),""),"") | Z29: ='01_CONFIG_GLOBAL'!$C$14 | AA29: =IFERROR(Y29*Z29,"") | AB29: =IFERROR(IF(Z29<1,Y29/(1-Z29),""),"") | AI29: =IFERROR(AVERAGE(AD29,AF29,AH29),"") | AJ29: =IFERROR(IF(AI29="","sem dados",IF(AB29<AI29*0.95,"abaixo",IF(AB29>AI29*1.05,"acima","em linha"))),"") | AK29: não | AO29: =A29 | AP29: =D29
A30: 5.0220.L025261.0 | B30: L025261 | C30: =IFERROR(LOWER(SUBSTITUTE(SUBSTITUTE(SUBSTITUTE(SUBSTITUTE(D30," ","-"),"/","-"),".",""),",","")),"") | D30: BOMBA HIDRÁULICA - APLICAÇÃO 22,5 B1.P6.A/16.A42.L | E30: Bombas Hidráulicas | F30: SOHIPREN | H30: draft | I30: AGRALE | J30: TRATOR | K30: PRINCIPAL E DIREÇÃO | L30: F000510708-8013108327003-8009108575005 | R30: =IFERROR(IF(AND(O30>0,P30>0,Q30>0),(O30*P30*Q30)/6000,""),"") | S30: =IFERROR(IF(AND(N30>0,R30>0),MAX(N30,R30),IF(N30>0,N30,IF(R30>0,R30,""))),"") | U30: FALTA | V30: 1551.28 | W30: 0.3 | X30: =IFERROR(V30+T30,"") | Y30: =IFERROR(IF(W30<1,X30/(1-W30),""),"") | Z30: ='01_CONFIG_GLOBAL'!$C$14 | AA30: =IFERROR(Y30*Z30,"") | AB30: =IFERROR(IF(Z30<1,Y30/(1-Z30),""),"") | AI30: =IFERROR(AVERAGE(AD30,AF30,AH30),"") | AJ30: =IFERROR(IF(AI30="","sem dados",IF(AB30<AI30*0.95,"abaixo",IF(AB30>AI30*1.05,"acima","em linha"))),"") | AK30: não | AO30: =A30 | AP30: =D30
A31: 5.1621.0620001.0 | C31: =IFERROR(LOWER(SUBSTITUTE(SUBSTITUTE(SUBSTITUTE(SUBSTITUTE(D31," ","-"),"/","-"),".",""),",","")),"") | D31: BPB2-100-Y4 | F31: SOHIPREN | H31: draft | I31: AGRALE TRATORES | J31: TRATOR | K31: HIDROSTÁTICA | L31: 8009.1030.2000.7 | R31: =IFERROR(IF(AND(O31>0,P31>0,Q31>0),(O31*P31*Q31)/6000,""),"") | S31: =IFERROR(IF(AND(N31>0,R31>0),MAX(N31,R31),IF(N31>0,N31,IF(R31>0,R31,""))),"") | U31: FALTA | V31: 826.55 | W31: 0.3 | X31: =IFERROR(V31+T31,"") | Y31: =IFERROR(IF(W31<1,X31/(1-W31),""),"") | Z31: ='01_CONFIG_GLOBAL'!$C$14 | AA31: =IFERROR(Y31*Z31,"") | AB31: =IFERROR(IF(Z31<1,Y31/(1-Z31),""),"") | AI31: =IFERROR(AVERAGE(AD31,AF31,AH31),"") | AJ31: =IFERROR(IF(AI31="","sem dados",IF(AB31<AI31*0.95,"abaixo",IF(AB31>AI31*1.05,"acima","em linha"))),"") | AK31: não | AO31: =A31 | AP31: =D31
A32: 5.0220.0547229.0 | B32: 547229 | C32: =IFERROR(LOWER(SUBSTITUTE(SUBSTITUTE(SUBSTITUTE(SUBSTITUTE(D32," ","-"),"/","-"),".",""),",","")),"") | D32: BOMBA HIDRÁULICA - APLICAÇÃO 19 B9.B4.A11/16 A7.D7 18-90 BAR | E32: Bombas Hidráulicas | F32: SOHIPREN | H32: draft | I32: AGRALE TRATORES | J32: TRATOR | K32: PRINCIPAL E DIREÇÃO | R32: =IFERROR(IF(AND(O32>0,P32>0,Q32>0),(O32*P32*Q32)/6000,""),"") | S32: =IFERROR(IF(AND(N32>0,R32>0),MAX(N32,R32),IF(N32>0,N32,IF(R32>0,R32,""))),"") | U32: FALTA | V32: 1615 | W32: 0.3 | X32: =IFERROR(V32+T32,"") | Y32: =IFERROR(IF(W32<1,X32/(1-W32),""),"") | Z32: ='01_CONFIG_GLOBAL'!$C$14 | AA32: =IFERROR(Y32*Z32,"") | AB32: =IFERROR(IF(Z32<1,Y32/(1-Z32),""),"") | AI32: =IFERROR(AVERAGE(AD32,AF32,AH32),"") | AJ32: =IFERROR(IF(AI32="","sem dados",IF(AB32<AI32*0.95,"abaixo",IF(AB32>AI32*1.05,"acima","em linha"))),"") | AK32: não | AO32: =A32 | AP32: =D32
A33: 5.0205.0542404.0 | B33: 542404 | C33: =IFERROR(LOWER(SUBSTITUTE(SUBSTITUTE(SUBSTITUTE(SUBSTITUTE(D33," ","-"),"/","-"),".",""),",","")),"") | D33: BOD 8 B1.B10.A.L | E33: Bombas Hidráulicas | F33: SOHIPREN | H33: draft | I33: AGRALE TRATORES | J33: TRATOR | K33: PRINCIPAL | L33: 8008108132007-9510080401-11101008012-90605002 | R33: =IFERROR(IF(AND(O33>0,P33>0,Q33>0),(O33*P33*Q33)/6000,""),"") | S33: =IFERROR(IF(AND(N33>0,R33>0),MAX(N33,R33),IF(N33>0,N33,IF(R33>0,R33,""))),"") | U33: FALTA | V33: 778 | W33: 0.3 | X33: =IFERROR(V33+T33,"") | Y33: =IFERROR(IF(W33<1,X33/(1-W33),""),"") | Z33: ='01_CONFIG_GLOBAL'!$C$14 | AA33: =IFERROR(Y33*Z33,"") | AB33: =IFERROR(IF(Z33<1,Y33/(1-Z33),""),"") | AI33: =IFERROR(AVERAGE(AD33,AF33,AH33),"") | AJ33: =IFERROR(IF(AI33="","sem dados",IF(AB33<AI33*0.95,"abaixo",IF(AB33>AI33*1.05,"acima","em linha"))),"") | AK33: não | AO33: =A33 | AP33: =D33
A34: 5.0220.0547205.0 | B34: 547205 | C34: =IFERROR(LOWER(SUBSTITUTE(SUBSTITUTE(SUBSTITUTE(SUBSTITUTE(D34," ","-"),"/","-"),".",""),",","")),"") | D34: Bomba Hidráulica Principal Valtra-Valmet 880/980/1780 | E34: Bombas Hidráulicas | F34: SOHIPREN | H34: active | I34: AGRALE TRATORES - VALTRA | J34: TRATOR | K34: PRINCIPAL | L34: 8.008.1080.100.03/801661-10/9510080741/11112022005 | N34: 7.2 | O34: 30 | P34: 12.5 | Q34: 12.5 | R34: =IFERROR(IF(AND(O34>0,P34>0,Q34>0),(O34*P34*Q34)/6000,""),"") | S34: =IFERROR(IF(AND(N34>0,R34>0),MAX(N34,R34),IF(N34>0,N34,IF(R34>0,R34,""))),"") | T34: 100 | U34: fornecedor | V34: 1043.8 | W34: 0.2 | X34: =IFERROR(V34+T34,"") | Y34: =IFERROR(IF(W34<1,X34/(1-W34),""),"") | Z34: ='01_CONFIG_GLOBAL'!$C$14 | AA34: =IFERROR(Y34*Z34,"") | AB34: =IFERROR(IF(Z34<1,Y34/(1-Z34),""),"") | AI34: =IFERROR(AVERAGE(AD34,AF34,AH34),"") | AJ34: =IFERROR(IF(AI34="","sem dados",IF(AB34<AI34*0.95,"abaixo",IF(AB34>AI34*1.05,"acima","em linha"))),"") | AK34: sim | AN34: Fotos: assets/livenza_5.0220.0547205-CT_REV._0_p1.png | AO34: =A34 | AP34: =D34 | AQ34: 0029_547205_Livenza_5_0220_0547205-CT_0_att86_p1_foto_3d_ecommerce.png | 0029_547205_Livenza_5_0220_0547205-CT_0_att86_p1_desenho_tec.png | livenza_5.0220.0547205-CT_REV._0_p1.png
A35: 5.0202.0540014.0 | B35: 540014 | C35: =IFERROR(LOWER(SUBSTITUTE(SUBSTITUTE(SUBSTITUTE(SUBSTITUTE(D35," ","-"),"/","-"),".",""),",","")),"") | D35: BOMBA HIDRÁULICA - APLICAÇÃO 4 A.B9.A.L (CRUCETA) | E35: Bombas Hidráulicas | F35: SOHIPREN | H35: draft | I35: AMEISE | J35: EMPILHADEIRA ELETRICA | K35: PRINCIPAL | L35: 750298 | R35: =IFERROR(IF(AND(O35>0,P35>0,Q35>0),(O35*P35*Q35)/6000,""),"") | S35: =IFERROR(IF(AND(N35>0,R35>0),MAX(N35,R35),IF(N35>0,N35,IF(R35>0,R35,""))),"") | U35: FALTA | V35: 473 | W35: 0.3 | X35: =IFERROR(V35+T35,"") | Y35: =IFERROR(IF(W35<1,X35/(1-W35),""),"") | Z35: ='01_CONFIG_GLOBAL'!$C$14 | AA35: =IFERROR(Y35*Z35,"") | AB35: =IFERROR(IF(Z35<1,Y35/(1-Z35),""),"") | AI35: =IFERROR(AVERAGE(AD35,AF35,AH35),"") | AJ35: =IFERROR(IF(AI35="","sem dados",IF(AB35<AI35*0.95,"abaixo",IF(AB35>AI35*1.05,"acima","em linha"))),"") | AK35: não | AO35: =A35 | AP35: =D35
A36: 5.0206.0543269.0 | B36: 543269 | C36: =IFERROR(LOWER(SUBSTITUTE(SUBSTITUTE(SUBSTITUTE(SUBSTITUTE(D36," ","-"),"/","-"),".",""),",","")),"") | D36: BOMBA HIDRÁULICA - APLICAÇÃO 11 A.B9.A4.L (CRUCETA) | E36: Bombas Hidráulicas | F36: SOHIPREN | H36: draft | I36: AMEISE | J36: EMPILHADEIRA ELETRICA | K36: PRINCIPAL | L36: 750117 | R36: =IFERROR(IF(AND(O36>0,P36>0,Q36>0),(O36*P36*Q36)/6000,""),"") | S36: =IFERROR(IF(AND(N36>0,R36>0),MAX(N36,R36),IF(N36>0,N36,IF(R36>0,R36,""))),"") | U36: FALTA | V36: 517 | W36: 0.3 | X36: =IFERROR(V36+T36,"") | Y36: =IFERROR(IF(W36<1,X36/(1-W36),""),"") | Z36: ='01_CONFIG_GLOBAL'!$C$14 | AA36: =IFERROR(Y36*Z36,"") | AB36: =IFERROR(IF(Z36<1,Y36/(1-Z36),""),"") | AI36: =IFERROR(AVERAGE(AD36,AF36,AH36),"") | AJ36: =IFERROR(IF(AI36="","sem dados",IF(AB36<AI36*0.95,"abaixo",IF(AB36>AI36*1.05,"acima","em linha"))),"") | AK36: não | AO36: =A36 | AP36: =D36
A37: 5.0208.0544879.0 | B37: 544879 | C37: =IFERROR(LOWER(SUBSTITUTE(SUBSTITUTE(SUBSTITUTE(SUBSTITUTE(D37," ","-"),"/","-"),".",""),",","")),"") | D37: BOMBA HIDRÁULICA - APLICAÇÃO 16 A.B9.A4.L | E37: Bombas Hidráulicas | F37: SOHIPREN | H37: draft | I37: AMEISE | J37: EMPILHADEIRA ELETRICA | K37: PRINCIPAL | L37: 750083 | R37: =IFERROR(IF(AND(O37>0,P37>0,Q37>0),(O37*P37*Q37)/6000,""),"") | S37: =IFERROR(IF(AND(N37>0,R37>0),MAX(N37,R37),IF(N37>0,N37,IF(R37>0,R37,""))),"") | U37: FALTA | V37: 605 | W37: 0.3 | X37: =IFERROR(V37+T37,"") | Y37: =IFERROR(IF(W37<1,X37/(1-W37),""),"") | Z37: ='01_CONFIG_GLOBAL'!$C$14 | AA37: =IFERROR(Y37*Z37,"") | AB37: =IFERROR(IF(Z37<1,Y37/(1-Z37),""),"") | AI37: =IFERROR(AVERAGE(AD37,AF37,AH37),"") | AJ37: =IFERROR(IF(AI37="","sem dados",IF(AB37<AI37*0.95,"abaixo",IF(AB37>AI37*1.05,"acima","em linha"))),"") | AK37: não | AO37: =A37 | AP37: =D37
A38: 5.5205.0549529.0 | B38: 549529 | C38: =IFERROR(LOWER(SUBSTITUTE(SUBSTITUTE(SUBSTITUTE(SUBSTITUTE(D38," ","-"),"/","-"),".",""),",","")),"") | D38: MRBO 8 C11.C.C3.L | F38: SOHIPREN | H38: draft | I38: ANDRADE | J38: BOMBA D'AGUA | K38: MOTOR HIDRÁULICO | L38: 28685/0513013715 | R38: =IFERROR(IF(AND(O38>0,P38>0,Q38>0),(O38*P38*Q38)/6000,""),"") | S38: =IFERROR(IF(AND(N38>0,R38>0),MAX(N38,R38),IF(N38>0,N38,IF(R38>0,R38,""))),"") | U38: FALTA | V38: 767.8 | W38: 0.3 | X38: =IFERROR(V38+T38,"") | Y38: =IFERROR(IF(W38<1,X38/(1-W38),""),"") | Z38: ='01_CONFIG_GLOBAL'!$C$14 | AA38: =IFERROR(Y38*Z38,"") | AB38: =IFERROR(IF(Z38<1,Y38/(1-Z38),""),"") | AI38: =IFERROR(AVERAGE(AD38,AF38,AH38),"") | AJ38: =IFERROR(IF(AI38="","sem dados",IF(AB38<AI38*0.95,"abaixo",IF(AB38>AI38*1.05,"acima","em linha"))),"") | AK38: não | AO38: =A38 | AP38: =D38
A39: 5.5209.L008060.0 | B39: L00806 | C39: =IFERROR(LOWER(SUBSTITUTE(SUBSTITUTE(SUBSTITUTE(SUBSTITUTE(D39," ","-"),"/","-"),".",""),",","")),"") | D39: MUD BO 8 C11.C.G.BL (2734) | F39: SOHIPREN | H39: draft | I39: ANDRADE | J39: BOMLBA TASP | K39: ACIONAMENTO BOMBA D'AGUA | R39: =IFERROR(IF(AND(O39>0,P39>0,Q39>0),(O39*P39*Q39)/6000,""),"") | S39: =IFERROR(IF(AND(N39>0,R39>0),MAX(N39,R39),IF(N39>0,N39,IF(R39>0,R39,""))),"") | U39: FALTA | V39: 428.93 | W39: 0.3 | X39: =IFERROR(V39+T39,"") | Y39: =IFERROR(IF(W39<1,X39/(1-W39),""),"") | Z39: ='01_CONFIG_GLOBAL'!$C$14 | AA39: =IFERROR(Y39*Z39,"") | AB39: =IFERROR(IF(Z39<1,Y39/(1-Z39),""),"") | AI39: =IFERROR(AVERAGE(AD39,AF39,AH39),"") | AJ39: =IFERROR(IF(AI39="","sem dados",IF(AB39<AI39*0.95,"abaixo",IF(AB39>AI39*1.05,"acima","em linha"))),"") | AK39: não | AO39: =A39 | AP39: =D39
A40: 5.5209.L009930.0 | B40: L00993 | C40: =IFERROR(LOWER(SUBSTITUTE(SUBSTITUTE(SUBSTITUTE(SUBSTITUTE(D40," ","-"),"/","-"),".",""),",","")),"") | D40: MUI BO 8 C11.C.G.BL (2734) | F40: SOHIPREN | H40: draft | I40: ANDRADE | J40: IRRIGADOR | K40: ACIONAMENTO BOMBA D'AGUA | R40: =IFERROR(IF(AND(O40>0,P40>0,Q40>0),(O40*P40*Q40)/6000,""),"") | S40: =IFERROR(IF(AND(N40>0,R40>0),MAX(N40,R40),IF(N40>0,N40,IF(R40>0,R40,""))),"") | U40: FALTA | V40: 790 | W40: 0.3 | X40: =IFERROR(V40+T40,"") | Y40: =IFERROR(IF(W40<1,X40/(1-W40),""),"") | Z40: ='01_CONFIG_GLOBAL'!$C$14 | AA40: =IFERROR(Y40*Z40,"") | AB40: =IFERROR(IF(Z40<1,Y40/(1-Z40),""),"") | AI40: =IFERROR(AVERAGE(AD40,AF40,AH40),"") | AJ40: =IFERROR(IF(AI40="","sem dados",IF(AB40<AI40*0.95,"abaixo",IF(AB40>AI40*1.05,"acima","em linha"))),"") | AK40: não | AO40: =A40 | AP40: =D40
A41: 5.5206.L010450.0 | B41: L01045 | C41: =IFERROR(LOWER(SUBSTITUTE(SUBSTITUTE(SUBSTITUTE(SUBSTITUTE(D41," ","-"),"/","-"),".",""),",","")),"") | D41: MUD BO 11 E18.C.G.BL (2734) | F41: SOHIPREN | H41: draft | I41: ANDRADE | J41: IRRIGADOR | K41: ACIONAMENTO BOMBA D'AGUA | R41: =IFERROR(IF(AND(O41>0,P41>0,Q41>0),(O41*P41*Q41)/6000,""),"") | S41: =IFERROR(IF(AND(N41>0,R41>0),MAX(N41,R41),IF(N41>0,N41,IF(R41>0,R41,""))),"") | U41: FALTA | V41: 708 | W41: 0.3 | X41: =IFERROR(V41+T41,"") | Y41: =IFERROR(IF(W41<1,X41/(1-W41),""),"") | Z41: ='01_CONFIG_GLOBAL'!$C$14 | AA41: =IFERROR(Y41*Z41,"") | AB41: =IFERROR(IF(Z41<1,Y41/(1-Z41),""),"") | AI41: =IFERROR(AVERAGE(AD41,AF41,AH41),"") | AJ41: =IFERROR(IF(AI41="","sem dados",IF(AB41<AI41*0.95,"abaixo",IF(AB41>AI41*1.05,"acima","em linha"))),"") | AK41: não | AO41: =A41 | AP41: =D41
A42: 5.5206.L008640.0 | B42: L00864 | C42: =IFERROR(LOWER(SUBSTITUTE(SUBSTITUTE(SUBSTITUTE(SUBSTITUTE(D42," ","-"),"/","-"),".",""),",","")),"") | D42: MUD BO 11 C11.C.G.BL (2734) | F42: SOHIPREN | H42: draft | I42: ANDRADE | J42: IRRIGADOR | K42: ACIONAMENTO BOMBA D'AGUA | R42: =IFERROR(IF(AND(O42>0,P42>0,Q42>0),(O42*P42*Q42)/6000,""),"") | S42: =IFERROR(IF(AND(N42>0,R42>0),MAX(N42,R42),IF(N42>0,N42,IF(R42>0,R42,""))),"") | U42: FALTA | V42: 497.13 | W42: 0.3 | X42: =IFERROR(V42+T42,"") | Y42: =IFERROR(IF(W42<1,X42/(1-W42),""),"") | Z42: ='01_CONFIG_GLOBAL'!$C$14 | AA42: =IFERROR(Y42*Z42,"") | AB42: =IFERROR(IF(Z42<1,Y42/(1-Z42),""),"") | AI42: =IFERROR(AVERAGE(AD42,AF42,AH42),"") | AJ42: =IFERROR(IF(AI42="","sem dados",IF(AB42<AI42*0.95,"abaixo",IF(AB42>AI42*1.05,"acima","em linha"))),"") | AK42: não | AO42: =A42 | AP42: =D42
A43: 5.5209.L010770.0 | B43: L01077 | C43: =IFERROR(LOWER(SUBSTITUTE(SUBSTITUTE(SUBSTITUTE(SUBSTITUTE(D43," ","-"),"/","-"),".",""),",","")),"") | D43: MUD BO 8 E18.C.G.BL (2734) | F43: SOHIPREN | H43: draft | I43: ANDRADE | J43: IRRIGADOR | K43: ACIONAMENTO BOMBA D'AGUA | R43: =IFERROR(IF(AND(O43>0,P43>0,Q43>0),(O43*P43*Q43)/6000,""),"") | S43: =IFERROR(IF(AND(N43>0,R43>0),MAX(N43,R43),IF(N43>0,N43,IF(R43>0,R43,""))),"") | U43: FALTA | V43: 708 | W43: 0.3 | X43: =IFERROR(V43+T43,"") | Y43: =IFERROR(IF(W43<1,X43/(1-W43),""),"") | Z43: ='01_CONFIG_GLOBAL'!$C$14 | AA43: =IFERROR(Y43*Z43,"") | AB43: =IFERROR(IF(Z43<1,Y43/(1-Z43),""),"") | AI43: =IFERROR(AVERAGE(AD43,AF43,AH43),"") | AJ43: =IFERROR(IF(AI43="","sem dados",IF(AB43<AI43*0.95,"abaixo",IF(AB43>AI43*1.05,"acima","em linha"))),"") | AK43: não | AO43: =A43 | AP43: =D43
A44: 5.5207.L010790.0 | B44: L01079 | C44: =IFERROR(LOWER(SUBSTITUTE(SUBSTITUTE(SUBSTITUTE(SUBSTITUTE(D44," ","-"),"/","-"),".",""),",","")),"") | D44: MRBO 14 B1.C.G.L | F44: SOHIPREN | H44: draft | I44: ANDRADE | J44: IRRIGADOR | K44: ACIONAMENTO BOMBA D'AGUA | R44: =IFERROR(IF(AND(O44>0,P44>0,Q44>0),(O44*P44*Q44)/6000,""),"") | S44: =IFERROR(IF(AND(N44>0,R44>0),MAX(N44,R44),IF(N44>0,N44,IF(R44>0,R44,""))),"") | U44: FALTA | V44: 708 | W44: 0.3 | X44: =IFERROR(V44+T44,"") | Y44: =IFERROR(IF(W44<1,X44/(1-W44),""),"") | Z44: ='01_CONFIG_GLOBAL'!$C$14 | AA44: =IFERROR(Y44*Z44,"") | AB44: =IFERROR(IF(Z44<1,Y44/(1-Z44),""),"") | AI44: =IFERROR(AVERAGE(AD44,AF44,AH44),"") | AJ44: =IFERROR(IF(AI44="","sem dados",IF(AB44<AI44*0.95,"abaixo",IF(AB44>AI44*1.05,"acima","em linha"))),"") | AK44: não | AO44: =A44 | AP44: =D44
A45: 5.5205.L010800.0 | B45: L01080 | C45: =IFERROR(LOWER(SUBSTITUTE(SUBSTITUTE(SUBSTITUTE(SUBSTITUTE(D45," ","-"),"/","-"),".",""),",","")),"") | D45: MUD 8 E18.C.C21.L | F45: SOHIPREN | H45: draft | I45: ANDRADE | J45: IRRIGADOR | K45: ACIONAMENTO BOMBA D'AGUA | R45: =IFERROR(IF(AND(O45>0,P45>0,Q45>0),(O45*P45*Q45)/6000,""),"") | S45: =IFERROR(IF(AND(N45>0,R45>0),MAX(N45,R45),IF(N45>0,N45,IF(R45>0,R45,""))),"") | U45: FALTA | V45: 651.2 | W45: 0.3 | X45: =IFERROR(V45+T45,"") | Y45: =IFERROR(IF(W45<1,X45/(1-W45),""),"") | Z45: ='01_CONFIG_GLOBAL'!$C$14 | AA45: =IFERROR(Y45*Z45,"") | AB45: =IFERROR(IF(Z45<1,Y45/(1-Z45),""),"") | AI45: =IFERROR(AVERAGE(AD45,AF45,AH45),"") | AJ45: =IFERROR(IF(AI45="","sem dados",IF(AB45<AI45*0.95,"abaixo",IF(AB45>AI45*1.05,"acima","em linha"))),"") | AK45: não | AO45: =A45 | AP45: =D45
A46: 5.5205.L012870.0 | B46: L01287 | C46: =IFERROR(LOWER(SUBSTITUTE(SUBSTITUTE(SUBSTITUTE(SUBSTITUTE(D46," ","-"),"/","-"),".",""),",","")),"") | D46: MUD BO 8 C11.C.G - (SIN BLOQUE) | F46: SOHIPREN | H46: draft | I46: ANDRADE | J46: IRRIGADOR | K46: ACIONAMENTO BOMBA D'AGUA | R46: =IFERROR(IF(AND(O46>0,P46>0,Q46>0),(O46*P46*Q46)/6000,""),"") | S46: =IFERROR(IF(AND(N46>0,R46>0),MAX(N46,R46),IF(N46>0,N46,IF(R46>0,R46,""))),"") | U46: FALTA | V46: 708 | W46: 0.3 | X46: =IFERROR(V46+T46,"") | Y46: =IFERROR(IF(W46<1,X46/(1-W46),""),"") | Z46: ='01_CONFIG_GLOBAL'!$C$14 | AA46: =IFERROR(Y46*Z46,"") | AB46: =IFERROR(IF(Z46<1,Y46/(1-Z46),""),"") | AI46: =IFERROR(AVERAGE(AD46,AF46,AH46),"") | AJ46: =IFERROR(IF(AI46="","sem dados",IF(AB46<AI46*0.95,"abaixo",IF(AB46>AI46*1.05,"acima","em linha"))),"") | AK46: não | AO46: =A46 | AP46: =D46
A47: 0.2201.F001184.0 | B47: F001184 | C47: =IFERROR(LOWER(SUBSTITUTE(SUBSTITUTE(SUBSTITUTE(SUBSTITUTE(D47," ","-"),"/","-"),".",""),",","")),"") | D47: PARAFUSO P/ INSERTO M3,5 | F47: SOHIPREN | H47: draft | I47: ANTARES | L47: 416.1-833 | R47: =IFERROR(IF(AND(O47>0,P47>0,Q47>0),(O47*P47*Q47)/6000,""),"") | S47: =IFERROR(IF(AND(N47>0,R47>0),MAX(N47,R47),IF(N47>0,N47,IF(R47>0,R47,""))),"") | U47: FALTA | V47: 9817.5 | W47: 0.3 | X47: =IFERROR(V47+T47,"") | Y47: =IFERROR(IF(W47<1,X47/(1-W47),""),"") | Z47: ='01_CONFIG_GLOBAL'!$C$14 | AA47: =IFERROR(Y47*Z47,"") | AB47: =IFERROR(IF(Z47<1,Y47/(1-Z47),""),"") | AI47: =IFERROR(AVERAGE(AD47,AF47,AH47),"") | AJ47: =IFERROR(IF(AI47="","sem dados",IF(AB47<AI47*0.95,"abaixo",IF(AB47>AI47*1.05,"acima","em linha"))),"") | AK47: não | AO47: =A47 | AP47: =D47
A48: 2.0410.L080977.1 | B48: L080977 | C48: =IFERROR(LOWER(SUBSTITUTE(SUBSTITUTE(SUBSTITUTE(SUBSTITUTE(D48," ","-"),"/","-"),".",""),",","")),"") | D48: BOBINA 24V CMD 80 LTRS | F48: SOHIPREN | H48: draft | I48: ARGO-HYTOS | J48: MOTOR BO | K48: FUN DRIVE | L48: 31805300 | R48: =IFERROR(IF(AND(O48>0,P48>0,Q48>0),(O48*P48*Q48)/6000,""),"") | S48: =IFERROR(IF(AND(N48>0,R48>0),MAX(N48,R48),IF(N48>0,N48,IF(R48>0,R48,""))),"") | U48: FALTA | V48: 308 | W48: 0.3 | X48: =IFERROR(V48+T48,"") | Y48: =IFERROR(IF(W48<1,X48/(1-W48),""),"") | Z48: ='01_CONFIG_GLOBAL'!$C$14 | AA48: =IFERROR(Y48*Z48,"") | AB48: =IFERROR(IF(Z48<1,Y48/(1-Z48),""),"") | AI48: =IFERROR(AVERAGE(AD48,AF48,AH48),"") | AJ48: =IFERROR(IF(AI48="","sem dados",IF(AB48<AI48*0.95,"abaixo",IF(AB48>AI48*1.05,"acima","em linha"))),"") | AK48: não | AO48: =A48 | AP48: =D48
A49: 0.0162.L082392.0 | B49: L082392 | C49: =IFERROR(LOWER(SUBSTITUTE(SUBSTITUTE(SUBSTITUTE(SUBSTITUTE(D49," ","-"),"/","-"),".",""),",","")),"") | D49: ADAPT MACHO 9/16'' ORING X 5/8'' JIC | F49: SOHIPREN | H49: draft | I49: ARGON | L49: M02702-06-07 | R49: =IFERROR(IF(AND(O49>0,P49>0,Q49>0),(O49*P49*Q49)/6000,""),"") | S49: =IFERROR(IF(AND(N49>0,R49>0),MAX(N49,R49),IF(N49>0,N49,IF(R49>0,R49,""))),"") | U49: FALTA | V49: 59 | W49: 0.3 | X49: =IFERROR(V49+T49,"") | Y49: =IFERROR(IF(W49<1,X49/(1-W49),""),"") | Z49: ='01_CONFIG_GLOBAL'!$C$14 | AA49: =IFERROR(Y49*Z49,"") | AB49: =IFERROR(IF(Z49<1,Y49/(1-Z49),""),"") | AI49: =IFERROR(AVERAGE(AD49,AF49,AH49),"") | AJ49: =IFERROR(IF(AI49="","sem dados",IF(AB49<AI49*0.95,"abaixo",IF(AB49>AI49*1.05,"acima","em linha"))),"") | AK49: não | AO49: =A49 | AP49: =D49
A50: 0.2206.F001181.0 | B50: F001181 | C50: =IFERROR(LOWER(SUBSTITUTE(SUBSTITUTE(SUBSTITUTE(SUBSTITUTE(D50," ","-"),"/","-"),".",""),",","")),"") | D50: BUCHA DE REDUCAO 3/4 NPT X 1/2 NPT | F50: SOHIPREN | H50: draft | I50: ARGON | L50: M081-12-08E | R50: =IFERROR(IF(AND(O50>0,P50>0,Q50>0),(O50*P50*Q50)/6000,""),"") | S50: =IFERROR(IF(AND(N50>0,R50>0),MAX(N50,R50),IF(N50>0,N50,IF(R50>0,R50,""))),"") | U50: FALTA | V50: 335.5 | W50: 0.3 | X50: =IFERROR(V50+T50,"") | Y50: =IFERROR(IF(W50<1,X50/(1-W50),""),"") | Z50: ='01_CONFIG_GLOBAL'!$C$14 | AA50: =IFERROR(Y50*Z50,"") | AB50: =IFERROR(IF(Z50<1,Y50/(1-Z50),""),"") | AI50: =IFERROR(AVERAGE(AD50,AF50,AH50),"") | AJ50: =IFERROR(IF(AI50="","sem dados",IF(AB50<AI50*0.95,"abaixo",IF(AB50>AI50*1.05,"acima","em linha"))),"") | AK50: não | AO50: =A50 | AP50: =D50
A51: 0.2206.F001194.0 | B51: F001194 | C51: =IFERROR(LOWER(SUBSTITUTE(SUBSTITUTE(SUBSTITUTE(SUBSTITUTE(D51," ","-"),"/","-"),".",""),",","")),"") | D51: VALVULA ESFERA PP 300 LBS 1.1/2 VEA-24 | F51: SOHIPREN | H51: draft | I51: ARGON | L51: 30200056 | R51: =IFERROR(IF(AND(O51>0,P51>0,Q51>0),(O51*P51*Q51)/6000,""),"") | S51: =IFERROR(IF(AND(N51>0,R51>0),MAX(N51,R51),IF(N51>0,N51,IF(R51>0,R51,""))),"") | U51: FALTA | V51: 335.5 | W51: 0.3 | X51: =IFERROR(V51+T51,"") | Y51: =IFERROR(IF(W51<1,X51/(1-W51),""),"") | Z51: ='01_CONFIG_GLOBAL'!$C$14 | AA51: =IFERROR(Y51*Z51,"") | AB51: =IFERROR(IF(Z51<1,Y51/(1-Z51),""),"") | AI51: =IFERROR(AVERAGE(AD51,AF51,AH51),"") | AJ51: =IFERROR(IF(AI51="","sem dados",IF(AB51<AI51*0.95,"abaixo",IF(AB51>AI51*1.05,"acima","em linha"))),"") | AK51: não | AO51: =A51 | AP51: =D51
A52: 0.0162.F001192.0 | B52: F001192 | C52: =IFERROR(LOWER(SUBSTITUTE(SUBSTITUTE(SUBSTITUTE(SUBSTITUTE(D52," ","-"),"/","-"),".",""),",","")),"") | D52: MANG SUCCAO E DESCARGA AZUL 1.1/4 - PVC | F52: SOHIPREN | H52: draft | I52: ARGON | L52: MKM-20 | R52: =IFERROR(IF(AND(O52>0,P52>0,Q52>0),(O52*P52*Q52)/6000,""),"") | S52: =IFERROR(IF(AND(N52>0,R52>0),MAX(N52,R52),IF(N52>0,N52,IF(R52>0,R52,""))),"") | U52: FALTA | V52: 59 | W52: 0.3 | X52: =IFERROR(V52+T52,"") | Y52: =IFERROR(IF(W52<1,X52/(1-W52),""),"") | Z52: ='01_CONFIG_GLOBAL'!$C$14 | AA52: =IFERROR(Y52*Z52,"") | AB52: =IFERROR(IF(Z52<1,Y52/(1-Z52),""),"") | AI52: =IFERROR(AVERAGE(AD52,AF52,AH52),"") | AJ52: =IFERROR(IF(AI52="","sem dados",IF(AB52<AI52*0.95,"abaixo",IF(AB52>AI52*1.05,"acima","em linha"))),"") | AK52: não | AO52: =A52 | AP52: =D52
A53: 0.0166.F001193.0 | B53: F001193 | C53: =IFERROR(LOWER(SUBSTITUTE(SUBSTITUTE(SUBSTITUTE(SUBSTITUTE(D53," ","-"),"/","-"),".",""),",","")),"") | D53: ABRACADEIRA DE FITA 14MM 25-38 | F53: SOHIPREN | H53: draft | I53: ARGON | L53: ABRAC14-25-38 | R53: =IFERROR(IF(AND(O53>0,P53>0,Q53>0),(O53*P53*Q53)/6000,""),"") | S53: =IFERROR(IF(AND(N53>0,R53>0),MAX(N53,R53),IF(N53>0,N53,IF(R53>0,R53,""))),"") | U53: FALTA | V53: 59 | W53: 0.3 | X53: =IFERROR(V53+T53,"") | Y53: =IFERROR(IF(W53<1,X53/(1-W53),""),"") | Z53: ='01_CONFIG_GLOBAL'!$C$14 | AA53: =IFERROR(Y53*Z53,"") | AB53: =IFERROR(IF(Z53<1,Y53/(1-Z53),""),"") | AI53: =IFERROR(AVERAGE(AD53,AF53,AH53),"") | AJ53: =IFERROR(IF(AI53="","sem dados",IF(AB53<AI53*0.95,"abaixo",IF(AB53>AI53*1.05,"acima","em linha"))),"") | AK53: não | AO53: =A53 | AP53: =D53
A54: 0.0162.F001195.0 | B54: F001195 | C54: =IFERROR(LOWER(SUBSTITUTE(SUBSTITUTE(SUBSTITUTE(SUBSTITUTE(D54," ","-"),"/","-"),".",""),",","")),"") | D54: NIPLE DUPLO GALV. 10 1.1/2 | F54: SOHIPREN | H54: draft | I54: ARGON | L54: TUPY-280-24 | R54: =IFERROR(IF(AND(O54>0,P54>0,Q54>0),(O54*P54*Q54)/6000,""),"") | S54: =IFERROR(IF(AND(N54>0,R54>0),MAX(N54,R54),IF(N54>0,N54,IF(R54>0,R54,""))),"") | U54: FALTA | V54: 59 | W54: 0.3 | X54: =IFERROR(V54+T54,"") | Y54: =IFERROR(IF(W54<1,X54/(1-W54),""),"") | Z54: ='01_CONFIG_GLOBAL'!$C$14 | AA54: =IFERROR(Y54*Z54,"") | AB54: =IFERROR(IF(Z54<1,Y54/(1-Z54),""),"") | AI54: =IFERROR(AVERAGE(AD54,AF54,AH54),"") | AJ54: =IFERROR(IF(AI54="","sem dados",IF(AB54<AI54*0.95,"abaixo",IF(AB54>AI54*1.05,"acima","em linha"))),"") | AK54: não | AO54: =A54 | AP54: =D54
A55: 0.0162.F001196.0 | B55: F001196 | C55: =IFERROR(LOWER(SUBSTITUTE(SUBSTITUTE(SUBSTITUTE(SUBSTITUTE(D55," ","-"),"/","-"),".",""),",","")),"") | D55: NIPLE DUPLO GALV. 10 1/1/4 | F55: SOHIPREN | H55: draft | I55: ARGON | L55: TUPY-280-20 | R55: =IFERROR(IF(AND(O55>0,P55>0,Q55>0),(O55*P55*Q55)/6000,""),"") | S55: =IFERROR(IF(AND(N55>0,R55>0),MAX(N55,R55),IF(N55>0,N55,IF(R55>0,R55,""))),"") | U55: FALTA | V55: 59 | W55: 0.3 | X55: =IFERROR(V55+T55,"") | Y55: =IFERROR(IF(W55<1,X55/(1-W55),""),"") | Z55: ='01_CONFIG_GLOBAL'!$C$14 | AA55: =IFERROR(Y55*Z55,"") | AB55: =IFERROR(IF(Z55<1,Y55/(1-Z55),""),"") | AI55: =IFERROR(AVERAGE(AD55,AF55,AH55),"") | AJ55: =IFERROR(IF(AI55="","sem dados",IF(AB55<AI55*0.95,"abaixo",IF(AB55>AI55*1.05,"acima","em linha"))),"") | AK55: não | AO55: =A55 | AP55: =D55
A56: 0.2122.F001197.0 | B56: F001197 | C56: =IFERROR(LOWER(SUBSTITUTE(SUBSTITUTE(SUBSTITUTE(SUBSTITUTE(D56," ","-"),"/","-"),".",""),",","")),"") | D56: COTOVELO 90 GALV. CL10 1.1/2 | F56: SOHIPREN | H56: draft | I56: ARGON | L56: TUPY-90-24 | R56: =IFERROR(IF(AND(O56>0,P56>0,Q56>0),(O56*P56*Q56)/6000,""),"") | S56: =IFERROR(IF(AND(N56>0,R56>0),MAX(N56,R56),IF(N56>0,N56,IF(R56>0,R56,""))),"") | U56: FALTA | V56: 9817.5 | W56: 0.3 | X56: =IFERROR(V56+T56,"") | Y56: =IFERROR(IF(W56<1,X56/(1-W56),""),"") | Z56: ='01_CONFIG_GLOBAL'!$C$14 | AA56: =IFERROR(Y56*Z56,"") | AB56: =IFERROR(IF(Z56<1,Y56/(1-Z56),""),"") | AI56: =IFERROR(AVERAGE(AD56,AF56,AH56),"") | AJ56: =IFERROR(IF(AI56="","sem dados",IF(AB56<AI56*0.95,"abaixo",IF(AB56>AI56*1.05,"acima","em linha"))),"") | AK56: não | AO56: =A56 | AP56: =D56
A57: 0.2122.F001198.0 | B57: F001198 | C57: =IFERROR(LOWER(SUBSTITUTE(SUBSTITUTE(SUBSTITUTE(SUBSTITUTE(D57," ","-"),"/","-"),".",""),",","")),"") | D57: COTOVELO 90 GALV. CL10 1.1/4 | F57: SOHIPREN | H57: draft | I57: ARGON | L57: TUPY-90-20 | R57: =IFERROR(IF(AND(O57>0,P57>0,Q57>0),(O57*P57*Q57)/6000,""),"") | S57: =IFERROR(IF(AND(N57>0,R57>0),MAX(N57,R57),IF(N57>0,N57,IF(R57>0,R57,""))),"") | U57: FALTA | V57: 9817.5 | W57: 0.3 | X57: =IFERROR(V57+T57,"") | Y57: =IFERROR(IF(W57<1,X57/(1-W57),""),"") | Z57: ='01_CONFIG_GLOBAL'!$C$14 | AA57: =IFERROR(Y57*Z57,"") | AB57: =IFERROR(IF(Z57<1,Y57/(1-Z57),""),"") | AI57: =IFERROR(AVERAGE(AD57,AF57,AH57),"") | AJ57: =IFERROR(IF(AI57="","sem dados",IF(AB57<AI57*0.95,"abaixo",IF(AB57>AI57*1.05,"acima","em linha"))),"") | AK57: não | AO57: =A57 | AP57: =D57
A58: 0.2122.F001199.0 | B58: F001199 | C58: =IFERROR(LOWER(SUBSTITUTE(SUBSTITUTE(SUBSTITUTE(SUBSTITUTE(D58," ","-"),"/","-"),".",""),",","")),"") | D58: ESPIGAO ROSCA 1.1/4 BSP X ESPIGAO 1.1/4 ALUMINIO | F58: SOHIPREN | H58: draft | I58: ARGON | L58: ERT-E-BSP-20A | R58: =IFERROR(IF(AND(O58>0,P58>0,Q58>0),(O58*P58*Q58)/6000,""),"") | S58: =IFERROR(IF(AND(N58>0,R58>0),MAX(N58,R58),IF(N58>0,N58,IF(R58>0,R58,""))),"") | U58: FALTA | V58: 9817.5 | W58: 0.3 | X58: =IFERROR(V58+T58,"") | Y58: =IFERROR(IF(W58<1,X58/(1-W58),""),"") | Z58: ='01_CONFIG_GLOBAL'!$C$14 | AA58: =IFERROR(Y58*Z58,"") | AB58: =IFERROR(IF(Z58<1,Y58/(1-Z58),""),"") | AI58: =IFERROR(AVERAGE(AD58,AF58,AH58),"") | AJ58: =IFERROR(IF(AI58="","sem dados",IF(AB58<AI58*0.95,"abaixo",IF(AB58>AI58*1.05,"acima","em linha"))),"") | AK58: não | AO58: =A58 | AP58: =D58
A59: 0.0166.F001541.0 | B59: F001541 | C59: =IFERROR(LOWER(SUBSTITUTE(SUBSTITUTE(SUBSTITUTE(SUBSTITUTE(D59," ","-"),"/","-"),".",""),",","")),"") | D59: ABRACADEIRA DE FITA 9MM 14-22 | F59: SOHIPREN | H59: draft | I59: ARGON | L59: ABRAC14-25-38 | R59: =IFERROR(IF(AND(O59>0,P59>0,Q59>0),(O59*P59*Q59)/6000,""),"") | S59: =IFERROR(IF(AND(N59>0,R59>0),MAX(N59,R59),IF(N59>0,N59,IF(R59>0,R59,""))),"") | U59: FALTA | V59: 59 | W59: 0.3 | X59: =IFERROR(V59+T59,"") | Y59: =IFERROR(IF(W59<1,X59/(1-W59),""),"") | Z59: ='01_CONFIG_GLOBAL'!$C$14 | AA59: =IFERROR(Y59*Z59,"") | AB59: =IFERROR(IF(Z59<1,Y59/(1-Z59),""),"") | AI59: =IFERROR(AVERAGE(AD59,AF59,AH59),"") | AJ59: =IFERROR(IF(AI59="","sem dados",IF(AB59<AI59*0.95,"abaixo",IF(AB59>AI59*1.05,"acima","em linha"))),"") | AK59: não | AO59: =A59 | AP59: =D59
A60: 0.0166.F001533.0 | B60: F001533 | C60: =IFERROR(LOWER(SUBSTITUTE(SUBSTITUTE(SUBSTITUTE(SUBSTITUTE(D60," ","-"),"/","-"),".",""),",","")),"") | D60: ABRACADEIRA DE FITA 14MM 13-19 | F60: SOHIPREN | H60: draft | I60: ARGON | L60: ABRAC14-25-38 | R60: =IFERROR(IF(AND(O60>0,P60>0,Q60>0),(O60*P60*Q60)/6000,""),"") | S60: =IFERROR(IF(AND(N60>0,R60>0),MAX(N60,R60),IF(N60>0,N60,IF(R60>0,R60,""))),"") | U60: FALTA | V60: 59 | W60: 0.3 | X60: =IFERROR(V60+T60,"") | Y60: =IFERROR(IF(W60<1,X60/(1-W60),""),"") | Z60: ='01_CONFIG_GLOBAL'!$C$14 | AA60: =IFERROR(Y60*Z60,"") | AB60: =IFERROR(IF(Z60<1,Y60/(1-Z60),""),"") | AI60: =IFERROR(AVERAGE(AD60,AF60,AH60),"") | AJ60: =IFERROR(IF(AI60="","sem dados",IF(AB60<AI60*0.95,"abaixo",IF(AB60>AI60*1.05,"acima","em linha"))),"") | AK60: não | AO60: =A60 | AP60: =D60
... A109: 0.2206.L081358.0 | B109: L081358 | C109: =IFERROR(LOWER(SUBSTITUTE(SUBSTITUTE(SUBSTITUTE(SUBSTITUTE(D109," ","-"),"/","-"),".",""),",","")),"") | D109: VÁLVULA DE ESFERA BAIXA PRESSÃO FF 1.1/4" BSP | F109: SOHIPREN | H109: draft | I109: ARGON COMERCIAL / MAMUTH | L109: 30200055 | R109: =IFERROR(IF(AND(O109>0,P109>0,Q109>0),(O109*P109*Q109)/6000,""),"") | S109: =IFERROR(IF(AND(N109>0,R109>0),MAX(N109,R109),IF(N109>0,N109,IF(R109>0,R109,""))),"") | U109: FALTA | V109: 335.5 | W109: 0.3 | X109: =IFERROR(V109+T109,"") | Y109: =IFERROR(IF(W109<1,X109/(1-W109),""),"") | Z109: ='01_CONFIG_GLOBAL'!$C$14 | AA109: =IFERROR(Y109*Z109,"") | AB109: =IFERROR(IF(Z109<1,Y109/(1-Z109),""),"") | AI109: =IFERROR(AVERAGE(AD109,AF109,AH109),"") | AJ109: =IFERROR(IF(AI109="","sem dados",IF(AB109<AI109*0.95,"abaixo",IF(AB109>AI109*1.05,"acima","em linha"))),"") | AK109: não | AO109: =A109 | AP109: =D109
A110: 5.0506.0505037.0 | B110: 505037 | C110: =IFERROR(LOWER(SUBSTITUTE(SUBSTITUTE(SUBSTITUTE(SUBSTITUTE(D110," ","-"),"/","-"),".",""),",","")),"") | D110: MC1 60 201.1.21.70.61 | F110: SOHIPREN | H110: draft | I110: ARGOS | J110: GUINDASTES | K110: PRINCIPAL | L110: 13 DENTES ( 1.1/4' x 1' SF ) | R110: =IFERROR(IF(AND(O110>0,P110>0,Q110>0),(O110*P110*Q110)/6000,""),"") | S110: =IFERROR(IF(AND(N110>0,R110>0),MAX(N110,R110),IF(N110>0,N110,IF(R110>0,R110,""))),"") | U110: FALTA | V110: 1150 | W110: 0.3 | X110: =IFERROR(V110+T110,"") | Y110: =IFERROR(IF(W110<1,X110/(1-W110),""),"") | Z110: ='01_CONFIG_GLOBAL'!$C$14 | AA110: =IFERROR(Y110*Z110,"") | AB110: =IFERROR(IF(Z110<1,Y110/(1-Z110),""),"") | AI110: =IFERROR(AVERAGE(AD110,AF110,AH110),"") | AJ110: =IFERROR(IF(AI110="","sem dados",IF(AB110<AI110*0.95,"abaixo",IF(AB110>AI110*1.05,"acima","em linha"))),"") | AK110: não | AO110: =A110 | AP110: =D110
A111: 5.0206.L027058.0 | B111: L027058 | C111: =IFERROR(LOWER(SUBSTITUTE(SUBSTITUTE(SUBSTITUTE(SUBSTITUTE(D111," ","-"),"/","-"),".",""),",","")),"") | D111: BOMBA HIDRÁULICA - APLICAÇÃO 11 E4.C102.G.G2 (C/ ADAPT) | E111: Bombas Hidráulicas | F111: SOHIPREN | H111: draft | I111: AXIONN | J111: CESTO AEREO | K111: PRINCIPAL | L111: AX.BR22797 | R111: =IFERROR(IF(AND(O111>0,P111>0,Q111>0),(O111*P111*Q111)/6000,""),"") | S111: =IFERROR(IF(AND(N111>0,R111>0),MAX(N111,R111),IF(N111>0,N111,IF(R111>0,R111,""))),"") | U111: FALTA | V111: 605 | W111: 0.3 | X111: =IFERROR(V111+T111,"") | Y111: =IFERROR(IF(W111<1,X111/(1-W111),""),"") | Z111: ='01_CONFIG_GLOBAL'!$C$14 | AA111: =IFERROR(Y111*Z111,"") | AB111: =IFERROR(IF(Z111<1,Y111/(1-Z111),""),"") | AI111: =IFERROR(AVERAGE(AD111,AF111,AH111),"") | AJ111: =IFERROR(IF(AI111="","sem dados",IF(AB111<AI111*0.95,"abaixo",IF(AB111>AI111*1.05,"acima","em linha"))),"") | AK111: não | AO111: =A111 | AP111: =D111
A112: 5.0521.L027059.0 | B112: L027059 | C112: =IFERROR(LOWER(SUBSTITUTE(SUBSTITUTE(SUBSTITUTE(SUBSTITUTE(D112," ","-"),"/","-"),".",""),",","")),"") | D112: MC1 32 201.1.21.349/19.B115/4.B12.L | F112: SOHIPREN | H112: draft | I112: AXIONN | R112: =IFERROR(IF(AND(O112>0,P112>0,Q112>0),(O112*P112*Q112)/6000,""),"") | S112: =IFERROR(IF(AND(N112>0,R112>0),MAX(N112,R112),IF(N112>0,N112,IF(R112>0,R112,""))),"") | U112: FALTA | V112: 1710 | W112: 0.3 | X112: =IFERROR(V112+T112,"") | Y112: =IFERROR(IF(W112<1,X112/(1-W112),""),"") | Z112: ='01_CONFIG_GLOBAL'!$C$14 | AA112: =IFERROR(Y112*Z112,"") | AB112: =IFERROR(IF(Z112<1,Y112/(1-Z112),""),"") | AI112: =IFERROR(AVERAGE(AD112,AF112,AH112),"") | AJ112: =IFERROR(IF(AI112="","sem dados",IF(AB112<AI112*0.95,"abaixo",IF(AB112>AI112*1.05,"acima","em linha"))),"") | AK112: não | AO112: =A112 | AP112: =D112
A113: 5.0220.L027060.0 | B113: L027060 | C113: =IFERROR(LOWER(SUBSTITUTE(SUBSTITUTE(SUBSTITUTE(SUBSTITUTE(D113," ","-"),"/","-"),".",""),",","")),"") | D113: BOD 19 E5.P.B2/2,5.C1.L (H15) | E113: Bombas Hidráulicas | F113: SOHIPREN | H113: draft | I113: AXIONN | R113: =IFERROR(IF(AND(O113>0,P113>0,Q113>0),(O113*P113*Q113)/6000,""),"") | S113: =IFERROR(IF(AND(N113>0,R113>0),MAX(N113,R113),IF(N113>0,N113,IF(R113>0,R113,""))),"") | U113: FALTA | V113: 1210 | W113: 0.3 | X113: =IFERROR(V113+T113,"") | Y113: =IFERROR(IF(W113<1,X113/(1-W113),""),"") | Z113: ='01_CONFIG_GLOBAL'!$C$14 | AA113: =IFERROR(Y113*Z113,"") | AB113: =IFERROR(IF(Z113<1,Y113/(1-Z113),""),"") | AI113: =IFERROR(AVERAGE(AD113,AF113,AH113),"") | AJ113: =IFERROR(IF(AI113="","sem dados",IF(AB113<AI113*0.95,"abaixo",IF(AB113>AI113*1.05,"acima","em linha"))),"") | AK113: não | AO113: =A113 | AP113: =D113
A114: 5.0202.0540009.0 | B114: 540009 | C114: =IFERROR(LOWER(SUBSTITUTE(SUBSTITUTE(SUBSTITUTE(SUBSTITUTE(D114," ","-"),"/","-"),".",""),",","")),"") | D114: BOD 4 B1.P1.A.L | E114: Bombas Hidráulicas | F114: SOHIPREN | H114: draft | I114: B Y G TRANSEQUIP EMPILHADEIRAS | J114: EMPILHADEIRA ELÉTRICA | K114: LEVANTE | L114: 9510080203 | R114: =IFERROR(IF(AND(O114>0,P114>0,Q114>0),(O114*P114*Q114)/6000,""),"") | S114: =IFERROR(IF(AND(N114>0,R114>0),MAX(N114,R114),IF(N114>0,N114,IF(R114>0,R114,""))),"") | U114: FALTA | V114: 605 | W114: 0.3 | X114: =IFERROR(V114+T114,"") | Y114: =IFERROR(IF(W114<1,X114/(1-W114),""),"") | Z114: ='01_CONFIG_GLOBAL'!$C$14 | AA114: =IFERROR(Y114*Z114,"") | AB114: =IFERROR(IF(Z114<1,Y114/(1-Z114),""),"") | AI114: =IFERROR(AVERAGE(AD114,AF114,AH114),"") | AJ114: =IFERROR(IF(AI114="","sem dados",IF(AB114<AI114*0.95,"abaixo",IF(AB114>AI114*1.05,"acima","em linha"))),"") | AK114: não | AO114: =A114 | AP114: =D114
A115: 6.5051.0673139.0 | B115: 673139 | C115: =IFERROR(LOWER(SUBSTITUTE(SUBSTITUTE(SUBSTITUTE(SUBSTITUTE(D115," ","-"),"/","-"),".",""),",","")),"") | D115: VALVULA RETENCION DOBLE CONTRABALANCE (VBCD12 DE) | F115: SOHIPREN | H115: draft | I115: BALDAN | J115: PLANTADEIRA | K115: MARCADOR DE LINHA | L115: VÁLVULA SEQUENCIA | R115: =IFERROR(IF(AND(O115>0,P115>0,Q115>0),(O115*P115*Q115)/6000,""),"") | S115: =IFERROR(IF(AND(N115>0,R115>0),MAX(N115,R115),IF(N115>0,N115,IF(R115>0,R115,""))),"") | U115: FALTA | V115: 416.9 | W115: 0.3 | X115: =IFERROR(V115+T115,"") | Y115: =IFERROR(IF(W115<1,X115/(1-W115),""),"") | Z115: ='01_CONFIG_GLOBAL'!$C$14 | AA115: =IFERROR(Y115*Z115,"") | AB115: =IFERROR(IF(Z115<1,Y115/(1-Z115),""),"") | AI115: =IFERROR(AVERAGE(AD115,AF115,AH115),"") | AJ115: =IFERROR(IF(AI115="","sem dados",IF(AB115<AI115*0.95,"abaixo",IF(AB115>AI115*1.05,"acima","em linha"))),"") | AK115: não | AO115: =A115 | AP115: =D115
A116: 6.5051.0673140.0 | B116: 673140 | C116: =IFERROR(LOWER(SUBSTITUTE(SUBSTITUTE(SUBSTITUTE(SUBSTITUTE(D116," ","-"),"/","-"),".",""),",","")),"") | D116: VALVULA RETENCION SIMPLE CONTRABALANCE (VBCD 38 SE) | F116: SOHIPREN | H116: draft | I116: BALDAN | J116: PLANTADEIRA | K116: MARCADOR DE LINHA | L116: VÁLVULA SEQUENCIA | R116: =IFERROR(IF(AND(O116>0,P116>0,Q116>0),(O116*P116*Q116)/6000,""),"") | S116: =IFERROR(IF(AND(N116>0,R116>0),MAX(N116,R116),IF(N116>0,N116,IF(R116>0,R116,""))),"") | U116: FALTA | V116: 416.9 | W116: 0.3 | X116: =IFERROR(V116+T116,"") | Y116: =IFERROR(IF(W116<1,X116/(1-W116),""),"") | Z116: ='01_CONFIG_GLOBAL'!$C$14 | AA116: =IFERROR(Y116*Z116,"") | AB116: =IFERROR(IF(Z116<1,Y116/(1-Z116),""),"") | AI116: =IFERROR(AVERAGE(AD116,AF116,AH116),"") | AJ116: =IFERROR(IF(AI116="","sem dados",IF(AB116<AI116*0.95,"abaixo",IF(AB116>AI116*1.05,"acima","em linha"))),"") | AK116: não | AO116: =A116 | AP116: =D116
A117: 6.5021.0673141.0 | B117: 673141 | C117: =IFERROR(LOWER(SUBSTITUTE(SUBSTITUTE(SUBSTITUTE(SUBSTITUTE(D117," ","-"),"/","-"),".",""),",","")),"") | D117: VALVULA ANTICHOQUE DOBLE (VAU 12) | F117: SOHIPREN | H117: draft | I117: BALDAN | J117: PLANTADEIRA | K117: MARCADOR DE LINHA | L117: VÁLVULA SEQUENCIA | R117: =IFERROR(IF(AND(O117>0,P117>0,Q117>0),(O117*P117*Q117)/6000,""),"") | S117: =IFERROR(IF(AND(N117>0,R117>0),MAX(N117,R117),IF(N117>0,N117,IF(R117>0,R117,""))),"") | U117: FALTA | V117: 170 | W117: 0.3 | X117: =IFERROR(V117+T117,"") | Y117: =IFERROR(IF(W117<1,X117/(1-W117),""),"") | Z117: ='01_CONFIG_GLOBAL'!$C$14 | AA117: =IFERROR(Y117*Z117,"") | AB117: =IFERROR(IF(Z117<1,Y117/(1-Z117),""),"") | AI117: =IFERROR(AVERAGE(AD117,AF117,AH117),"") | AJ117: =IFERROR(IF(AI117="","sem dados",IF(AB117<AI117*0.95,"abaixo",IF(AB117>AI117*1.05,"acima","em linha"))),"") | AK117: não | AO117: =A117 | AP117: =D117
A118: 6.5061.0673142.0 | B118: 673142 | C118: =IFERROR(LOWER(SUBSTITUTE(SUBSTITUTE(SUBSTITUTE(SUBSTITUTE(D118," ","-"),"/","-"),".",""),",","")),"") | D118: UTILIZAR O CÓDIGO L082173 | F118: SOHIPREN | H118: draft | I118: BALDAN | J118: PLANTADEIRA | K118: MARCADOR DE LINHA | L118: VÁLVULA SEQUENCIA | R118: =IFERROR(IF(AND(O118>0,P118>0,Q118>0),(O118*P118*Q118)/6000,""),"") | S118: =IFERROR(IF(AND(N118>0,R118>0),MAX(N118,R118),IF(N118>0,N118,IF(R118>0,R118,""))),"") | U118: FALTA | V118: 4923.6 | W118: 0.3 | X118: =IFERROR(V118+T118,"") | Y118: =IFERROR(IF(W118<1,X118/(1-W118),""),"") | Z118: ='01_CONFIG_GLOBAL'!$C$14 | AA118: =IFERROR(Y118*Z118,"") | AB118: =IFERROR(IF(Z118<1,Y118/(1-Z118),""),"") | AI118: =IFERROR(AVERAGE(AD118,AF118,AH118),"") | AJ118: =IFERROR(IF(AI118="","sem dados",IF(AB118<AI118*0.95,"abaixo",IF(AB118>AI118*1.05,"acima","em linha"))),"") | AK118: não | AO118: =A118 | AP118: =D118
A119: 6.5061.0673143.0 | B119: 673143 | C119: =IFERROR(LOWER(SUBSTITUTE(SUBSTITUTE(SUBSTITUTE(SUBSTITUTE(D119," ","-"),"/","-"),".",""),",","")),"") | D119: VALVULA ELECTRICA (BLOQUE TN6 TANDEM 12V - VRD) | F119: SOHIPREN | H119: draft | I119: BALDAN | J119: PLANTADEIRA | K119: MARCADOR DE LINHA | L119: VÁLVULA SEQUENCIA | R119: =IFERROR(IF(AND(O119>0,P119>0,Q119>0),(O119*P119*Q119)/6000,""),"") | S119: =IFERROR(IF(AND(N119>0,R119>0),MAX(N119,R119),IF(N119>0,N119,IF(R119>0,R119,""))),"") | U119: FALTA | V119: 4923.6 | W119: 0.3 | X119: =IFERROR(V119+T119,"") | Y119: =IFERROR(IF(W119<1,X119/(1-W119),""),"") | Z119: ='01_CONFIG_GLOBAL'!$C$14 | AA119: =IFERROR(Y119*Z119,"") | AB119: =IFERROR(IF(Z119<1,Y119/(1-Z119),""),"") | AI119: =IFERROR(AVERAGE(AD119,AF119,AH119),"") | AJ119: =IFERROR(IF(AI119="","sem dados",IF(AB119<AI119*0.95,"abaixo",IF(AB119>AI119*1.05,"acima","em linha"))),"") | AK119: não | AO119: =A119 | AP119: =D119
A120: 6.5051.0673138.0 | B120: 673138 | C120: =IFERROR(LOWER(SUBSTITUTE(SUBSTITUTE(SUBSTITUTE(SUBSTITUTE(D120," ","-"),"/","-"),".",""),",","")),"") | D120: VALVULA RETENCION DOBLE CONTRABALANCE TIPO A (VBCD34 DE-A) | F120: SOHIPREN | H120: draft | I120: BALDAN | J120: PLANTADEIRA | K120: MARCADOR DE LINHA | L120: VÁLVULA SEQUENCIA | R120: =IFERROR(IF(AND(O120>0,P120>0,Q120>0),(O120*P120*Q120)/6000,""),"") | S120: =IFERROR(IF(AND(N120>0,R120>0),MAX(N120,R120),IF(N120>0,N120,IF(R120>0,R120,""))),"") | U120: FALTA | V120: 416.9 | W120: 0.3 | X120: =IFERROR(V120+T120,"") | Y120: =IFERROR(IF(W120<1,X120/(1-W120),""),"") | Z120: ='01_CONFIG_GLOBAL'!$C$14 | AA120: =IFERROR(Y120*Z120,"") | AB120: =IFERROR(IF(Z120<1,Y120/(1-Z120),""),"") | AI120: =IFERROR(AVERAGE(AD120,AF120,AH120),"") | AJ120: =IFERROR(IF(AI120="","sem dados",IF(AB120<AI120*0.95,"abaixo",IF(AB120>AI120*1.05,"acima","em linha"))),"") | AK120: não | AO120: =A120 | AP120: =D120
A121: 6.5061.0673002.0 | B121: 673002 | C121: =IFERROR(LOWER(SUBSTITUTE(SUBSTITUTE(SUBSTITUTE(SUBSTITUTE(D121," ","-"),"/","-"),".",""),",","")),"") | D121: VALVULA SECUENCIAL (BRASIL) | F121: SOHIPREN | H121: draft | I121: BALDAN | J121: PLANTADEIRA | K121: MARCADOR DE LINHA | L121: VÁLVULA SEQUENCIA | R121: =IFERROR(IF(AND(O121>0,P121>0,Q121>0),(O121*P121*Q121)/6000,""),"") | S121: =IFERROR(IF(AND(N121>0,R121>0),MAX(N121,R121),IF(N121>0,N121,IF(R121>0,R121,""))),"") | U121: FALTA | V121: 416.9 | W121: 0.3 | X121: =IFERROR(V121+T121,"") | Y121: =IFERROR(IF(W121<1,X121/(1-W121),""),"") | Z121: ='01_CONFIG_GLOBAL'!$C$14 | AA121: =IFERROR(Y121*Z121,"") | AB121: =IFERROR(IF(Z121<1,Y121/(1-Z121),""),"") | AI121: =IFERROR(AVERAGE(AD121,AF121,AH121),"") | AJ121: =IFERROR(IF(AI121="","sem dados",IF(AB121<AI121*0.95,"abaixo",IF(AB121>AI121*1.05,"acima","em linha"))),"") | AK121: não | AO121: =A121 | AP121: =D121
A122: 6.5051.0673129.0 | B122: 673129 | C122: =IFERROR(LOWER(SUBSTITUTE(SUBSTITUTE(SUBSTITUTE(SUBSTITUTE(D122," ","-"),"/","-"),".",""),",","")),"") | D122: VALVULA RETENCION DOBLE PILOTADA AEREA 30LPM (VLVDT015) | F122: SOHIPREN | H122: draft | I122: BALDAN | J122: PLANTADEIRA | K122: MARCADOR DE LINHA | L122: VÁLVULA SEQUENCIA | R122: =IFERROR(IF(AND(O122>0,P122>0,Q122>0),(O122*P122*Q122)/6000,""),"") | S122: =IFERROR(IF(AND(N122>0,R122>0),MAX(N122,R122),IF(N122>0,N122,IF(R122>0,R122,""))),"") | U122: FALTA | V122: 900 | W122: 0.3 | X122: =IFERROR(V122+T122,"") | Y122: =IFERROR(IF(W122<1,X122/(1-W122),""),"") | Z122: ='01_CONFIG_GLOBAL'!$C$14 | AA122: =IFERROR(Y122*Z122,"") | AB122: =IFERROR(IF(Z122<1,Y122/(1-Z122),""),"") | AI122: =IFERROR(AVERAGE(AD122,AF122,AH122),"") | AJ122: =IFERROR(IF(AI122="","sem dados",IF(AB122<AI122*0.95,"abaixo",IF(AB122>AI122*1.05,"acima","em linha"))),"") | AK122: não | AO122: =A122 | AP122: =D122
A123: 5.0906.0580566.0 | B123: 580566 | C123: =IFERROR(LOWER(SUBSTITUTE(SUBSTITUTE(SUBSTITUTE(SUBSTITUTE(D123," ","-"),"/","-"),".",""),",","")),"") | D123: APR 50 201.1.24.83 (ADAPTADOR 24) (PROTOTIPO) | F123: SOHIPREN | H123: draft | I123: BALDAN | J123: TRATOR DE PNEUS | K123: PRINCIPAL | L123: EIXO 14 DENTES 1.1/4' | R123: =IFERROR(IF(AND(O123>0,P123>0,Q123>0),(O123*P123*Q123)/6000,""),"") | S123: =IFERROR(IF(AND(N123>0,R123>0),MAX(N123,R123),IF(N123>0,N123,IF(R123>0,R123,""))),"") | U123: FALTA | V123: 1018.22 | W123: 0.3 | X123: =IFERROR(V123+T123,"") | Y123: =IFERROR(IF(W123<1,X123/(1-W123),""),"") | Z123: ='01_CONFIG_GLOBAL'!$C$14 | AA123: =IFERROR(Y123*Z123,"") | AB123: =IFERROR(IF(Z123<1,Y123/(1-Z123),""),"") | AI123: =IFERROR(AVERAGE(AD123,AF123,AH123),"") | AJ123: =IFERROR(IF(AI123="","sem dados",IF(AB123<AI123*0.95,"abaixo",IF(AB123>AI123*1.05,"acima","em linha"))),"") | AK123: não | AO123: =A123 | AP123: =D123
A124: 5.0220.L026898.0 | B124: L026898 | C124: =IFERROR(LOWER(SUBSTITUTE(SUBSTITUTE(SUBSTITUTE(SUBSTITUTE(D124," ","-"),"/","-"),".",""),",","")),"") | D124: BOD 22,5 E4.C102.C134/11.C1/8.C1.L (C/ ADAPTADOR) | E124: Bombas Hidráulicas | F124: SOHIPREN | H124: draft | I124: BALDAN | J124: PULVERIZADOR | K124: BOMBA TRIPLA | R124: =IFERROR(IF(AND(O124>0,P124>0,Q124>0),(O124*P124*Q124)/6000,""),"") | S124: =IFERROR(IF(AND(N124>0,R124>0),MAX(N124,R124),IF(N124>0,N124,IF(R124>0,R124,""))),"") | U124: FALTA | V124: 1034 | W124: 0.3 | X124: =IFERROR(V124+T124,"") | Y124: =IFERROR(IF(W124<1,X124/(1-W124),""),"") | Z124: ='01_CONFIG_GLOBAL'!$C$14 | AA124: =IFERROR(Y124*Z124,"") | AB124: =IFERROR(IF(Z124<1,Y124/(1-Z124),""),"") | AI124: =IFERROR(AVERAGE(AD124,AF124,AH124),"") | AJ124: =IFERROR(IF(AI124="","sem dados",IF(AB124<AI124*0.95,"abaixo",IF(AB124>AI124*1.05,"acima","em linha"))),"") | AK124: não | AO124: =A124 | AP124: =D124
A125: 5.0504.0503013.0 | B125: 503013 | C125: =IFERROR(LOWER(SUBSTITUTE(SUBSTITUTE(SUBSTITUTE(SUBSTITUTE(D125," ","-"),"/","-"),".",""),",","")),"") | D125: MC1 40 201.1.12.83-1.61 | F125: SOHIPREN | H125: draft | I125: BALDAN | J125: TRATOR DE PNEUS | K125: PRINCIPAL | L125: EIXO CONICO | R125: =IFERROR(IF(AND(O125>0,P125>0,Q125>0),(O125*P125*Q125)/6000,""),"") | S125: =IFERROR(IF(AND(N125>0,R125>0),MAX(N125,R125),IF(N125>0,N125,IF(R125>0,R125,""))),"") | U125: FALTA | V125: 1045 | W125: 0.3 | X125: =IFERROR(V125+T125,"") | Y125: =IFERROR(IF(W125<1,X125/(1-W125),""),"") | Z125: ='01_CONFIG_GLOBAL'!$C$14 | AA125: =IFERROR(Y125*Z125,"") | AB125: =IFERROR(IF(Z125<1,Y125/(1-Z125),""),"") | AI125: =IFERROR(AVERAGE(AD125,AF125,AH125),"") | AJ125: =IFERROR(IF(AI125="","sem dados",IF(AB125<AI125*0.95,"abaixo",IF(AB125>AI125*1.05,"acima","em linha"))),"") | AK125: não | AO125: =A125 | AP125: =D125
A126: 5.0504.0503014.0 | B126: 503014 | C126: =IFERROR(LOWER(SUBSTITUTE(SUBSTITUTE(SUBSTITUTE(SUBSTITUTE(D126," ","-"),"/","-"),".",""),",","")),"") | D126: MC1 40 201.1.21.83-1.61 | F126: SOHIPREN | H126: draft | I126: BALDAN | J126: TRATOR DE PNEUS | K126: PRINCIPAL | L126: EIXO ESTRIADO | R126: =IFERROR(IF(AND(O126>0,P126>0,Q126>0),(O126*P126*Q126)/6000,""),"") | S126: =IFERROR(IF(AND(N126>0,R126>0),MAX(N126,R126),IF(N126>0,N126,IF(R126>0,R126,""))),"") | U126: FALTA | V126: 1045 | W126: 0.3 | X126: =IFERROR(V126+T126,"") | Y126: =IFERROR(IF(W126<1,X126/(1-W126),""),"") | Z126: ='01_CONFIG_GLOBAL'!$C$14 | AA126: =IFERROR(Y126*Z126,"") | AB126: =IFERROR(IF(Z126<1,Y126/(1-Z126),""),"") | AI126: =IFERROR(AVERAGE(AD126,AF126,AH126),"") | AJ126: =IFERROR(IF(AI126="","sem dados",IF(AB126<AI126*0.95,"abaixo",IF(AB126>AI126*1.05,"acima","em linha"))),"") | AK126: não | AO126: =A126 | AP126: =D126
A127: 5.0504.0503017.0 | B127: 503017 | C127: =IFERROR(LOWER(SUBSTITUTE(SUBSTITUTE(SUBSTITUTE(SUBSTITUTE(D127," ","-"),"/","-"),".",""),",","")),"") | D127: MC1 40 201.1.37.83.61 | F127: SOHIPREN | H127: draft | I127: BALDAN | J127: TRATOR DE PNEUS | K127: PRINCIPAL | L127: EIXO CHAV. 1 | R127: =IFERROR(IF(AND(O127>0,P127>0,Q127>0),(O127*P127*Q127)/6000,""),"") | S127: =IFERROR(IF(AND(N127>0,R127>0),MAX(N127,R127),IF(N127>0,N127,IF(R127>0,R127,""))),"") | U127: FALTA | V127: 1150 | W127: 0.3 | X127: =IFERROR(V127+T127,"") | Y127: =IFERROR(IF(W127<1,X127/(1-W127),""),"") | Z127: ='01_CONFIG_GLOBAL'!$C$14 | AA127: =IFERROR(Y127*Z127,"") | AB127: =IFERROR(IF(Z127<1,Y127/(1-Z127),""),"") | AI127: =IFERROR(AVERAGE(AD127,AF127,AH127),"") | AJ127: =IFERROR(IF(AI127="","sem dados",IF(AB127<AI127*0.95,"abaixo",IF(AB127>AI127*1.05,"acima","em linha"))),"") | AK127: não | AO127: =A127 | AP127: =D127
A128: 5.5209.L012960.0 | B128: L01296 | C128: =IFERROR(LOWER(SUBSTITUTE(SUBSTITUTE(SUBSTITUTE(SUBSTITUTE(D128," ","-"),"/","-"),".",""),",","")),"") | D128: MRBO 19 E4.C1.C3.L (C/ ADAPT) | F128: SOHIPREN | H128: draft | I128: BASCOPRENS | R128: =IFERROR(IF(AND(O128>0,P128>0,Q128>0),(O128*P128*Q128)/6000,""),"") | S128: =IFERROR(IF(AND(N128>0,R128>0),MAX(N128,R128),IF(N128>0,N128,IF(R128>0,R128,""))),"") | U128: FALTA | V128: 708 | W128: 0.3 | X128: =IFERROR(V128+T128,"") | Y128: =IFERROR(IF(W128<1,X128/(1-W128),""),"") | Z128: ='01_CONFIG_GLOBAL'!$C$14 | AA128: =IFERROR(Y128*Z128,"") | AB128: =IFERROR(IF(Z128<1,Y128/(1-Z128),""),"") | AI128: =IFERROR(AVERAGE(AD128,AF128,AH128),"") | AJ128: =IFERROR(IF(AI128="","sem dados",IF(AB128<AI128*0.95,"abaixo",IF(AB128>AI128*1.05,"acima","em linha"))),"") | AK128: não | AO128: =A128 | AP128: =D128
A129: 5.0701.0503810.0 | B129: 503810 | C129: =IFERROR(LOWER(SUBSTITUTE(SUBSTITUTE(SUBSTITUTE(SUBSTITUTE(D129," ","-"),"/","-"),".",""),",","")),"") | D129: MD1 60 201.3.31.93 (ACC NEUMATICO 2 POS.) | F129: SOHIPREN | H129: draft | I129: BASCULANTE | J129: CAMINHAO BASCULANTE | K129: PRINCIPAL | L129: BHM 200 | R129: =IFERROR(IF(AND(O129>0,P129>0,Q129>0),(O129*P129*Q129)/6000,""),"") | S129: =IFERROR(IF(AND(N129>0,R129>0),MAX(N129,R129),IF(N129>0,N129,IF(R129>0,R129,""))),"") | U129: FALTA | V129: 330 | W129: 0.3 | X129: =IFERROR(V129+T129,"") | Y129: =IFERROR(IF(W129<1,X129/(1-W129),""),"") | Z129: ='01_CONFIG_GLOBAL'!$C$14 | AA129: =IFERROR(Y129*Z129,"") | AB129: =IFERROR(IF(Z129<1,Y129/(1-Z129),""),"") | AI129: =IFERROR(AVERAGE(AD129,AF129,AH129),"") | AJ129: =IFERROR(IF(AI129="","sem dados",IF(AB129<AI129*0.95,"abaixo",IF(AB129>AI129*1.05,"acima","em linha"))),"") | AK129: não | AO129: =A129 | AP129: =D129
A130: 5.0702.0503811.0 | B130: 503811 | C130: =IFERROR(LOWER(SUBSTITUTE(SUBSTITUTE(SUBSTITUTE(SUBSTITUTE(D130," ","-"),"/","-"),".",""),",","")),"") | D130: MD1 75 205.1.23.92 (SALIDA POSTERIOR) | F130: SOHIPREN | H130: draft | I130: BASCULANTE | J130: CAMINHÃO BASCULANTE | K130: PRINCIPAL | L130: BHM 200 | R130: =IFERROR(IF(AND(O130>0,P130>0,Q130>0),(O130*P130*Q130)/6000,""),"") | S130: =IFERROR(IF(AND(N130>0,R130>0),MAX(N130,R130),IF(N130>0,N130,IF(R130>0,R130,""))),"") | U130: FALTA | V130: 1078 | W130: 0.3 | X130: =IFERROR(V130+T130,"") | Y130: =IFERROR(IF(W130<1,X130/(1-W130),""),"") | Z130: ='01_CONFIG_GLOBAL'!$C$14 | AA130: =IFERROR(Y130*Z130,"") | AB130: =IFERROR(IF(Z130<1,Y130/(1-Z130),""),"") | AI130: =IFERROR(AVERAGE(AD130,AF130,AH130),"") | AJ130: =IFERROR(IF(AI130="","sem dados",IF(AB130<AI130*0.95,"abaixo",IF(AB130>AI130*1.05,"acima","em linha"))),"") | AK130: não | AO130: =A130 | AP130: =D130
A131: 5.0703.0503813.0 | B131: 503813 | C131: =IFERROR(LOWER(SUBSTITUTE(SUBSTITUTE(SUBSTITUTE(SUBSTITUTE(D131," ","-"),"/","-"),".",""),",","")),"") | D131: MD1 90 201.3.31.93 (ACC NEUMATICO 2 POS.) | F131: SOHIPREN | H131: draft | I131: BASCULANTE | J131: CAMINHÃO BASCULANTE | K131: PRINCIPAL | L131: BHM 200 | R131: =IFERROR(IF(AND(O131>0,P131>0,Q131>0),(O131*P131*Q131)/6000,""),"") | S131: =IFERROR(IF(AND(N131>0,R131>0),MAX(N131,R131),IF(N131>0,N131,IF(R131>0,R131,""))),"") | U131: FALTA | V131: 1078 | W131: 0.3 | X131: =IFERROR(V131+T131,"") | Y131: =IFERROR(IF(W131<1,X131/(1-W131),""),"") | Z131: ='01_CONFIG_GLOBAL'!$C$14 | AA131: =IFERROR(Y131*Z131,"") | AB131: =IFERROR(IF(Z131<1,Y131/(1-Z131),""),"") | AI131: =IFERROR(AVERAGE(AD131,AF131,AH131),"") | AJ131: =IFERROR(IF(AI131="","sem dados",IF(AB131<AI131*0.95,"abaixo",IF(AB131>AI131*1.05,"acima","em linha"))),"") | AK131: não | AO131: =A131 | AP131: =D131
A132: 5.0701.0503799.0 | B132: 503799 | C132: =IFERROR(LOWER(SUBSTITUTE(SUBSTITUTE(SUBSTITUTE(SUBSTITUTE(D132," ","-"),"/","-"),".",""),",","")),"") | D132: MD1 60 205.2.23.92 (MANUAL 2 POS.) | F132: SOHIPREN | H132: draft | I132: BASCULANTE | J132: CAMINHAO BASCULANTE | K132: PRINCIPAL | L132: BHM 200 | R132: =IFERROR(IF(AND(O132>0,P132>0,Q132>0),(O132*P132*Q132)/6000,""),"") | S132: =IFERROR(IF(AND(N132>0,R132>0),MAX(N132,R132),IF(N132>0,N132,IF(R132>0,R132,""))),"") | U132: FALTA | V132: 330 | W132: 0.3 | X132: =IFERROR(V132+T132,"") | Y132: =IFERROR(IF(W132<1,X132/(1-W132),""),"") | Z132: ='01_CONFIG_GLOBAL'!$C$14 | AA132: =IFERROR(Y132*Z132,"") | AB132: =IFERROR(IF(Z132<1,Y132/(1-Z132),""),"") | AI132: =IFERROR(AVERAGE(AD132,AF132,AH132),"") | AJ132: =IFERROR(IF(AI132="","sem dados",IF(AB132<AI132*0.95,"abaixo",IF(AB132>AI132*1.05,"acima","em linha"))),"") | AK132: não | AO132: =A132 | AP132: =D132
A133: 5.0701.0503774.0 | B133: 503774 | C133: =IFERROR(LOWER(SUBSTITUTE(SUBSTITUTE(SUBSTITUTE(SUBSTITUTE(D133," ","-"),"/","-"),".",""),",","")),"") | D133: MD1 60 205.1.23.92 (MANUAL 2 POS.) | F133: SOHIPREN | H133: draft | I133: BASCULANTE | J133: CAMINHÃO BASCULANTE | K133: PRINCIPAL | L133: BHM 200 | R133: =IFERROR(IF(AND(O133>0,P133>0,Q133>0),(O133*P133*Q133)/6000,""),"") | S133: =IFERROR(IF(AND(N133>0,R133>0),MAX(N133,R133),IF(N133>0,N133,IF(R133>0,R133,""))),"") | U133: FALTA | V133: 330 | W133: 0.3 | X133: =IFERROR(V133+T133,"") | Y133: =IFERROR(IF(W133<1,X133/(1-W133),""),"") | Z133: ='01_CONFIG_GLOBAL'!$C$14 | AA133: =IFERROR(Y133*Z133,"") | AB133: =IFERROR(IF(Z133<1,Y133/(1-Z133),""),"") | AI133: =IFERROR(AVERAGE(AD133,AF133,AH133),"") | AJ133: =IFERROR(IF(AI133="","sem dados",IF(AB133<AI133*0.95,"abaixo",IF(AB133>AI133*1.05,"acima","em linha"))),"") | AK133: não | AO133: =A133 | AP133: =D133
A134: 5.0702.0503775.0 | B134: 503775 | C134: =IFERROR(LOWER(SUBSTITUTE(SUBSTITUTE(SUBSTITUTE(SUBSTITUTE(D134," ","-"),"/","-"),".",""),",","")),"") | D134: MD1 75 205.1.23.92 (MANUAL 2 POS.) | F134: SOHIPREN | H134: draft | I134: BASCULANTE | J134: CAMINHÃO BASCULANTE | K134: PRINCIPAL | L134: BHM 200 | R134: =IFERROR(IF(AND(O134>0,P134>0,Q134>0),(O134*P134*Q134)/6000,""),"") | S134: =IFERROR(IF(AND(N134>0,R134>0),MAX(N134,R134),IF(N134>0,N134,IF(R134>0,R134,""))),"") | U134: FALTA | V134: 1078 | W134: 0.3 | X134: =IFERROR(V134+T134,"") | Y134: =IFERROR(IF(W134<1,X134/(1-W134),""),"") | Z134: ='01_CONFIG_GLOBAL'!$C$14 | AA134: =IFERROR(Y134*Z134,"") | AB134: =IFERROR(IF(Z134<1,Y134/(1-Z134),""),"") | AI134: =IFERROR(AVERAGE(AD134,AF134,AH134),"") | AJ134: =IFERROR(IF(AI134="","sem dados",IF(AB134<AI134*0.95,"abaixo",IF(AB134>AI134*1.05,"acima","em linha"))),"") | AK134: não | AO134: =A134 | AP134: =D134
A135: 5.0703.0503776.0 | B135: 503776 | C135: =IFERROR(LOWER(SUBSTITUTE(SUBSTITUTE(SUBSTITUTE(SUBSTITUTE(D135," ","-"),"/","-"),".",""),",","")),"") | D135: MD1 90 205.1.23.92 (MANUAL 2 POS.) | F135: SOHIPREN | H135: draft | I135: BASCULANTE | J135: CAMINHAO BASCULANTE | K135: PRINCIPAL | L135: BHM 200 | R135: =IFERROR(IF(AND(O135>0,P135>0,Q135>0),(O135*P135*Q135)/6000,""),"") | S135: =IFERROR(IF(AND(N135>0,R135>0),MAX(N135,R135),IF(N135>0,N135,IF(R135>0,R135,""))),"") | U135: FALTA | V135: 1078 | W135: 0.3 | X135: =IFERROR(V135+T135,"") | Y135: =IFERROR(IF(W135<1,X135/(1-W135),""),"") | Z135: ='01_CONFIG_GLOBAL'!$C$14 | AA135: =IFERROR(Y135*Z135,"") | AB135: =IFERROR(IF(Z135<1,Y135/(1-Z135),""),"") | AI135: =IFERROR(AVERAGE(AD135,AF135,AH135),"") | AJ135: =IFERROR(IF(AI135="","sem dados",IF(AB135<AI135*0.95,"abaixo",IF(AB135>AI135*1.05,"acima","em linha"))),"") | AK135: não | AO135: =A135 | AP135: =D135
A136: 5.0701.0503778.0 | B136: 503778 | C136: =IFERROR(LOWER(SUBSTITUTE(SUBSTITUTE(SUBSTITUTE(SUBSTITUTE(D136," ","-"),"/","-"),".",""),",","")),"") | D136: MD1 60 205.1.23.93 (ACC NEUMATICO 2 POS.) | F136: SOHIPREN | H136: draft | I136: BASCULANTE | J136: CAMINHÃO BASCULANTE | K136: PRINCIPAL | L136: BHM 200 | R136: =IFERROR(IF(AND(O136>0,P136>0,Q136>0),(O136*P136*Q136)/6000,""),"") | S136: =IFERROR(IF(AND(N136>0,R136>0),MAX(N136,R136),IF(N136>0,N136,IF(R136>0,R136,""))),"") | U136: FALTA | V136: 330 | W136: 0.3 | X136: =IFERROR(V136+T136,"") | Y136: =IFERROR(IF(W136<1,X136/(1-W136),""),"") | Z136: ='01_CONFIG_GLOBAL'!$C$14 | AA136: =IFERROR(Y136*Z136,"") | AB136: =IFERROR(IF(Z136<1,Y136/(1-Z136),""),"") | AI136: =IFERROR(AVERAGE(AD136,AF136,AH136),"") | AJ136: =IFERROR(IF(AI136="","sem dados",IF(AB136<AI136*0.95,"abaixo",IF(AB136>AI136*1.05,"acima","em linha"))),"") | AK136: não | AO136: =A136 | AP136: =D136
A137: 5.0702.0503779.0 | B137: 503779 | C137: =IFERROR(LOWER(SUBSTITUTE(SUBSTITUTE(SUBSTITUTE(SUBSTITUTE(D137," ","-"),"/","-"),".",""),",","")),"") | D137: MD1 75 205.1.23.93 (ACC NEUMATICO 2 POS.) | F137: SOHIPREN | H137: draft | I137: BASCULANTE | J137: CAMINHAO BASCULANTE | K137: PRINCIPAL | L137: BHM 200 | R137: =IFERROR(IF(AND(O137>0,P137>0,Q137>0),(O137*P137*Q137)/6000,""),"") | S137: =IFERROR(IF(AND(N137>0,R137>0),MAX(N137,R137),IF(N137>0,N137,IF(R137>0,R137,""))),"") | U137: FALTA | V137: 1078 | W137: 0.3 | X137: =IFERROR(V137+T137,"") | Y137: =IFERROR(IF(W137<1,X137/(1-W137),""),"") | Z137: ='01_CONFIG_GLOBAL'!$C$14 | AA137: =IFERROR(Y137*Z137,"") | AB137: =IFERROR(IF(Z137<1,Y137/(1-Z137),""),"") | AI137: =IFERROR(AVERAGE(AD137,AF137,AH137),"") | AJ137: =IFERROR(IF(AI137="","sem dados",IF(AB137<AI137*0.95,"abaixo",IF(AB137>AI137*1.05,"acima","em linha"))),"") | AK137: não | AO137: =A137 | AP137: =D137
A138: 5.0703.0503780.0 | B138: 503780 | C138: =IFERROR(LOWER(SUBSTITUTE(SUBSTITUTE(SUBSTITUTE(SUBSTITUTE(D138," ","-"),"/","-"),".",""),",","")),"") | D138: MD1 90 205.1.23.93 (ACC NEUMATICO 2 POS) | F138: SOHIPREN | H138: draft | I138: BASCULANTE | J138: CAMINHÃO BASCULANTE | K138: PRINCIPAL | L138: BHM 200 | R138: =IFERROR(IF(AND(O138>0,P138>0,Q138>0),(O138*P138*Q138)/6000,""),"") | S138: =IFERROR(IF(AND(N138>0,R138>0),MAX(N138,R138),IF(N138>0,N138,IF(R138>0,R138,""))),"") | U138: FALTA | V138: 1078 | W138: 0.3 | X138: =IFERROR(V138+T138,"") | Y138: =IFERROR(IF(W138<1,X138/(1-W138),""),"") | Z138: ='01_CONFIG_GLOBAL'!$C$14 | AA138: =IFERROR(Y138*Z138,"") | AB138: =IFERROR(IF(Z138<1,Y138/(1-Z138),""),"") | AI138: =IFERROR(AVERAGE(AD138,AF138,AH138),"") | AJ138: =IFERROR(IF(AI138="","sem dados",IF(AB138<AI138*0.95,"abaixo",IF(AB138>AI138*1.05,"acima","em linha"))),"") | AK138: não | AO138: =A138 | AP138: =D138
A139: 5.0701.0503782.0 | B139: 503782 | C139: =IFERROR(LOWER(SUBSTITUTE(SUBSTITUTE(SUBSTITUTE(SUBSTITUTE(D139," ","-"),"/","-"),".",""),",","")),"") | D139: MD1 60 201.3.31.92 (MANUAL 2 POS.) | F139: SOHIPREN | H139: draft | I139: BASCULANTE | J139: CAMINHÃO BASCULANTE | K139: PRINCIPAL | L139: BHM 200 | R139: =IFERROR(IF(AND(O139>0,P139>0,Q139>0),(O139*P139*Q139)/6000,""),"") | S139: =IFERROR(IF(AND(N139>0,R139>0),MAX(N139,R139),IF(N139>0,N139,IF(R139>0,R139,""))),"") | U139: FALTA | V139: 330 | W139: 0.3 | X139: =IFERROR(V139+T139,"") | Y139: =IFERROR(IF(W139<1,X139/(1-W139),""),"") | Z139: ='01_CONFIG_GLOBAL'!$C$14 | AA139: =IFERROR(Y139*Z139,"") | AB139: =IFERROR(IF(Z139<1,Y139/(1-Z139),""),"") | AI139: =IFERROR(AVERAGE(AD139,AF139,AH139),"") | AJ139: =IFERROR(IF(AI139="","sem dados",IF(AB139<AI139*0.95,"abaixo",IF(AB139>AI139*1.05,"acima","em linha"))),"") | AK139: não | AO139: =A139 | AP139: =D139
A140: 5.0702.0503712.0 | B140: 503712 | C140: =IFERROR(LOWER(SUBSTITUTE(SUBSTITUTE(SUBSTITUTE(SUBSTITUTE(D140," ","-"),"/","-"),".",""),",","")),"") | D140: MD1 75 201.3.31.92 (MANUAL 2 POS.) | F140: SOHIPREN | H140: draft | I140: BASCULANTE | J140: CAMINHAO BASCULANTE | K140: PRINCIPAL | L140: BHM 200 | R140: =IFERROR(IF(AND(O140>0,P140>0,Q140>0),(O140*P140*Q140)/6000,""),"") | S140: =IFERROR(IF(AND(N140>0,R140>0),MAX(N140,R140),IF(N140>0,N140,IF(R140>0,R140,""))),"") | U140: FALTA | V140: 1078 | W140: 0.3 | X140: =IFERROR(V140+T140,"") | Y140: =IFERROR(IF(W140<1,X140/(1-W140),""),"") | Z140: ='01_CONFIG_GLOBAL'!$C$14 | AA140: =IFERROR(Y140*Z140,"") | AB140: =IFERROR(IF(Z140<1,Y140/(1-Z140),""),"") | AI140: =IFERROR(AVERAGE(AD140,AF140,AH140),"") | AJ140: =IFERROR(IF(AI140="","sem dados",IF(AB140<AI140*0.95,"abaixo",IF(AB140>AI140*1.05,"acima","em linha"))),"") | AK140: não | AO140: =A140 | AP140: =D140
... A142: 5.0702.0503628.0 | B142: 503628 | C142: =IFERROR(LOWER(SUBSTITUTE(SUBSTITUTE(SUBSTITUTE(SUBSTITUTE(D142," ","-"),"/","-"),".",""),",","")),"") | D142: MD1 75 201.3.31.93 (ACC NEUMATICO 2 POS.) | F142: SOHIPREN | H142: draft | I142: BASCULANTE | J142: CAMINHÃO BASCULANTE | K142: PRINCIPAL | L142: BHM 200 | R142: =IFERROR(IF(AND(O142>0,P142>0,Q142>0),(O142*P142*Q142)/6000,""),"") | S142: =IFERROR(IF(AND(N142>0,R142>0),MAX(N142,R142),IF(N142>0,N142,IF(R142>0,R142,""))),"") | U142: FALTA | V142: 330 | W142: 0.3 | X142: =IFERROR(V142+T142,"") | Y142: =IFERROR(IF(W142<1,X142/(1-W142),""),"") | Z142: ='01_CONFIG_GLOBAL'!$C$14 | AA142: =IFERROR(Y142*Z142,"") | AB142: =IFERROR(IF(Z142<1,Y142/(1-Z142),""),"") | AI142: =IFERROR(AVERAGE(AD142,AF142,AH142),"") | AJ142: =IFERROR(IF(AI142="","sem dados",IF(AB142<AI142*0.95,"abaixo",IF(AB142>AI142*1.05,"acima","em linha"))),"") | AK142: não | AO142: =A142 | AP142: =D142
A143: 5.0208.0544827.0 | B143: 544827 | C143: =IFERROR(LOWER(SUBSTITUTE(SUBSTITUTE(SUBSTITUTE(SUBSTITUTE(D143," ","-"),"/","-"),".",""),",","")),"") | D143: BOD 16 C4.C.C3.L (ADAPTADOR C4) | E143: Bombas Hidráulicas | F143: SOHIPREN | H143: draft | I143: BOELTER | J143: NIVELADORA | K143: PRINCIPAL | R143: =IFERROR(IF(AND(O143>0,P143>0,Q143>0),(O143*P143*Q143)/6000,""),"") | S143: =IFERROR(IF(AND(N143>0,R143>0),MAX(N143,R143),IF(N143>0,N143,IF(R143>0,R143,""))),"") | U143: FALTA | V143: 605 | W143: 0.3 | X143: =IFERROR(V143+T143,"") | Y143: =IFERROR(IF(W143<1,X143/(1-W143),""),"") | Z143: ='01_CONFIG_GLOBAL'!$C$14 | AA143: =IFERROR(Y143*Z143,"") | AB143: =IFERROR(IF(Z143<1,Y143/(1-Z143),""),"") | AI143: =IFERROR(AVERAGE(AD143,AF143,AH143),"") | AJ143: =IFERROR(IF(AI143="","sem dados",IF(AB143<AI143*0.95,"abaixo",IF(AB143>AI143*1.05,"acima","em linha"))),"") | AK143: não | AO143: =A143 | AP143: =D143
A144: 5.0521.L025882.0 | B144: L025882 | C144: =IFERROR(LOWER(SUBSTITUTE(SUBSTITUTE(SUBSTITUTE(SUBSTITUTE(D144," ","-"),"/","-"),".",""),",","")),"") | D144: MC1 26 201.2.21.93/19.A.L | F144: SOHIPREN | H144: draft | I144: BOSCH | L144: R979012920 | R144: =IFERROR(IF(AND(O144>0,P144>0,Q144>0),(O144*P144*Q144)/6000,""),"") | S144: =IFERROR(IF(AND(N144>0,R144>0),MAX(N144,R144),IF(N144>0,N144,IF(R144>0,R144,""))),"") | U144: FALTA | V144: 1823.2 | W144: 0.3 | X144: =IFERROR(V144+T144,"") | Y144: =IFERROR(IF(W144<1,X144/(1-W144),""),"") | Z144: ='01_CONFIG_GLOBAL'!$C$14 | AA144: =IFERROR(Y144*Z144,"") | AB144: =IFERROR(IF(Z144<1,Y144/(1-Z144),""),"") | AI144: =IFERROR(AVERAGE(AD144,AF144,AH144),"") | AJ144: =IFERROR(IF(AI144="","sem dados",IF(AB144<AI144*0.95,"abaixo",IF(AB144>AI144*1.05,"acima","em linha"))),"") | AK144: não | AO144: =A144 | AP144: =D144
A145: 5.0521.L025887.0 | B145: L025887 | C145: =IFERROR(LOWER(SUBSTITUTE(SUBSTITUTE(SUBSTITUTE(SUBSTITUTE(D145," ","-"),"/","-"),".",""),",","")),"") | D145: MC1 26.201.1.21.314/22,5.A.L | F145: SOHIPREN | H145: draft | I145: BOSCH | R145: =IFERROR(IF(AND(O145>0,P145>0,Q145>0),(O145*P145*Q145)/6000,""),"") | S145: =IFERROR(IF(AND(N145>0,R145>0),MAX(N145,R145),IF(N145>0,N145,IF(R145>0,R145,""))),"") | U145: FALTA | V145: 1650 | W145: 0.3 | X145: =IFERROR(V145+T145,"") | Y145: =IFERROR(IF(W145<1,X145/(1-W145),""),"") | Z145: ='01_CONFIG_GLOBAL'!$C$14 | AA145: =IFERROR(Y145*Z145,"") | AB145: =IFERROR(IF(Z145<1,Y145/(1-Z145),""),"") | AI145: =IFERROR(AVERAGE(AD145,AF145,AH145),"") | AJ145: =IFERROR(IF(AI145="","sem dados",IF(AB145<AI145*0.95,"abaixo",IF(AB145>AI145*1.05,"acima","em linha"))),"") | AK145: não | AO145: =A145 | AP145: =D145
A146: 5.0202.0540029.0 | B146: 540029 | C146: =IFERROR(LOWER(SUBSTITUTE(SUBSTITUTE(SUBSTITUTE(SUBSTITUTE(D146," ","-"),"/","-"),".",""),",","")),"") | D146: BOD 4 C11.P1.C27.L | E146: Bombas Hidráulicas | F146: SOHIPREN | H146: draft | I146: BOSCH | J146: DIVERSOS | L146: F000510204 / 41076503 / | R146: =IFERROR(IF(AND(O146>0,P146>0,Q146>0),(O146*P146*Q146)/6000,""),"") | S146: =IFERROR(IF(AND(N146>0,R146>0),MAX(N146,R146),IF(N146>0,N146,IF(R146>0,R146,""))),"") | U146: FALTA | V146: 620 | W146: 0.3 | X146: =IFERROR(V146+T146,"") | Y146: =IFERROR(IF(W146<1,X146/(1-W146),""),"") | Z146: ='01_CONFIG_GLOBAL'!$C$14 | AA146: =IFERROR(Y146*Z146,"") | AB146: =IFERROR(IF(Z146<1,Y146/(1-Z146),""),"") | AI146: =IFERROR(AVERAGE(AD146,AF146,AH146),"") | AJ146: =IFERROR(IF(AI146="","sem dados",IF(AB146<AI146*0.95,"abaixo",IF(AB146>AI146*1.05,"acima","em linha"))),"") | AK146: não | AO146: =A146 | AP146: =D146
A147: 5.0201.0540617.0 | B147: 540617 | C147: =IFERROR(LOWER(SUBSTITUTE(SUBSTITUTE(SUBSTITUTE(SUBSTITUTE(D147," ","-"),"/","-"),".",""),",","")),"") | D147: BOD 2,5 C11.C.C27.L | E147: Bombas Hidráulicas | F147: SOHIPREN | H147: draft | I147: BOSCH | J147: DIVERSOS | L147: F000510100 | R147: =IFERROR(IF(AND(O147>0,P147>0,Q147>0),(O147*P147*Q147)/6000,""),"") | S147: =IFERROR(IF(AND(N147>0,R147>0),MAX(N147,R147),IF(N147>0,N147,IF(R147>0,R147,""))),"") | U147: FALTA | V147: 665 | W147: 0.3 | X147: =IFERROR(V147+T147,"") | Y147: =IFERROR(IF(W147<1,X147/(1-W147),""),"") | Z147: ='01_CONFIG_GLOBAL'!$C$14 | AA147: =IFERROR(Y147*Z147,"") | AB147: =IFERROR(IF(Z147<1,Y147/(1-Z147),""),"") | AI147: =IFERROR(AVERAGE(AD147,AF147,AH147),"") | AJ147: =IFERROR(IF(AI147="","sem dados",IF(AB147<AI147*0.95,"abaixo",IF(AB147>AI147*1.05,"acima","em linha"))),"") | AK147: não | AO147: =A147 | AP147: =D147
A148: 5.0220.L027089.0 | B148: L027089 | C148: =IFERROR(LOWER(SUBSTITUTE(SUBSTITUTE(SUBSTITUTE(SUBSTITUTE(D148," ","-"),"/","-"),".",""),",","")),"") | D148: BOMBA HIDRÁULICA - APLICAÇÃO 19 B2 P100.B116/11.B117.L | E148: Bombas Hidráulicas | F148: SOHIPREN | H148: draft | I148: BOSCH / REXROTH | L148: R979107648 | R148: =IFERROR(IF(AND(O148>0,P148>0,Q148>0),(O148*P148*Q148)/6000,""),"") | S148: =IFERROR(IF(AND(N148>0,R148>0),MAX(N148,R148),IF(N148>0,N148,IF(R148>0,R148,""))),"") | U148: FALTA | V148: 1935 | W148: 0.3 | X148: =IFERROR(V148+T148,"") | Y148: =IFERROR(IF(W148<1,X148/(1-W148),""),"") | Z148: ='01_CONFIG_GLOBAL'!$C$14 | AA148: =IFERROR(Y148*Z148,"") | AB148: =IFERROR(IF(Z148<1,Y148/(1-Z148),""),"") | AI148: =IFERROR(AVERAGE(AD148,AF148,AH148),"") | AJ148: =IFERROR(IF(AI148="","sem dados",IF(AB148<AI148*0.95,"abaixo",IF(AB148>AI148*1.05,"acima","em linha"))),"") | AK148: não | AO148: =A148 | AP148: =D148
A149: 5.0210.0546431.0 | B149: 546431 | C149: =IFERROR(LOWER(SUBSTITUTE(SUBSTITUTE(SUBSTITUTE(SUBSTITUTE(D149," ","-"),"/","-"),".",""),",","")),"") | D149: BOD 22,5 B1.P1.A.L | E149: Bombas Hidráulicas | F149: SOHIPREN | H149: draft | I149: BOSCH / SCHWING-SIW / SKAM | J149: SKAM | L149: 9510080720/0510725030/13300350/41086203 | R149: =IFERROR(IF(AND(O149>0,P149>0,Q149>0),(O149*P149*Q149)/6000,""),"") | S149: =IFERROR(IF(AND(N149>0,R149>0),MAX(N149,R149),IF(N149>0,N149,IF(R149>0,R149,""))),"") | U149: FALTA | V149: 605 | W149: 0.3 | X149: =IFERROR(V149+T149,"") | Y149: =IFERROR(IF(W149<1,X149/(1-W149),""),"") | Z149: ='01_CONFIG_GLOBAL'!$C$14 | AA149: =IFERROR(Y149*Z149,"") | AB149: =IFERROR(IF(Z149<1,Y149/(1-Z149),""),"") | AI149: =IFERROR(AVERAGE(AD149,AF149,AH149),"") | AJ149: =IFERROR(IF(AI149="","sem dados",IF(AB149<AI149*0.95,"abaixo",IF(AB149>AI149*1.05,"acima","em linha"))),"") | AK149: não | AO149: =A149 | AP149: =D149
A150: 5.0103.0569015.0 | B150: 569015 | C150: =IFERROR(LOWER(SUBSTITUTE(SUBSTITUTE(SUBSTITUTE(SUBSTITUTE(D150," ","-"),"/","-"),".",""),",","")),"") | D150: B1I 2,1 A.B7.G.G4 | F150: SOHIPREN | H150: draft | I150: BOSCH REXROTH | K150: PRINCIPAL | L150: 0510112307/R979021467 | R150: =IFERROR(IF(AND(O150>0,P150>0,Q150>0),(O150*P150*Q150)/6000,""),"") | S150: =IFERROR(IF(AND(N150>0,R150>0),MAX(N150,R150),IF(N150>0,N150,IF(R150>0,R150,""))),"") | U150: FALTA | V150: 694 | W150: 0.3 | X150: =IFERROR(V150+T150,"") | Y150: =IFERROR(IF(W150<1,X150/(1-W150),""),"") | Z150: ='01_CONFIG_GLOBAL'!$C$14 | AA150: =IFERROR(Y150*Z150,"") | AB150: =IFERROR(IF(Z150<1,Y150/(1-Z150),""),"") | AI150: =IFERROR(AVERAGE(AD150,AF150,AH150),"") | AJ150: =IFERROR(IF(AI150="","sem dados",IF(AB150<AI150*0.95,"abaixo",IF(AB150>AI150*1.05,"acima","em linha"))),"") | AK150: não | AO150: =A150 | AP150: =D150
...

Sheet 03_AGCO
A1: APP — Agro Peças Padrão | Master 05_AGCO
A2: Total de SKUs: | B2: =COUNTA(A6:A99997) | D2: Faltando embalagem: | E2: =COUNTIF(X6:X99997,"FALTA") | G2: Cadastrados Shopify: | H2: =COUNTIF(AN6:AN99997,"sim") | J2: Divergentes: | K2: =COUNTIF(AN6:AN99997,"divergente")
A4: IDENTIFICAÇÃO | I4: APLICAÇÃO TÉCNICA | P4: LOGÍSTICA E EMBALAGEM | Y4: CUSTO E PRECIFICAÇÃO | AF4: PESQUISA DE MERCADO | AN4: WORKFLOW
A5: SKU / Código | B5: Part Number | C5: Handle (Shopify) | D5: Title (PT-BR) | E5: Product Type | F5: Vendor (Fabricante) | G5: Tags (vírgula) | H5: Status | I5: Montadora compatível | J5: Equipamento / Modelo | K5: Função / Aplicação | L5: Códigos cruzados | M5: NCM | N5: Qtde KIT | O5: Lead Time | P5: Peso (kg) | Q5: Comprimento (cm) | R5: Largura (cm) | S5: Altura (cm) | T5: Peso cubado (kg) KIT | U5: Peso cubado (kg) | V5: Peso considerado (kg) | W5: Frete fábrica → eCom () | X5: Origem do dado embalagem | Y5: Custo unitário () | Z5: % Margem de lucro | AA5: Custo + frete inbound () | AB5: Preço c/ margem () | AC5: Taxa Mercado Pago (%) | AD5: Taxa MP () | AE5: Preço final site () | AF5: Concorrente 1 — Nome | AG5: Concorrente 1 — Preço () | AH5: Concorrente 2 — Nome | AI5: Concorrente 2 — Preço () | AJ5: Concorrente 3 — Nome | AK5: Concorrente 3 — Preço () | AL5: Preço médio concorrência () | AM5: Posicionamento | AN5: Cadastrado Shopify? | AO5: Última atualização | AP5: Operador responsável | AQ5: Instruções | AR5: Observações | AS5: SKU Shopify (derivado) | AT5: Título Shopify (derivado) | AU5: Imagens site (assets)
A6: ACX3266690 | B6: ACX3266690 | C6: =IFERROR(LOWER(SUBSTITUTE(SUBSTITUTE(SUBSTITUTE(SUBSTITUTE(D6," ","-"),"/","-"),".",""),",","")),"") | D6: Suporte do Dosador - AGCO ACX3266690 | Plantadeira Momentum | E6: Peças Plásticas Injetadas | F6: APP | H6: active | I6: AGCO | J6: PLANTADEIRA | K6: =LOWER(CONCATENATE(E6," ",J6," ",D6)) | M6: 84329000 | N6: 1 | O6: 5 | P6: 0.36 | Q6: 12 | R6: 3 | S6: 6 | T6: =IFERROR(IF(AND(Q6>0,R6>0,S6>0),(Q6*R6*S6)/6000,""),"") | U6: =IFERROR(IF(AND(Q6>0,R6>0,S6>0),(Q6*R6*S6)/6000,""),"") | V6: =IFERROR(IF(AND(P6>0,U6>0),MAX(P6,U6),IF(P6>0,P6,IF(U6>0,U6,""))),"") | W6: 16.75 | X6: fornecedor | Y6: 100.96 | Z6: 0.2 | AA6: =IFERROR(Y6+W6,"") | AB6: =IFERROR(IF(Z6<1,AA6/(1-Z6),""),"") | AC6: ='01_CONFIG_GLOBAL'!$C$14 | AD6: =IFERROR(AB6*AC6,"") | AE6: =IFERROR(IF(AC6<1,AB6/(1-AC6),""),"") | AL6: =IFERROR(AVERAGE(AG6,AI6,AK6),"") | AM6: =IFERROR(IF(AL6="","sem dados",IF(AE6<AL6*0.95,"abaixo",IF(AE6>AL6*1.05,"acima","em linha"))),"") | AN6: sim | AR6: Fotos: assets/agco_ACX3266690_ecommerce_1.png; assets/agco_ACX3266690_ecommerce_2.png; assets/agco_ACX3266690_ecommerce_3.png | AS6: =IF(AND(N6<>"",N6>1),A6&"-KIT"&N6,A6) | AT6: =IF(AND(N6<>"",N6>1),D6&" — Kit "&N6&" unidades",D6) | AU6: agco_ACX3266690_ecommerce_1.png | agco_ACX3266690_ecommerce_2.png | agco_ACX3266690_ecommerce_3.png
A7: ACW0551840 | B7: ACW0551840 | C7: =IFERROR(LOWER(SUBSTITUTE(SUBSTITUTE(SUBSTITUTE(SUBSTITUTE(D7," ","-"),"/","-"),".",""),",","")),"") | D7: Condutor de Sementes para Sensor - AGCO ACW0551840 | E7: Peças Plásticas Injetadas | F7: APP | H7: active | I7: AGCO | J7: PLANTADEIRA | K7: =LOWER(CONCATENATE(E7," ",J7," ",D7)) | M7: 84329000 | N7: 1 | O7: 5 | P7: 0.35 | Q7: 50 | R7: 7 | S7: 4.5 | T7: =IFERROR(IF(AND(Q7>0,R7>0,S7>0),(Q7*R7*S7)/6000,""),"") | U7: =IFERROR(IF(AND(Q7>0,R7>0,S7>0),(Q7*R7*S7)/6000,""),"") | V7: =IFERROR(IF(AND(P7>0,U7>0),MAX(P7,U7),IF(P7>0,P7,IF(U7>0,U7,""))),"") | W7: 2.21 | X7: fornecedor | Y7: 9.15 | Z7: 0.2 | AA7: =IFERROR(Y7+W7,"") | AB7: =IFERROR(IF(Z7<1,AA7/(1-Z7),""),"") | AC7: ='01_CONFIG_GLOBAL'!$C$14 | AD7: =IFERROR(AB7*AC7,"") | AE7: =IFERROR(IF(AC7<1,AB7/(1-AC7),""),"") | AL7: =IFERROR(AVERAGE(AG7,AI7,AK7),"") | AM7: =IFERROR(IF(AL7="","sem dados",IF(AE7<AL7*0.95,"abaixo",IF(AE7>AL7*1.05,"acima","em linha"))),"") | AN7: sim | AR7: Fotos: assets/agco_ACW0551840_ecommerce_1.png; assets/agco_ACW0551840_ecommerce_2.png | CORRIGIDO 21/07: peso 3,5kg impossível p/ conduto plástico — estimado 0,35kg (verificar balança) | AS7: =IF(AND(N7<>"",N7>1),A7&"-KIT"&N7,A7) | AT7: =IF(AND(N7<>"",N7>1),D7&" — Kit "&N7&" unidades",D7) | AU7: agco_ACW0551840_ecommerce_1.png | agco_ACW0551840_ecommerce_2.png
A8: ACW0551840 | B8: ACW0551840 | C8: =IFERROR(LOWER(SUBSTITUTE(SUBSTITUTE(SUBSTITUTE(SUBSTITUTE(D8," ","-"),"/","-"),".",""),",","")),"") | D8: Condutor de Sementes para Sensor - Kit 25 Unidades - AGCO ACW0551840 | E8: Peças Plásticas Injetadas | F8: APP | H8: active | I8: AGCO | J8: PLANTADEIRA | K8: =LOWER(CONCATENATE(E8," ",J8," ",D8)) | M8: 84329000 | N8: 25 | O8: 5 | P8: =P7*N8 | Q8: 50 | R8: 25 | S8: 50 | T8: =IFERROR(IF(AND(Q8>0,R8>0,S8>0),(Q8*R8*S8)/6000,""),"") | U8: =IFERROR(IF(AND(Q8>0,R8>0,S8>0),(Q8*R8*S8)/6000,""),"") | V8: =IFERROR(IF(AND(P8>0,U8>0),MAX(P8,U8),IF(P8>0,P8,IF(U8>0,U8,""))),"") | W8: 55.23 | X8: fornecedor | Y8: 228.75 | Z8: 0.2 | AA8: =IFERROR(Y8+W8,"") | AB8: =IFERROR(IF(Z8<1,AA8/(1-Z8),""),"") | AC8: ='01_CONFIG_GLOBAL'!$C$14 | AD8: =IFERROR(AB8*AC8,"") | AE8: =IFERROR(IF(AC8<1,AB8/(1-AC8),""),"") | AM8: =IFERROR(IF(AL8="","sem dados",IF(AE8<AL8*0.95,"abaixo",IF(AE8>AL8*1.05,"acima","em linha"))),"") | AN8: sim | AR8: peso kit recalculado após correção do peso unitário | AS8: =IF(AND(N8<>"",N8>1),A8&"-KIT"&N8,A8) | AT8: =IF(AND(N8<>"",N8>1),D8&" — Kit "&N8&" unidades",D8) | AU8: agco_ACW0551840_ecommerce_1.png | agco_ACW0551840_ecommerce_2.png
A9: ACX2865730 | B9: ACX2865730 | C9: =IFERROR(LOWER(SUBSTITUTE(SUBSTITUTE(SUBSTITUTE(SUBSTITUTE(D9," ","-"),"/","-"),".",""),",","")),"") | D9: Tampa do Módulo SRM - Kit 60 Unidades - AGCO ACX2865730 | E9: Peças Plásticas Injetadas | F9: APP | H9: active | I9: AGCO | J9: PLANTADEIRA | K9: =LOWER(CONCATENATE(E9," ",J9," ",D9)) | M9: 84329000 | N9: 60 | O9: 5 | P9: 22.4 | Q9: 35 | R9: 43 | S9: 50 | T9: =IFERROR(IF(AND(Q9>0,R9>0,S9>0),(Q9*R9*S9)/6000,""),"") | U9: =IFERROR(IF(AND(Q9>0,R9>0,S9>0),(Q9*R9*S9)/6000,""),"") | V9: =IFERROR(IF(AND(P9>0,U9>0),MAX(P9,U9),IF(P9>0,P9,IF(U9>0,U9,""))),"") | W9: 105.71 | X9: fornecedor | Y9: =10.02*N9 | Z9: 0.2 | AA9: =IFERROR(Y9+W9,"") | AB9: =IFERROR(IF(Z9<1,AA9/(1-Z9),""),"") | AC9: ='01_CONFIG_GLOBAL'!$C$14 | AD9: =IFERROR(AB9*AC9,"") | AE9: =IFERROR(IF(AC9<1,AB9/(1-AC9),""),"") | AL9: =IFERROR(AVERAGE(AG9,AI9,AK9),"") | AM9: =IFERROR(IF(AL9="","sem dados",IF(AE9<AL9*0.95,"abaixo",IF(AE9>AL9*1.05,"acima","em linha"))),"") | AN9: sim | AS9: =IF(AND(N9<>"",N9>1),A9&"-KIT"&N9,A9) | AT9: =IF(AND(N9<>"",N9>1),D9&" — Kit "&N9&" unidades",D9) | AU9: SEM IMAGEM
A10: ACX3454710 | B10: ACX3454710 | C10: =IFERROR(LOWER(SUBSTITUTE(SUBSTITUTE(SUBSTITUTE(SUBSTITUTE(D10," ","-"),"/","-"),".",""),",","")),"") | D10: Conjunto Montado Reservatório de Sementes Mecânico - AGCO ACX3454710 | E10: Peças Plásticas Injetadas | F10: APP | H10: draft | I10: AGCO | J10: PLANTADEIRA | K10: =LOWER(CONCATENATE(E10," ",J10," ",D10)) | M10: 84329000 | N10: 25 | O10: 5 | P10: 32.5 | Q10: 100 | R10: 120 | S10: 72 | T10: =IFERROR(IF(AND(Q10>0,R10>0,S10>0),(Q10*R10*S10)/6000,""),"") | U10: =IFERROR(IF(AND(Q10>0,R10>0,S10>0),(Q10*R10*S10)/6000,""),"") | V10: =IFERROR(IF(AND(P10>0,U10>0),MAX(P10,U10),IF(P10>0,P10,IF(U10>0,U10,""))),"") | W10: 1609.15 | X10: fornecedor | Y10: =Y11*N10 | Z10: 0.2 | AA10: =IFERROR(Y10+W10,"") | AB10: =IFERROR(IF(Z10<1,AA10/(1-Z10),""),"") | AC10: ='01_CONFIG_GLOBAL'!$C$14 | AD10: =IFERROR(AB10*AC10,"") | AE10: =IFERROR(IF(AC10<1,AB10/(1-AC10),""),"") | AL10: =IFERROR(AVERAGE(AG10,AI10,AK10),"") | AM10: =IFERROR(IF(AL10="","sem dados",IF(AE10<AL10*0.95,"abaixo",IF(AE10>AL10*1.05,"acima","em linha"))),"") | AN10: sim | AR10: Fotos: assets/agco_ACX3454710_ecommerce_1.png; assets/agco_ACX3454710_ecommerce_2.png; assets/agco_ACX3454710_ecommerce_3.png; assets/agco_ACX3454710_ecommerce_4.png | DRAFT 21/07: frete parcel inviável (R$1609/R$645 cotados p/ caixa-palete) — cotar transportadora de carga antes de publicar | AS10: =IF(AND(N10<>"",N10>1),A10&"-KIT"&N10,A10) | AT10: =IF(AND(N10<>"",N10>1),D10&" — Kit "&N10&" unidades",D10) | AU10: agco_ACX3454710_ecommerce_1.png | agco_ACX3454710_ecommerce_2.png | agco_ACX3454710_ecommerce_3.png | agco_ACX3454710_ecommerce_4.png
A11: ACX3454710 | B11: ACX3454710 | C11: =IFERROR(LOWER(SUBSTITUTE(SUBSTITUTE(SUBSTITUTE(SUBSTITUTE(D11," ","-"),"/","-"),".",""),",","")),"") | D11: Conjunto Montado Reservatório de Sementes Mecânico - AGCO ACX3454710 | E11: Peças Plásticas Injetadas | F11: APP | H11: active | I11: AGCO | J11: PLANTADEIRA | K11: =LOWER(CONCATENATE(E11," ",J11," ",D11)) | M11: 84329000 | N11: 1 | O11: 5 | P11: 1.3 | Q11: 31 | R11: 25 | S11: 25 | T11: =IFERROR(IF(AND(Q11>0,R11>0,S11>0),(Q11*R11*S11)/6000,""),"") | U11: =IFERROR(IF(AND(Q11>0,R11>0,S11>0),(Q11*R11*S11)/6000,""),"") | V11: =IFERROR(IF(AND(P11>0,U11>0),MAX(P11,U11),IF(P11>0,P11,IF(U11>0,U11,""))),"") | W11: 40.06 | X11: fornecedor | Y11: 35.74 | Z11: 0.2 | AA11: =IFERROR(Y11+W11,"") | AB11: =IFERROR(IF(Z11<1,AA11/(1-Z11),""),"") | AC11: ='01_CONFIG_GLOBAL'!$C$14 | AD11: =IFERROR(AB11*AC11,"") | AE11: =IFERROR(IF(AC11<1,AB11/(1-AC11),""),"") | AL11: =IFERROR(AVERAGE(AG11,AI11,AK11),"") | AM11: =IFERROR(IF(AL11="","sem dados",IF(AE11<AL11*0.95,"abaixo",IF(AE11>AL11*1.05,"acima","em linha"))),"") | AN11: sim | AR11: Fotos: assets/agco_ACX3454710_ecommerce_1.png; assets/agco_ACX3454710_ecommerce_2.png; assets/agco_ACX3454710_ecommerce_3.png; assets/agco_ACX3454710_ecommerce_4.png | frete mantido no valor anterior (40,06) — rateio via palete suspenso | AS11: =IF(AND(N11<>"",N11>1),A11&"-KIT"&N11,A11) | AT11: =IF(AND(N11<>"",N11>1),D11&" — Kit "&N11&" unidades",D11) | AU11: agco_ACX3454710_ecommerce_1.png | agco_ACX3454710_ecommerce_2.png | agco_ACX3454710_ecommerce_3.png | agco_ACX3454710_ecommerce_4.png
A12: ACX3454710 | B12: ACX3454710 | C12: =IFERROR(LOWER(SUBSTITUTE(SUBSTITUTE(SUBSTITUTE(SUBSTITUTE(D12," ","-"),"/","-"),".",""),",","")),"") | D12: Conjunto Montado Reservatório de Sementes Mecânico - AGCO ACX3454710 | E12: Peças Plásticas Injetadas | F12: APP | H12: draft | I12: AGCO | J12: PLANTADEIRA | K12: =LOWER(CONCATENATE(E12," ",J12," ",D12)) | M12: 84329000 | N12: 12 | O12: 5 | P12: =P11*N12 | Q12: 100 | R12: 60 | S12: 60 | T12: =IFERROR(IF(AND(Q12>0,R12>0,S12>0),(Q12*R12*S12)/6000,""),"") | U12: =IFERROR(IF(AND(Q12>0,R12>0,S12>0),(Q12*R12*S12)/6000,""),"") | V12: =IFERROR(IF(AND(P12>0,U12>0),MAX(P12,U12),IF(P12>0,P12,IF(U12>0,U12,""))),"") | W12: 644.59 | X12: fornecedor | Y12: =Y11*N12 | Z12: 0.2 | AA12: =IFERROR(Y12+W12,"") | AB12: =IFERROR(IF(Z12<1,AA12/(1-Z12),""),"") | AC12: ='01_CONFIG_GLOBAL'!$C$14 | AD12: =IFERROR(AB12*AC12,"") | AE12: =IFERROR(IF(AC12<1,AB12/(1-AC12),""),"") | AM12: =IFERROR(IF(AL12="","sem dados",IF(AE12<AL12*0.95,"abaixo",IF(AE12>AL12*1.05,"acima","em linha"))),"") | AN12: sim | AS12: =IF(AND(N12<>"",N12>1),A12&"-KIT"&N12,A12) | AT12: =IF(AND(N12<>"",N12>1),D12&" — Kit "&N12&" unidades",D12) | AU12: agco_ACX3454710_ecommerce_1.png | agco_ACX3454710_ecommerce_2.png | agco_ACX3454710_ecommerce_3.png | agco_ACX3454710_ecommerce_4.png
A13: ACX2719210 | B13: ACX2719210 | C13: =IFERROR(LOWER(SUBSTITUTE(SUBSTITUTE(SUBSTITUTE(SUBSTITUTE(D13," ","-"),"/","-"),".",""),",","")),"") | D13: Conjunto Montado Joelho - AGCO ACX2719210 | E13: Peças Plásticas Injetadas | F13: APP | H13: active | I13: AGCO | J13: PLANTADEIRA | K13: =LOWER(CONCATENATE(E13," ",J13," ",D13)) | M13: 84329000 | N13: 1 | O13: 5 | P13: 0.2 | Q13: 4.4 | R13: 16.3 | S13: 9.2 | T13: =IFERROR(IF(AND(Q13>0,R13>0,S13>0),(Q13*R13*S13)/6000,""),"") | U13: =IFERROR(IF(AND(Q13>0,R13>0,S13>0),(Q13*R13*S13)/6000,""),"") | V13: =IFERROR(IF(AND(P13>0,U13>0),MAX(P13,U13),IF(P13>0,P13,IF(U13>0,U13,""))),"") | W13: 1.12 | X13: fornecedor | Y13: 13.81 | Z13: 0.2 | AA13: =IFERROR(Y13+W13,"") | AB13: =IFERROR(IF(Z13<1,AA13/(1-Z13),""),"") | AC13: ='01_CONFIG_GLOBAL'!$C$14 | AD13: =IFERROR(AB13*AC13,"") | AE13: =IFERROR(IF(AC13<1,AB13/(1-AC13),""),"") | AL13: =IFERROR(AVERAGE(AG13,AI13,AK13),"") | AM13: =IFERROR(IF(AL13="","sem dados",IF(AE13<AL13*0.95,"abaixo",IF(AE13>AL13*1.05,"acima","em linha"))),"") | AN13: sim | AS13: =IF(AND(N13<>"",N13>1),A13&"-KIT"&N13,A13) | AT13: =IF(AND(N13<>"",N13>1),D13&" — Kit "&N13&" unidades",D13) | AU13: AGCO_ACX2719210_ecommerce_1.png | AGCO_ACX2719210_ecommerce_2.png
A14: ACX2719210 | B14: ACX2719210 | C14: =IFERROR(LOWER(SUBSTITUTE(SUBSTITUTE(SUBSTITUTE(SUBSTITUTE(D14," ","-"),"/","-"),".",""),",","")),"") | D14: Conjunto Montado Joelho - Kit 30 Unidades - AGCO ACX2719210 | E14: Peças Plásticas Injetadas | F14: APP | H14: active | I14: AGCO | J14: PLANTADEIRA | K14: =LOWER(CONCATENATE(E14," ",J14," ",D14)) | M14: 84329000 | N14: 30 | O14: 5 | P14: =P13*N14 | Q14: 50 | R14: 18 | S14: 32 | T14: =IFERROR(IF(AND(Q14>0,R14>0,S14>0),(Q14*R14*S14)/6000,""),"") | U14: =IFERROR(IF(AND(Q14>0,R14>0,S14>0),(Q14*R14*S14)/6000,""),"") | V14: =IFERROR(IF(AND(P14>0,U14>0),MAX(P14,U14),IF(P14>0,P14,IF(U14>0,U14,""))),"") | W14: 33.55 | X14: fornecedor | Y14: =Y13*N14 | Z14: 0.2 | AA14: =IFERROR(Y14+W14,"") | AB14: =IFERROR(IF(Z14<1,AA14/(1-Z14),""),"") | AC14: ='01_CONFIG_GLOBAL'!$C$14 | AD14: =IFERROR(AB14*AC14,"") | AE14: =IFERROR(IF(AC14<1,AB14/(1-AC14),""),"") | AM14: =IFERROR(IF(AL14="","sem dados",IF(AE14<AL14*0.95,"abaixo",IF(AE14>AL14*1.05,"acima","em linha"))),"") | AN14: sim | AS14: =IF(AND(N14<>"",N14>1),A14&"-KIT"&N14,A14) | AT14: =IF(AND(N14<>"",N14>1),D14&" — Kit "&N14&" unidades",D14) | AU14: AGCO_ACX2719210_ecommerce_1.png | AGCO_ACX2719210_ecommerce_2.png
A15: 4383927M4 | B15: 4383927M4 | C15: =IFERROR(LOWER(SUBSTITUTE(SUBSTITUTE(SUBSTITUTE(SUBSTITUTE(D15," ","-"),"/","-"),".",""),",","")),"") | D15: Dobradiça Esquerda Inferior - Massey Ferguson 4383927M4 | E15: Peças Plásticas Injetadas | F15: APP | H15: active | I15: AGCO | J15: TRATOR | K15: =LOWER(CONCATENATE(E15," ",J15," ",D15)) | M15: 84329000 | N15: 1 | O15: 5 | P15: 0.19 | Q15: 3 | R15: 12.5 | S15: 8 | T15: =IFERROR(IF(AND(Q15>0,R15>0,S15>0),(Q15*R15*S15)/6000,""),"") | U15: =IFERROR(IF(AND(Q15>0,R15>0,S15>0),(Q15*R15*S15)/6000,""),"") | V15: =IFERROR(IF(AND(P15>0,U15>0),MAX(P15,U15),IF(P15>0,P15,IF(U15>0,U15,""))),"") | W15: 2.08 | X15: fornecedor | Y15: 20.01 | Z15: 0.2 | AA15: =IFERROR(Y15+W15,"") | AB15: =IFERROR(IF(Z15<1,AA15/(1-Z15),""),"") | AC15: ='01_CONFIG_GLOBAL'!$C$14 | AD15: =IFERROR(AB15*AC15,"") | AE15: =IFERROR(IF(AC15<1,AB15/(1-AC15),""),"") | AL15: =IFERROR(AVERAGE(AG15,AI15,AK15),"") | AM15: =IFERROR(IF(AL15="","sem dados",IF(AE15<AL15*0.95,"abaixo",IF(AE15>AL15*1.05,"acima","em linha"))),"") | AN15: sim | AR15: Fotos: assets/AGCO_4383927M4_ecommerce_1.png; assets/AGCO_4383927M4_ecommerce_2.png | AS15: =IF(AND(N15<>"",N15>1),A15&"-KIT"&N15,A15) | AT15: =IF(AND(N15<>"",N15>1),D15&" — Kit "&N15&" unidades",D15) | AU15: AGCO_4383927M4_ecommerce_1.png | AGCO_4383927M4_ecommerce_2.png
A16: 4383927M4 | B16: 4383927M4 | C16: =IFERROR(LOWER(SUBSTITUTE(SUBSTITUTE(SUBSTITUTE(SUBSTITUTE(D16," ","-"),"/","-"),".",""),",","")),"") | D16: Dobradiça Esquerda Inferior - Kit 10 Unidades - Massey Ferguson 4383927M4 | E16: Peças Plásticas Injetadas | F16: APP | H16: active | I16: AGCO | J16: TRATOR | K16: =LOWER(CONCATENATE(E16," ",J16," ",D16)) | M16: 84329000 | N16: 10 | O16: 5 | P16: =P15*N16 | Q16: 35 | R16: 15 | S16: 10 | T16: =IFERROR(IF(AND(Q16>0,R16>0,S16>0),(Q16*R16*S16)/6000,""),"") | U16: =IFERROR(IF(AND(Q16>0,R16>0,S16>0),(Q16*R16*S16)/6000,""),"") | V16: =IFERROR(IF(AND(P16>0,U16>0),MAX(P16,U16),IF(P16>0,P16,IF(U16>0,U16,""))),"") | W16: 20.77 | X16: fornecedor | Y16: =Y15*N16 | Z16: 0.2 | AA16: =IFERROR(Y16+W16,"") | AB16: =IFERROR(IF(Z16<1,AA16/(1-Z16),""),"") | AC16: ='01_CONFIG_GLOBAL'!$C$14 | AD16: =IFERROR(AB16*AC16,"") | AE16: =IFERROR(IF(AC16<1,AB16/(1-AC16),""),"") | AM16: =IFERROR(IF(AL16="","sem dados",IF(AE16<AL16*0.95,"abaixo",IF(AE16>AL16*1.05,"acima","em linha"))),"") | AN16: sim | AS16: =IF(AND(N16<>"",N16>1),A16&"-KIT"&N16,A16) | AT16: =IF(AND(N16<>"",N16>1),D16&" — Kit "&N16&" unidades",D16) | AU16: AGCO_4383927M4_ecommerce_1.png | AGCO_4383927M4_ecommerce_2.png
A17: ACX283890A | B17: ACX283890A | C17: =IFERROR(LOWER(SUBSTITUTE(SUBSTITUTE(SUBSTITUTE(SUBSTITUTE(D17," ","-"),"/","-"),".",""),",","")),"") | D17: Vedação Tubo de Ar - AGCO ACX283890A | Sistema Pneumático | E17: Peças Plásticas Injetadas | F17: APP | H17: active | I17: AGCO | J17: PLANTADEIRA | K17: =LOWER(CONCATENATE(E17," ",J17," ",D17)) | M17: 84329000 | N17: 1 | O17: 5 | P17: 0.1 | Q17: 16.1 | R17: 20.7 | S17: 1.5 | T17: =IFERROR(IF(AND(Q17>0,R17>0,S17>0),(Q17*R17*S17)/6000,""),"") | U17: =IFERROR(IF(AND(Q17>0,R17>0,S17>0),(Q17*R17*S17)/6000,""),"") | V17: =IFERROR(IF(AND(P17>0,U17>0),MAX(P17,U17),IF(P17>0,P17,IF(U17>0,U17,""))),"") | W17: 2.08 | X17: fornecedor | Y17: 20.14 | Z17: 0.2 | AA17: =IFERROR(Y17+W17,"") | AB17: =IFERROR(IF(Z17<1,AA17/(1-Z17),""),"") | AC17: ='01_CONFIG_GLOBAL'!$C$14 | AD17: =IFERROR(AB17*AC17,"") | AE17: =IFERROR(IF(AC17<1,AB17/(1-AC17),""),"") | AL17: =IFERROR(AVERAGE(AG17,AI17,AK17),"") | AM17: =IFERROR(IF(AL17="","sem dados",IF(AE17<AL17*0.95,"abaixo",IF(AE17>AL17*1.05,"acima","em linha"))),"") | AN17: sim | AR17: Fotos: assets/AGCO_ACX283890A_ecommerce.png | AS17: =IF(AND(N17<>"",N17>1),A17&"-KIT"&N17,A17) | AT17: =IF(AND(N17<>"",N17>1),D17&" — Kit "&N17&" unidades",D17) | AU17: AGCO_ACX283890A_ecommerce.png
A18: ACX283890A | B18: ACX283890A | C18: =IFERROR(LOWER(SUBSTITUTE(SUBSTITUTE(SUBSTITUTE(SUBSTITUTE(D18," ","-"),"/","-"),".",""),",","")),"") | D18: Vedação Tubo de Ar - Kit 10 Unidades - AGCO ACX283890A | E18: Peças Plásticas Injetadas | F18: APP | H18: active | I18: AGCO | J18: PLANTADEIRA | K18: =LOWER(CONCATENATE(E18," ",J18," ",D18)) | M18: 84329000 | N18: 10 | O18: 5 | P18: =P17*N18 | Q18: 18 | R18: 22 | S18: 18 | T18: =IFERROR(IF(AND(Q18>0,R18>0,S18>0),(Q18*R18*S18)/6000,""),"") | U18: =IFERROR(IF(AND(Q18>0,R18>0,S18>0),(Q18*R18*S18)/6000,""),"") | V18: =IFERROR(IF(AND(P18>0,U18>0),MAX(P18,U18),IF(P18>0,P18,IF(U18>0,U18,""))),"") | W18: 20.78 | X18: fornecedor | Y18: =Y17*N18 | Z18: 0.2 | AA18: =IFERROR(Y18+W18,"") | AB18: =IFERROR(IF(Z18<1,AA18/(1-Z18),""),"") | AC18: ='01_CONFIG_GLOBAL'!$C$14 | AD18: =IFERROR(AB18*AC18,"") | AE18: =IFERROR(IF(AC18<1,AB18/(1-AC18),""),"") | AM18: =IFERROR(IF(AL18="","sem dados",IF(AE18<AL18*0.95,"abaixo",IF(AE18>AL18*1.05,"acima","em linha"))),"") | AN18: sim | AS18: =IF(AND(N18<>"",N18>1),A18&"-KIT"&N18,A18) | AT18: =IF(AND(N18<>"",N18>1),D18&" — Kit "&N18&" unidades",D18) | AU18: AGCO_ACX283890A_ecommerce.png
A19: ACX310603A | B19: ACX310603A | C19: =IFERROR(LOWER(SUBSTITUTE(SUBSTITUTE(SUBSTITUTE(SUBSTITUTE(D19," ","-"),"/","-"),".",""),",","")),"") | D19: Manípulo Pneumático - AGCO ACX310603A | E19: Peças Plásticas Injetadas | F19: APP | H19: active | I19: AGCO | J19: PLANTADEIRA | K19: =LOWER(CONCATENATE(E19," ",J19," ",D19)) | M19: 84329000 | N19: 1 | O19: 5 | P19: 0.06 | Q19: 5.4 | R19: 11.7 | S19: 3.4 | T19: =IFERROR(IF(AND(Q19>0,R19>0,S19>0),(Q19*R19*S19)/6000,""),"") | U19: =IFERROR(IF(AND(Q19>0,R19>0,S19>0),(Q19*R19*S19)/6000,""),"") | V19: =IFERROR(IF(AND(P19>0,U19>0),MAX(P19,U19),IF(P19>0,P19,IF(U19>0,U19,""))),"") | W19: 0.49 | X19: fornecedor | Y19: 4.53 | Z19: 0.2 | AA19: =IFERROR(Y19+W19,"") | AB19: =IFERROR(IF(Z19<1,AA19/(1-Z19),""),"") | AC19: ='01_CONFIG_GLOBAL'!$C$14 | AD19: =IFERROR(AB19*AC19,"") | AE19: =IFERROR(IF(AC19<1,AB19/(1-AC19),""),"") | AL19: =IFERROR(AVERAGE(AG19,AI19,AK19),"") | AM19: =IFERROR(IF(AL19="","sem dados",IF(AE19<AL19*0.95,"abaixo",IF(AE19>AL19*1.05,"acima","em linha"))),"") | AN19: sim | AR19: Fotos: assets/agco_ACX310603A_ecommerce.png | AS19: =IF(AND(N19<>"",N19>1),A19&"-KIT"&N19,A19) | AT19: =IF(AND(N19<>"",N19>1),D19&" — Kit "&N19&" unidades",D19) | AU19: agco_ACX310603A_ecommerce.png
A20: ACX310603A | B20: ACX310603A | C20: =IFERROR(LOWER(SUBSTITUTE(SUBSTITUTE(SUBSTITUTE(SUBSTITUTE(D20," ","-"),"/","-"),".",""),",","")),"") | D20: Manípulo Pneumático - Kit 50 Unidades - AGCO ACX310603A | E20: Peças Plásticas Injetadas | F20: APP | H20: active | I20: AGCO | J20: PLANTADEIRA | K20: =LOWER(CONCATENATE(E20," ",J20," ",D20)) | M20: 84329000 | N20: 50 | O20: 5 | P20: =P19*N20 | Q20: 30 | R20: 14 | S20: 20 | T20: =IFERROR(IF(AND(Q20>0,R20>0,S20>0),(Q20*R20*S20)/6000,""),"") | U20: =IFERROR(IF(AND(Q20>0,R20>0,S20>0),(Q20*R20*S20)/6000,""),"") | V20: =IFERROR(IF(AND(P20>0,U20>0),MAX(P20,U20),IF(P20>0,P20,IF(U20>0,U20,""))),"") | W20: 24.71 | X20: fornecedor | Y20: =Y19*N20 | Z20: 0.2 | AA20: =IFERROR(Y20+W20,"") | AB20: =IFERROR(IF(Z20<1,AA20/(1-Z20),""),"") | AC20: ='01_CONFIG_GLOBAL'!$C$14 | AD20: =IFERROR(AB20*AC20,"") | AE20: =IFERROR(IF(AC20<1,AB20/(1-AC20),""),"") | AM20: =IFERROR(IF(AL20="","sem dados",IF(AE20<AL20*0.95,"abaixo",IF(AE20>AL20*1.05,"acima","em linha"))),"") | AN20: sim | AS20: =IF(AND(N20<>"",N20>1),A20&"-KIT"&N20,A20) | AT20: =IF(AND(N20<>"",N20>1),D20&" — Kit "&N20&" unidades",D20) | AU20: agco_ACX310603A_ecommerce.png
A21: 4383923M4 | B21: 4383923M4 | C21: =IFERROR(LOWER(SUBSTITUTE(SUBSTITUTE(SUBSTITUTE(SUBSTITUTE(D21," ","-"),"/","-"),".",""),",","")),"") | D21: Dobradiça Esquerda Superior - Massey Ferguson 4383923M4 | E21: Peças Plásticas Injetadas | F21: APP | H21: active | I21: AGCO | J21: TRATOR | K21: =LOWER(CONCATENATE(E21," ",J21," ",D21)) | M21: 84329000 | O21: 5 | P21: 0.19 | Q21: 3 | R21: 12.5 | S21: 8 | T21: =IFERROR(IF(AND(Q21>0,R21>0,S21>0),(Q21*R21*S21)/6000,""),"") | U21: =IFERROR(IF(AND(Q21>0,R21>0,S21>0),(Q21*R21*S21)/6000,""),"") | V21: =IFERROR(IF(AND(P21>0,U21>0),MAX(P21,U21),IF(P21>0,P21,IF(U21>0,U21,""))),"") | W21: 16.74 | X21: fornecedor | Y21: 20.01 | Z21: 0.2 | AA21: =IFERROR(Y21+W21,"") | AB21: =IFERROR(IF(Z21<1,AA21/(1-Z21),""),"") | AC21: ='01_CONFIG_GLOBAL'!$C$14 | AD21: =IFERROR(AB21*AC21,"") | AE21: =IFERROR(IF(AC21<1,AB21/(1-AC21),""),"") | AL21: =IFERROR(AVERAGE(AG21,AI21,AK21),"") | AM21: =IFERROR(IF(AL21="","sem dados",IF(AE21<AL21*0.95,"abaixo",IF(AE21>AL21*1.05,"acima","em linha"))),"") | AN21: sim | AR21: Fotos: assets/AGCO_4383923M4_ecommerce_1.png; assets/AGCO_4383923M4_ecommerce_2.png | AS21: =IF(AND(N21<>"",N21>1),A21&"-KIT"&N21,A21) | AT21: =IF(AND(N21<>"",N21>1),D21&" — Kit "&N21&" unidades",D21) | AU21: AGCO_4383923M4_ecommerce_1.png | AGCO_4383923M4_ecommerce_2.png
A22: ACX363311C | B22: ACX363311C | C22: =IFERROR(LOWER(SUBSTITUTE(SUBSTITUTE(SUBSTITUTE(SUBSTITUTE(D22," ","-"),"/","-"),".",""),",","")),"") | D22: Copo Venturi C - AGCO ACX363311C | Dosador Pneumático | E22: Peças Plásticas Injetadas | F22: APP | H22: active | I22: AGCO | J22: PLANTADEIRA | K22: =LOWER(CONCATENATE(E22," ",J22," ",D22)) | M22: 84329000 | O22: 5 | P22: 0.19 | Q22: 3 | R22: 11 | S22: 7 | T22: =IFERROR(IF(AND(Q22>0,R22>0,S22>0),(Q22*R22*S22)/6000,""),"") | U22: =IFERROR(IF(AND(Q22>0,R22>0,S22>0),(Q22*R22*S22)/6000,""),"") | V22: =IFERROR(IF(AND(P22>0,U22>0),MAX(P22,U22),IF(P22>0,P22,IF(U22>0,U22,""))),"") | W22: 1.03 | X22: fornecedor | Y22: 8.31 | Z22: 0.2 | AA22: =IFERROR(Y22+W22,"") | AB22: =IFERROR(IF(Z22<1,AA22/(1-Z22),""),"") | AC22: ='01_CONFIG_GLOBAL'!$C$14 | AD22: =IFERROR(AB22*AC22,"") | AE22: =IFERROR(IF(AC22<1,AB22/(1-AC22),""),"") | AL22: =IFERROR(AVERAGE(AG22,AI22,AK22),"") | AM22: =IFERROR(IF(AL22="","sem dados",IF(AE22<AL22*0.95,"abaixo",IF(AE22>AL22*1.05,"acima","em linha"))),"") | AN22: sim | AR22: Fotos: assets/agco_ACX363311C_ecommerce.png | AS22: =IF(AND(N22<>"",N22>1),A22&"-KIT"&N22,A22) | AT22: =IF(AND(N22<>"",N22>1),D22&" — Kit "&N22&" unidades",D22) | AU22: agco_ACX363311C_ecommerce.png
A23: ACX363311C | B23: ACX363311C | C23: =IFERROR(LOWER(SUBSTITUTE(SUBSTITUTE(SUBSTITUTE(SUBSTITUTE(D23," ","-"),"/","-"),".",""),",","")),"") | D23: Copo Venturi C - Kit 60 Unidades - AGCO ACX363311C | E23: Peças Plásticas Injetadas | F23: APP | H23: active | I23: AGCO | J23: PLANTADEIRA | K23: =LOWER(CONCATENATE(E23," ",J23," ",D23)) | M23: 84329000 | N23: 60 | O23: 5 | P23: =P22*N23 | Q23: 45 | R23: 32 | S23: 18 | T23: =IFERROR(IF(AND(Q23>0,R23>0,S23>0),(Q23*R23*S23)/6000,""),"") | U23: =IFERROR(IF(AND(Q23>0,R23>0,S23>0),(Q23*R23*S23)/6000,""),"") | V23: =IFERROR(IF(AND(P23>0,U23>0),MAX(P23,U23),IF(P23>0,P23,IF(U23>0,U23,""))),"") | W23: 61.52 | X23: fornecedor | Y23: =Y22*N23 | Z23: 0.2 | AA23: =IFERROR(Y23+W23,"") | AB23: =IFERROR(IF(Z23<1,AA23/(1-Z23),""),"") | AC23: ='01_CONFIG_GLOBAL'!$C$14 | AD23: =IFERROR(AB23*AC23,"") | AE23: =IFERROR(IF(AC23<1,AB23/(1-AC23),""),"") | AM23: =IFERROR(IF(AL23="","sem dados",IF(AE23<AL23*0.95,"abaixo",IF(AE23>AL23*1.05,"acima","em linha"))),"") | AN23: sim | AS23: =IF(AND(N23<>"",N23>1),A23&"-KIT"&N23,A23) | AT23: =IF(AND(N23<>"",N23>1),D23&" — Kit "&N23&" unidades",D23) | AU23: AGCO_ACX3601860_ecommerce_2.png
A24: ACX363311B | B24: ACX363311B | C24: =IFERROR(LOWER(SUBSTITUTE(SUBSTITUTE(SUBSTITUTE(SUBSTITUTE(D24," ","-"),"/","-"),".",""),",","")),"") | D24: Copo Venturi B - AGCO ACX363311B | Dosador Pneumático | E24: Peças Plásticas Injetadas | F24: APP | H24: active | I24: AGCO | J24: PLANTADEIRA | K24: =LOWER(CONCATENATE(E24," ",J24," ",D24)) | M24: 84329000 | N24: 1 | O24: 5 | P24: 0.19 | Q24: 3 | R24: 10 | S24: 7 | T24: =IFERROR(IF(AND(Q24>0,R24>0,S24>0),(Q24*R24*S24)/6000,""),"") | U24: =IFERROR(IF(AND(Q24>0,R24>0,S24>0),(Q24*R24*S24)/6000,""),"") | V24: =IFERROR(IF(AND(P24>0,U24>0),MAX(P24,U24),IF(P24>0,P24,IF(U24>0,U24,""))),"") | W24: 1.03 | X24: fornecedor | Y24: 8.31 | Z24: 0.2 | AA24: =IFERROR(Y24+W24,"") | AB24: =IFERROR(IF(Z24<1,AA24/(1-Z24),""),"") | AC24: ='01_CONFIG_GLOBAL'!$C$14 | AD24: =IFERROR(AB24*AC24,"") | AE24: =IFERROR(IF(AC24<1,AB24/(1-AC24),""),"") | AL24: =IFERROR(AVERAGE(AG24,AI24,AK24),"") | AM24: =IFERROR(IF(AL24="","sem dados",IF(AE24<AL24*0.95,"abaixo",IF(AE24>AL24*1.05,"acima","em linha"))),"") | AN24: sim | AR24: Fotos: assets/agco_ACX363311B_ecommerce.png | AS24: =IF(AND(N24<>"",N24>1),A24&"-KIT"&N24,A24) | AT24: =IF(AND(N24<>"",N24>1),D24&" — Kit "&N24&" unidades",D24) | AU24: agco_ACX363311B_ecommerce.png
A25: ACX363311B | B25: ACX363311B | C25: =IFERROR(LOWER(SUBSTITUTE(SUBSTITUTE(SUBSTITUTE(SUBSTITUTE(D25," ","-"),"/","-"),".",""),",","")),"") | D25: Copo Venturi B - Kit 60 Unidades - AGCO ACX363311B | E25: Peças Plásticas Injetadas | F25: APP | H25: active | I25: AGCO | J25: PLANTADEIRA | K25: =LOWER(CONCATENATE(E25," ",J25," ",D25)) | M25: 84329000 | N25: 60 | O25: 5 | P25: =P24*N25 | Q25: 45 | R25: 32 | S25: 18 | T25: =IFERROR(IF(AND(Q25>0,R25>0,S25>0),(Q25*R25*S25)/6000,""),"") | U25: =IFERROR(IF(AND(Q25>0,R25>0,S25>0),(Q25*R25*S25)/6000,""),"") | V25: =IFERROR(IF(AND(P25>0,U25>0),MAX(P25,U25),IF(P25>0,P25,IF(U25>0,U25,""))),"") | W25: 61.52 | X25: fornecedor | Y25: =Y24*N25 | Z25: 0.2 | AA25: =IFERROR(Y25+W25,"") | AB25: =IFERROR(IF(Z25<1,AA25/(1-Z25),""),"") | AC25: ='01_CONFIG_GLOBAL'!$C$14 | AD25: =IFERROR(AB25*AC25,"") | AE25: =IFERROR(IF(AC25<1,AB25/(1-AC25),""),"") | AM25: =IFERROR(IF(AL25="","sem dados",IF(AE25<AL25*0.95,"abaixo",IF(AE25>AL25*1.05,"acima","em linha"))),"") | AN25: sim | AS25: =IF(AND(N25<>"",N25>1),A25&"-KIT"&N25,A25) | AT25: =IF(AND(N25<>"",N25>1),D25&" — Kit "&N25&" unidades",D25) | AU25: AGCO_ACX3601860_ecommerce_1.png
A26: ACX2414460 | B26: ACX2414460 | C26: =IFERROR(LOWER(SUBSTITUTE(SUBSTITUTE(SUBSTITUTE(SUBSTITUTE(D26," ","-"),"/","-"),".",""),",","")),"") | D26: Conjunto Adaptador de Vácuo - AGCO ACX2414460 | E26: Peças Plásticas Injetadas | F26: APP | H26: active | I26: AGCO | J26: PLANTADEIRA | K26: =LOWER(CONCATENATE(E26," ",J26," ",D26)) | M26: 84329000 | N26: 1 | O26: 5 | P26: 0.1 | Q26: 22.5 | R26: 12 | S26: 4 | T26: =IFERROR(IF(AND(Q26>0,R26>0,S26>0),(Q26*R26*S26)/6000,""),"") | U26: =IFERROR(IF(AND(Q26>0,R26>0,S26>0),(Q26*R26*S26)/6000,""),"") | V26: =IFERROR(IF(AND(P26>0,U26>0),MAX(P26,U26),IF(P26>0,P26,IF(U26>0,U26,""))),"") | W26: 1.38 | X26: fornecedor | Y26: 9.02 | Z26: 0.2 | AA26: =IFERROR(Y26+W26,"") | AB26: =IFERROR(IF(Z26<1,AA26/(1-Z26),""),"") | AC26: ='01_CONFIG_GLOBAL'!$C$14 | AD26: =IFERROR(AB26*AC26,"") | AE26: =IFERROR(IF(AC26<1,AB26/(1-AC26),""),"") | AL26: =IFERROR(AVERAGE(AG26,AI26,AK26),"") | AM26: =IFERROR(IF(AL26="","sem dados",IF(AE26<AL26*0.95,"abaixo",IF(AE26>AL26*1.05,"acima","em linha"))),"") | AN26: sim | AR26: Fotos: assets/agco_ACX2414460_ecommerce.png | AS26: =IF(AND(N26<>"",N26>1),A26&"-KIT"&N26,A26) | AT26: =IF(AND(N26<>"",N26>1),D26&" — Kit "&N26&" unidades",D26) | AU26: agco_ACX2414460_ecommerce.png
A27: ACX2414460 | B27: ACX2414460 | C27: =IFERROR(LOWER(SUBSTITUTE(SUBSTITUTE(SUBSTITUTE(SUBSTITUTE(D27," ","-"),"/","-"),".",""),",","")),"") | D27: Conjunto Adaptador de Vácuo - Kit 20 Unidades - AGCO ACX2414460 | E27: Peças Plásticas Injetadas | F27: APP | H27: active | I27: AGCO | J27: PLANTADEIRA | K27: =LOWER(CONCATENATE(E27," ",J27," ",D27)) | M27: 84329000 | N27: 20 | O27: 5 | P27: =P26*N27 | Q27: 25 | R27: 25 | S27: 45 | T27: =IFERROR(IF(AND(Q27>0,R27>0,S27>0),(Q27*R27*S27)/6000,""),"") | U27: =IFERROR(IF(AND(Q27>0,R27>0,S27>0),(Q27*R27*S27)/6000,""),"") | V27: =IFERROR(IF(AND(P27>0,U27>0),MAX(P27,U27),IF(P27>0,P27,IF(U27>0,U27,""))),"") | W27: 27.58 | X27: fornecedor | Y27: =Y26*N27 | Z27: 0.2 | AA27: =IFERROR(Y27+W27,"") | AB27: =IFERROR(IF(Z27<1,AA27/(1-Z27),""),"") | AC27: ='01_CONFIG_GLOBAL'!$C$14 | AD27: =IFERROR(AB27*AC27,"") | AE27: =IFERROR(IF(AC27<1,AB27/(1-AC27),""),"") | AM27: =IFERROR(IF(AL27="","sem dados",IF(AE27<AL27*0.95,"abaixo",IF(AE27>AL27*1.05,"acima","em linha"))),"") | AN27: sim | AS27: =IF(AND(N27<>"",N27>1),A27&"-KIT"&N27,A27) | AT27: =IF(AND(N27<>"",N27>1),D27&" — Kit "&N27&" unidades",D27) | AU27: agco_ACX2414460_ecommerce.png
A28: ACX3371800 | B28: ACX3371800 | C28: =IFERROR(LOWER(SUBSTITUTE(SUBSTITUTE(SUBSTITUTE(SUBSTITUTE(D28," ","-"),"/","-"),".",""),",","")),"") | D28: Bocal Cotovelo de Vácuo - AGCO ACX3371800 | E28: Peças Plásticas Injetadas | F28: APP | H28: active | I28: AGCO | J28: PLANTADEIRA | K28: =LOWER(CONCATENATE(E28," ",J28," ",D28)) | M28: 84329000 | N28: 1 | O28: 5 | P28: 0.25 | Q28: 6.7 | R28: 12 | S28: 6.7 | T28: =IFERROR(IF(AND(Q28>0,R28>0,S28>0),(Q28*R28*S28)/6000,""),"") | U28: =IFERROR(IF(AND(Q28>0,R28>0,S28>0),(Q28*R28*S28)/6000,""),"") | V28: =IFERROR(IF(AND(P28>0,U28>0),MAX(P28,U28),IF(P28>0,P28,IF(U28>0,U28,""))),"") | W28: 1.28 | X28: fornecedor | Y28: 5.77 | Z28: 0.2 | AA28: =IFERROR(Y28+W28,"") | AB28: =IFERROR(IF(Z28<1,AA28/(1-Z28),""),"") | AC28: ='01_CONFIG_GLOBAL'!$C$14 | AD28: =IFERROR(AB28*AC28,"") | AE28: =IFERROR(IF(AC28<1,AB28/(1-AC28),""),"") | AL28: =IFERROR(AVERAGE(AG28,AI28,AK28),"") | AM28: =IFERROR(IF(AL28="","sem dados",IF(AE28<AL28*0.95,"abaixo",IF(AE28>AL28*1.05,"acima","em linha"))),"") | AN28: sim | AR28: Fotos: assets/agco_ACX3371800_ecommerce.png | AS28: =IF(AND(N28<>"",N28>1),A28&"-KIT"&N28,A28) | AT28: =IF(AND(N28<>"",N28>1),D28&" — Kit "&N28&" unidades",D28) | AU28: agco_ACX3371800_ecommerce.png
A29: ACX3371800 | B29: ACX3371800 | C29: =IFERROR(LOWER(SUBSTITUTE(SUBSTITUTE(SUBSTITUTE(SUBSTITUTE(D29," ","-"),"/","-"),".",""),",","")),"") | D29: Bocal Cotovelo de Vácuo - Kit 50 Unidades - AGCO ACX3371800 | E29: Peças Plásticas Injetadas | F29: APP | H29: active | I29: AGCO | J29: PLANTADEIRA | K29: =LOWER(CONCATENATE(E29," ",J29," ",D29)) | M29: 84329000 | N29: 50 | O29: 5 | P29: =P28*N29 | Q29: 40 | R29: 25 | S29: 40 | T29: =IFERROR(IF(AND(Q29>0,R29>0,S29>0),(Q29*R29*S29)/6000,""),"") | U29: =IFERROR(IF(AND(Q29>0,R29>0,S29>0),(Q29*R29*S29)/6000,""),"") | V29: =IFERROR(IF(AND(P29>0,U29>0),MAX(P29,U29),IF(P29>0,P29,IF(U29>0,U29,""))),"") | W29: 63.83 | X29: fornecedor | Y29: =Y28*N29 | Z29: 0.2 | AA29: =IFERROR(Y29+W29,"") | AB29: =IFERROR(IF(Z29<1,AA29/(1-Z29),""),"") | AC29: ='01_CONFIG_GLOBAL'!$C$14 | AD29: =IFERROR(AB29*AC29,"") | AE29: =IFERROR(IF(AC29<1,AB29/(1-AC29),""),"") | AM29: =IFERROR(IF(AL29="","sem dados",IF(AE29<AL29*0.95,"abaixo",IF(AE29>AL29*1.05,"acima","em linha"))),"") | AN29: sim | AS29: =IF(AND(N29<>"",N29>1),A29&"-KIT"&N29,A29) | AT29: =IF(AND(N29<>"",N29>1),D29&" — Kit "&N29&" unidades",D29) | AU29: agco_ACX3371800_ecommerce.png
A30: 7038105M1 | B30: 7038105M1 | C30: =IFERROR(LOWER(SUBSTITUTE(SUBSTITUTE(SUBSTITUTE(SUBSTITUTE(D30," ","-"),"/","-"),".",""),",","")),"") | D30: Acoplamento do Condutor - Massey Ferguson 7038105M1 | E30: Peças Plásticas Injetadas | F30: APP | H30: active | I30: AGCO | J30: PLANTADEIRA | K30: =LOWER(CONCATENATE(E30," ",J30," ",D30)) | M30: 84329000 | N30: 1 | O30: 5 | P30: 0.1 | Q30: 8.5 | R30: 10 | S30: 4 | T30: =IFERROR(IF(AND(Q30>0,R30>0,S30>0),(Q30*R30*S30)/6000,""),"") | U30: =IFERROR(IF(AND(Q30>0,R30>0,S30>0),(Q30*R30*S30)/6000,""),"") | V30: =IFERROR(IF(AND(P30>0,U30>0),MAX(P30,U30),IF(P30>0,P30,IF(U30>0,U30,""))),"") | W30: 0.53 | X30: fornecedor | Y30: 3.94 | Z30: 0.2 | AA30: =IFERROR(Y30+W30,"") | AB30: =IFERROR(IF(Z30<1,AA30/(1-Z30),""),"") | AC30: ='01_CONFIG_GLOBAL'!$C$14 | AD30: =IFERROR(AB30*AC30,"") | AE30: =IFERROR(IF(AC30<1,AB30/(1-AC30),""),"") | AL30: =IFERROR(AVERAGE(AG30,AI30,AK30),"") | AM30: =IFERROR(IF(AL30="","sem dados",IF(AE30<AL30*0.95,"abaixo",IF(AE30>AL30*1.05,"acima","em linha"))),"") | AN30: sim | AR30: Fotos: assets/agco_7038105M1_ecommerce.png | AS30: =IF(AND(N30<>"",N30>1),A30&"-KIT"&N30,A30) | AT30: =IF(AND(N30<>"",N30>1),D30&" — Kit "&N30&" unidades",D30) | AU30: agco_7038105M1_ecommerce.png
A31: 7038105M1 | B31: 7038105M1 | C31: =IFERROR(LOWER(SUBSTITUTE(SUBSTITUTE(SUBSTITUTE(SUBSTITUTE(D31," ","-"),"/","-"),".",""),",","")),"") | D31: Acoplamento do Condutor - Kit 60 Unidades - Massey Ferguson 7038105M1 | E31: Peças Plásticas Injetadas | F31: APP | H31: active | I31: AGCO | J31: PLANTADEIRA | K31: =LOWER(CONCATENATE(E31," ",J31," ",D31)) | M31: 84329000 | N31: 60 | O31: 5 | P31: =P30*N31 | Q31: 20 | R31: 32 | S31: 45 | T31: =IFERROR(IF(AND(Q31>0,R31>0,S31>0),(Q31*R31*S31)/6000,""),"") | U31: =IFERROR(IF(AND(Q31>0,R31>0,S31>0),(Q31*R31*S31)/6000,""),"") | V31: =IFERROR(IF(AND(P31>0,U31>0),MAX(P31,U31),IF(P31>0,P31,IF(U31>0,U31,""))),"") | W31: 32.09 | X31: fornecedor | Y31: =Y30*N31 | Z31: 0.2 | AA31: =IFERROR(Y31+W31,"") | AB31: =IFERROR(IF(Z31<1,AA31/(1-Z31),""),"") | AC31: ='01_CONFIG_GLOBAL'!$C$14 | AD31: =IFERROR(AB31*AC31,"") | AE31: =IFERROR(IF(AC31<1,AB31/(1-AC31),""),"") | AM31: =IFERROR(IF(AL31="","sem dados",IF(AE31<AL31*0.95,"abaixo",IF(AE31>AL31*1.05,"acima","em linha"))),"") | AN31: sim | AS31: =IF(AND(N31<>"",N31>1),A31&"-KIT"&N31,A31) | AT31: =IF(AND(N31<>"",N31>1),D31&" — Kit "&N31&" unidades",D31) | AU31: agco_7038105M1_ecommerce.png
A32: 7038106M1 | B32: 7038106M1 | C32: =IFERROR(LOWER(SUBSTITUTE(SUBSTITUTE(SUBSTITUTE(SUBSTITUTE(D32," ","-"),"/","-"),".",""),",","")),"") | D32: Acoplamento da Curva - Massey Ferguson 7038106M1 | E32: Peças Plásticas Injetadas | F32: APP | H32: active | I32: AGCO | J32: PLANTADEIRA | K32: =LOWER(CONCATENATE(E32," ",J32," ",D32)) | M32: 84329000 | N32: 1 | O32: 5 | P32: 0.1 | Q32: 8.5 | R32: 10 | S32: 3.8 | T32: =IFERROR(IF(AND(Q32>0,R32>0,S32>0),(Q32*R32*S32)/6000,""),"") | U32: =IFERROR(IF(AND(Q32>0,R32>0,S32>0),(Q32*R32*S32)/6000,""),"") | V32: =IFERROR(IF(AND(P32>0,U32>0),MAX(P32,U32),IF(P32>0,P32,IF(U32>0,U32,""))),"") | W32: 0.53 | X32: fornecedor | Y32: 3.94 | Z32: 0.2 | AA32: =IFERROR(Y32+W32,"") | AB32: =IFERROR(IF(Z32<1,AA32/(1-Z32),""),"") | AC32: ='01_CONFIG_GLOBAL'!$C$14 | AD32: =IFERROR(AB32*AC32,"") | AE32: =IFERROR(IF(AC32<1,AB32/(1-AC32),""),"") | AL32: =IFERROR(AVERAGE(AG32,AI32,AK32),"") | AM32: =IFERROR(IF(AL32="","sem dados",IF(AE32<AL32*0.95,"abaixo",IF(AE32>AL32*1.05,"acima","em linha"))),"") | AN32: sim | AR32: Fotos: assets/agco_7038106M1_ecommerce.png | AS32: =IF(AND(N32<>"",N32>1),A32&"-KIT"&N32,A32) | AT32: =IF(AND(N32<>"",N32>1),D32&" — Kit "&N32&" unidades",D32) | AU32: agco_7038106M1_ecommerce.png
A33: 7038106M1 | B33: 7038106M1 | C33: =IFERROR(LOWER(SUBSTITUTE(SUBSTITUTE(SUBSTITUTE(SUBSTITUTE(D33," ","-"),"/","-"),".",""),",","")),"") | D33: Acoplamento da Curva - Kit 60 Unidades - Massey Ferguson 7038106M1 | E33: Peças Plásticas Injetadas | F33: APP | H33: active | I33: AGCO | J33: PLANTADEIRA | K33: =LOWER(CONCATENATE(E33," ",J33," ",D33)) | M33: 84329000 | N33: 60 | O33: 5 | P33: =P32*N33 | Q33: 20 | R33: 32 | S33: 45 | T33: =IFERROR(IF(AND(Q33>0,R33>0,S33>0),(Q33*R33*S33)/6000,""),"") | U33: =IFERROR(IF(AND(Q33>0,R33>0,S33>0),(Q33*R33*S33)/6000,""),"") | V33: =IFERROR(IF(AND(P33>0,U33>0),MAX(P33,U33),IF(P33>0,P33,IF(U33>0,U33,""))),"") | W33: 32.09 | X33: fornecedor | Y33: =Y32*N33 | Z33: 0.2 | AA33: =IFERROR(Y33+W33,"") | AB33: =IFERROR(IF(Z33<1,AA33/(1-Z33),""),"") | AC33: ='01_CONFIG_GLOBAL'!$C$14 | AD33: =IFERROR(AB33*AC33,"") | AE33: =IFERROR(IF(AC33<1,AB33/(1-AC33),""),"") | AM33: =IFERROR(IF(AL33="","sem dados",IF(AE33<AL33*0.95,"abaixo",IF(AE33>AL33*1.05,"acima","em linha"))),"") | AN33: sim | AS33: =IF(AND(N33<>"",N33>1),A33&"-KIT"&N33,A33) | AT33: =IF(AND(N33<>"",N33>1),D33&" — Kit "&N33&" unidades",D33) | AU33: agco_7038106M1_ecommerce.png
A34: ACX5458940 | B34: ACX5458940 | C34: =IFERROR(LOWER(SUBSTITUTE(SUBSTITUTE(SUBSTITUTE(SUBSTITUTE(D34," ","-"),"/","-"),".",""),",","")),"") | D34: Proteção SRM - AGCO ACX5458940 | Monitor de Linhas | E34: Peças Plásticas Injetadas | F34: APP | H34: active | I34: AGCO | J34: PLANTADEIRA | K34: =LOWER(CONCATENATE(E34," ",J34," ",D34)) | M34: 84329000 | N34: 1 | O34: 5 | P34: 0.16 | Q34: 13 | R34: 14 | S34: 13.2 | T34: =IFERROR(IF(AND(Q34>0,R34>0,S34>0),(Q34*R34*S34)/6000,""),"") | U34: =IFERROR(IF(AND(Q34>0,R34>0,S34>0),(Q34*R34*S34)/6000,""),"") | V34: =IFERROR(IF(AND(P34>0,U34>0),MAX(P34,U34),IF(P34>0,P34,IF(U34>0,U34,""))),"") | W34: 1.81 | X34: fornecedor | Y34: 8.64 | Z34: 0.2 | AA34: =IFERROR(Y34+W34,"") | AB34: =IFERROR(IF(Z34<1,AA34/(1-Z34),""),"") | AC34: ='01_CONFIG_GLOBAL'!$C$14 | AD34: =IFERROR(AB34*AC34,"") | AE34: =IFERROR(IF(AC34<1,AB34/(1-AC34),""),"") | AL34: =IFERROR(AVERAGE(AG34,AI34,AK34),"") | AM34: =IFERROR(IF(AL34="","sem dados",IF(AE34<AL34*0.95,"abaixo",IF(AE34>AL34*1.05,"acima","em linha"))),"") | AN34: sim | AR34: Fotos: assets/agco_ACX5458940_ecommerce.png | AS34: =IF(AND(N34<>"",N34>1),A34&"-KIT"&N34,A34) | AT34: =IF(AND(N34<>"",N34>1),D34&" — Kit "&N34&" unidades",D34) | AU34: agco_ACX5458940_ecommerce.png
A35: ACX5458940 | B35: ACX5458940 | C35: =IFERROR(LOWER(SUBSTITUTE(SUBSTITUTE(SUBSTITUTE(SUBSTITUTE(D35," ","-"),"/","-"),".",""),",","")),"") | D35: Proteção SRM - Kit 40 Unidades - AGCO ACX5458940 | E35: Peças Plásticas Injetadas | F35: APP | H35: active | I35: AGCO | J35: PLANTADEIRA | K35: =LOWER(CONCATENATE(E35," ",J35," ",D35)) | M35: 84329000 | N35: 40 | O35: 5 | P35: =P34*N35 | Q35: 35 | R35: 40 | S35: 60 | T35: =IFERROR(IF(AND(Q35>0,R35>0,S35>0),(Q35*R35*S35)/6000,""),"") | U35: =IFERROR(IF(AND(Q35>0,R35>0,S35>0),(Q35*R35*S35)/6000,""),"") | V35: =IFERROR(IF(AND(P35>0,U35>0),MAX(P35,U35),IF(P35>0,P35,IF(U35>0,U35,""))),"") | W35: 72.41 | X35: fornecedor | Y35: =Y34*N35 | Z35: 0.2 | AA35: =IFERROR(Y35+W35,"") | AB35: =IFERROR(IF(Z35<1,AA35/(1-Z35),""),"") | AC35: ='01_CONFIG_GLOBAL'!$C$14 | AD35: =IFERROR(AB35*AC35,"") | AE35: =IFERROR(IF(AC35<1,AB35/(1-AC35),""),"") | AM35: =IFERROR(IF(AL35="","sem dados",IF(AE35<AL35*0.95,"abaixo",IF(AE35>AL35*1.05,"acima","em linha"))),"") | AN35: sim | AS35: =IF(AND(N35<>"",N35>1),A35&"-KIT"&N35,A35) | AT35: =IF(AND(N35<>"",N35>1),D35&" — Kit "&N35&" unidades",D35) | AU35: agco_ACX5458940_ecommerce.png
A36: ACX3601860 | B36: ACX3601860 | C36: =IFERROR(LOWER(SUBSTITUTE(SUBSTITUTE(SUBSTITUTE(SUBSTITUTE(D36," ","-"),"/","-"),".",""),",","")),"") | D36: Copo Venturi - AGCO ACX3601860 | Dosador Pneumático | E36: Peças Plásticas Injetadas | F36: APP | H36: active | I36: AGCO | J36: PLANTADEIRA | K36: =LOWER(CONCATENATE(E36," ",J36," ",D36)) | M36: 84329000 | N36: 1 | O36: 5 | P36: 0.12 | Q36: 8.8 | R36: 13 | S36: 3 | T36: =IFERROR(IF(AND(Q36>0,R36>0,S36>0),(Q36*R36*S36)/6000,""),"") | U36: =IFERROR(IF(AND(Q36>0,R36>0,S36>0),(Q36*R36*S36)/6000,""),"") | V36: =IFERROR(IF(AND(P36>0,U36>0),MAX(P36,U36),IF(P36>0,P36,IF(U36>0,U36,""))),"") | W36: 0.68 | X36: fornecedor | Y36: 9.57 | Z36: 0.2 | AA36: =IFERROR(Y36+W36,"") | AB36: =IFERROR(IF(Z36<1,AA36/(1-Z36),""),"") | AC36: ='01_CONFIG_GLOBAL'!$C$14 | AD36: =IFERROR(AB36*AC36,"") | AE36: =IFERROR(IF(AC36<1,AB36/(1-AC36),""),"") | AL36: =IFERROR(AVERAGE(AG36,AI36,AK36),"") | AM36: =IFERROR(IF(AL36="","sem dados",IF(AE36<AL36*0.95,"abaixo",IF(AE36>AL36*1.05,"acima","em linha"))),"") | AN36: sim | AR36: Fotos: assets/AGCO_ACX3601860_ecommerce_1.png; assets/AGCO_ACX3601860_ecommerce_2.png | AS36: =IF(AND(N36<>"",N36>1),A36&"-KIT"&N36,A36) | AT36: =IF(AND(N36<>"",N36>1),D36&" — Kit "&N36&" unidades",D36) | AU36: AGCO_ACX3601860_ecommerce_1.png | AGCO_ACX3601860_ecommerce_2.png
A37: ACX3601860 | B37: ACX3601860 | C37: =IFERROR(LOWER(SUBSTITUTE(SUBSTITUTE(SUBSTITUTE(SUBSTITUTE(D37," ","-"),"/","-"),".",""),",","")),"") | D37: Copo Venturi - Kit 60 Unidades - AGCO ACX3601860 | E37: Peças Plásticas Injetadas | F37: APP | H37: active | I37: AGCO | J37: PLANTADEIRA | K37: =LOWER(CONCATENATE(E37," ",J37," ",D37)) | M37: 84329000 | N37: 60 | O37: 5 | P37: =P36*N37 | Q37: 30 | R37: 30 | S37: 45 | T37: =IFERROR(IF(AND(Q37>0,R37>0,S37>0),(Q37*R37*S37)/6000,""),"") | U37: =IFERROR(IF(AND(Q37>0,R37>0,S37>0),(Q37*R37*S37)/6000,""),"") | V37: =IFERROR(IF(AND(P37>0,U37>0),MAX(P37,U37),IF(P37>0,P37,IF(U37>0,U37,""))),"") | W37: 40.99 | X37: fornecedor | Y37: =Y36*N37 | Z37: 0.2 | AA37: =IFERROR(Y37+W37,"") | AB37: =IFERROR(IF(Z37<1,AA37/(1-Z37),""),"") | AC37: ='01_CONFIG_GLOBAL'!$C$14 | AD37: =IFERROR(AB37*AC37,"") | AE37: =IFERROR(IF(AC37<1,AB37/(1-AC37),""),"") | AM37: =IFERROR(IF(AL37="","sem dados",IF(AE37<AL37*0.95,"abaixo",IF(AE37>AL37*1.05,"acima","em linha"))),"") | AN37: sim | AS37: =IF(AND(N37<>"",N37>1),A37&"-KIT"&N37,A37) | AT37: =IF(AND(N37<>"",N37>1),D37&" — Kit "&N37&" unidades",D37) | AU37: AGCO_ACX3601860_ecommerce_1.png | AGCO_ACX3601860_ecommerce_2.png
A38: 4383933M4 | B38: 4383933M4 | C38: =IFERROR(LOWER(SUBSTITUTE(SUBSTITUTE(SUBSTITUTE(SUBSTITUTE(D38," ","-"),"/","-"),".",""),",","")),"") | D38: Dobradiça Direita Superior - Massey Ferguson 4383933M4 | E38: Peças Plásticas Injetadas | F38: APP | H38: active | I38: AGCO | J38: TRATOR | K38: =LOWER(CONCATENATE(E38," ",J38," ",D38)) | M38: 84329000 | N38: 1 | O38: 5 | P38: 0.19 | Q38: 3 | R38: 12.5 | S38: 8 | T38: =IFERROR(IF(AND(Q38>0,R38>0,S38>0),(Q38*R38*S38)/6000,""),"") | U38: =IFERROR(IF(AND(Q38>0,R38>0,S38>0),(Q38*R38*S38)/6000,""),"") | V38: =IFERROR(IF(AND(P38>0,U38>0),MAX(P38,U38),IF(P38>0,P38,IF(U38>0,U38,""))),"") | W38: 2.08 | X38: fornecedor | Y38: 20.01 | Z38: 0.2 | AA38: =IFERROR(Y38+W38,"") | AB38: =IFERROR(IF(Z38<1,AA38/(1-Z38),""),"") | AC38: ='01_CONFIG_GLOBAL'!$C$14 | AD38: =IFERROR(AB38*AC38,"") | AE38: =IFERROR(IF(AC38<1,AB38/(1-AC38),""),"") | AL38: =IFERROR(AVERAGE(AG38,AI38,AK38),"") | AM38: =IFERROR(IF(AL38="","sem dados",IF(AE38<AL38*0.95,"abaixo",IF(AE38>AL38*1.05,"acima","em linha"))),"") | AN38: sim | AR38: Fotos: assets/AGCO_4383933M4_ecommerce_1.png; assets/AGCO_4383933M4_ecommerce_2.png | AS38: =IF(AND(N38<>"",N38>1),A38&"-KIT"&N38,A38) | AT38: =IF(AND(N38<>"",N38>1),D38&" — Kit "&N38&" unidades",D38) | AU38: AGCO_4383933M4_ecommerce_1.png | AGCO_4383933M4_ecommerce_2.png
A39: 4383933M4 | B39: 4383933M4 | C39: =IFERROR(LOWER(SUBSTITUTE(SUBSTITUTE(SUBSTITUTE(SUBSTITUTE(D39," ","-"),"/","-"),".",""),",","")),"") | D39: Dobradiça Direita Superior - Kit 10 Unidades - Massey Ferguson 4383933M4 | E39: Peças Plásticas Injetadas | F39: APP | H39: active | I39: AGCO | J39: TRATOR | K39: =LOWER(CONCATENATE(E39," ",J39," ",D39)) | M39: 84329000 | N39: 10 | O39: 5 | P39: =P38*N39 | Q39: 35 | R39: 15 | S39: 10 | T39: =IFERROR(IF(AND(Q39>0,R39>0,S39>0),(Q39*R39*S39)/6000,""),"") | U39: =IFERROR(IF(AND(Q39>0,R39>0,S39>0),(Q39*R39*S39)/6000,""),"") | V39: =IFERROR(IF(AND(P39>0,U39>0),MAX(P39,U39),IF(P39>0,P39,IF(U39>0,U39,""))),"") | W39: 20.77 | X39: fornecedor | Y39: =Y38*N39 | Z39: 0.2 | AA39: =IFERROR(Y39+W39,"") | AB39: =IFERROR(IF(Z39<1,AA39/(1-Z39),""),"") | AC39: ='01_CONFIG_GLOBAL'!$C$14 | AD39: =IFERROR(AB39*AC39,"") | AE39: =IFERROR(IF(AC39<1,AB39/(1-AC39),""),"") | AM39: =IFERROR(IF(AL39="","sem dados",IF(AE39<AL39*0.95,"abaixo",IF(AE39>AL39*1.05,"acima","em linha"))),"") | AN39: sim | AS39: =IF(AND(N39<>"",N39>1),A39&"-KIT"&N39,A39) | AT39: =IF(AND(N39<>"",N39>1),D39&" — Kit "&N39&" unidades",D39) | AU39: AGCO_4383933M4_ecommerce_1.png | AGCO_4383933M4_ecommerce_2.png
A40: 4383934M4 | B40: 4383934M4 | C40: =IFERROR(LOWER(SUBSTITUTE(SUBSTITUTE(SUBSTITUTE(SUBSTITUTE(D40," ","-"),"/","-"),".",""),",","")),"") | D40: Dobradiça Direita Inferior - Massey Ferguson 4383934M4 | E40: Peças Plásticas Injetadas | F40: APP | H40: active | I40: AGCO | J40: TRATOR | K40: =LOWER(CONCATENATE(E40," ",J40," ",D40)) | M40: 84329000 | N40: 1 | O40: 5 | P40: 0.19 | Q40: 3 | R40: 12.5 | S40: 8 | T40: =IFERROR(IF(AND(Q40>0,R40>0,S40>0),(Q40*R40*S40)/6000,""),"") | U40: =IFERROR(IF(AND(Q40>0,R40>0,S40>0),(Q40*R40*S40)/6000,""),"") | V40: =IFERROR(IF(AND(P40>0,U40>0),MAX(P40,U40),IF(P40>0,P40,IF(U40>0,U40,""))),"") | W40: 2.08 | X40: fornecedor | Y40: 20.01 | Z40: 0.2 | AA40: =IFERROR(Y40+W40,"") | AB40: =IFERROR(IF(Z40<1,AA40/(1-Z40),""),"") | AC40: ='01_CONFIG_GLOBAL'!$C$14 | AD40: =IFERROR(AB40*AC40,"") | AE40: =IFERROR(IF(AC40<1,AB40/(1-AC40),""),"") | AL40: =IFERROR(AVERAGE(AG40,AI40,AK40),"") | AM40: =IFERROR(IF(AL40="","sem dados",IF(AE40<AL40*0.95,"abaixo",IF(AE40>AL40*1.05,"acima","em linha"))),"") | AN40: sim | AR40: Fotos: assets/AGCO_4383934M4_ecommerce_1.png; assets/AGCO_4383934M4_ecommerce_2.png | AS40: =IF(AND(N40<>"",N40>1),A40&"-KIT"&N40,A40) | AT40: =IF(AND(N40<>"",N40>1),D40&" — Kit "&N40&" unidades",D40) | AU40: AGCO_4383934M4_ecommerce_1.png | AGCO_4383934M4_ecommerce_2.png
A41: 4383934M4 | B41: 4383934M4 | C41: =IFERROR(LOWER(SUBSTITUTE(SUBSTITUTE(SUBSTITUTE(SUBSTITUTE(D41," ","-"),"/","-"),".",""),",","")),"") | D41: Dobradiça Direita Inferior - Kit 10 Unidades - Massey Ferguson 4383934M4 | E41: Peças Plásticas Injetadas | F41: APP | H41: active | I41: AGCO | J41: TRATOR | K41: =LOWER(CONCATENATE(E41," ",J41," ",D41)) | M41: 84329000 | N41: 10 | O41: 5 | P41: =P40*N41 | Q41: 35 | R41: 15 | S41: 10 | T41: =IFERROR(IF(AND(Q41>0,R41>0,S41>0),(Q41*R41*S41)/6000,""),"") | U41: =IFERROR(IF(AND(Q41>0,R41>0,S41>0),(Q41*R41*S41)/6000,""),"") | V41: =IFERROR(IF(AND(P41>0,U41>0),MAX(P41,U41),IF(P41>0,P41,IF(U41>0,U41,""))),"") | W41: 20.77 | X41: fornecedor | Y41: =Y40*N41 | Z41: 0.2 | AA41: =IFERROR(Y41+W41,"") | AB41: =IFERROR(IF(Z41<1,AA41/(1-Z41),""),"") | AC41: ='01_CONFIG_GLOBAL'!$C$14 | AD41: =IFERROR(AB41*AC41,"") | AE41: =IFERROR(IF(AC41<1,AB41/(1-AC41),""),"") | AM41: =IFERROR(IF(AL41="","sem dados",IF(AE41<AL41*0.95,"abaixo",IF(AE41>AL41*1.05,"acima","em linha"))),"") | AN41: sim | AS41: =IF(AND(N41<>"",N41>1),A41&"-KIT"&N41,A41) | AT41: =IF(AND(N41<>"",N41>1),D41&" — Kit "&N41&" unidades",D41) | AU41: AGCO_4383934M4_ecommerce_1.png | AGCO_4383934M4_ecommerce_2.png
A42: ACX3473430 | B42: ACX3473430 | C42: =IFERROR(LOWER(SUBSTITUTE(SUBSTITUTE(SUBSTITUTE(SUBSTITUTE(D42," ","-"),"/","-"),".",""),",","")),"") | D42: Tampa Maior do Tubo - AGCO ACX3473430 | E42: Peças Plásticas Injetadas | F42: APP | H42: active | I42: AGCO | J42: PLANTADEIRA | K42: =LOWER(CONCATENATE(E42," ",J42," ",D42)) | M42: 84329000 | N42: 1 | O42: 5 | P42: 0.08 | Q42: 10 | R42: 10 | S42: 2.5 | T42: =IFERROR(IF(AND(Q42>0,R42>0,S42>0),(Q42*R42*S42)/6000,""),"") | U42: =IFERROR(IF(AND(Q42>0,R42>0,S42>0),(Q42*R42*S42)/6000,""),"") | V42: =IFERROR(IF(AND(P42>0,U42>0),MAX(P42,U42),IF(P42>0,P42,IF(U42>0,U42,""))),"") | W42: 0.66 | X42: fornecedor | Y42: 5.46 | Z42: 0.2 | AA42: =IFERROR(Y42+W42,"") | AB42: =IFERROR(IF(Z42<1,AA42/(1-Z42),""),"") | AC42: ='01_CONFIG_GLOBAL'!$C$14 | AD42: =IFERROR(AB42*AC42,"") | AE42: =IFERROR(IF(AC42<1,AB42/(1-AC42),""),"") | AL42: =IFERROR(AVERAGE(AG42,AI42,AK42),"") | AM42: =IFERROR(IF(AL42="","sem dados",IF(AE42<AL42*0.95,"abaixo",IF(AE42>AL42*1.05,"acima","em linha"))),"") | AN42: sim | AS42: =IF(AND(N42<>"",N42>1),A42&"-KIT"&N42,A42) | AT42: =IF(AND(N42<>"",N42>1),D42&" — Kit "&N42&" unidades",D42) | AU42: AGCO_ACX3473430_ecommerce_1.png | AGCO_ACX3473430_ecommerce_2.png
A43: ACX3473430 | B43: ACX3473430 | C43: =IFERROR(LOWER(SUBSTITUTE(SUBSTITUTE(SUBSTITUTE(SUBSTITUTE(D43," ","-"),"/","-"),".",""),",","")),"") | D43: Tampa Maior do Tubo - Kit 40 Unidades - AGCO ACX3473430 | E43: Peças Plásticas Injetadas | F43: APP | H43: active | I43: AGCO | J43: PLANTADEIRA | K43: =LOWER(CONCATENATE(E43," ",J43," ",D43)) | M43: 84329000 | N43: 40 | O43: 5 | P43: =P42*N43 | Q43: 22 | R43: 22 | S43: 35 | T43: =IFERROR(IF(AND(Q43>0,R43>0,S43>0),(Q43*R43*S43)/6000,""),"") | U43: =IFERROR(IF(AND(Q43>0,R43>0,S43>0),(Q43*R43*S43)/6000,""),"") | V43: =IFERROR(IF(AND(P43>0,U43>0),MAX(P43,U43),IF(P43>0,P43,IF(U43>0,U43,""))),"") | W43: 26.2 | X43: fornecedor | Y43: =Y42*N43 | Z43: 0.2 | AA43: =IFERROR(Y43+W43,"") | AB43: =IFERROR(IF(Z43<1,AA43/(1-Z43),""),"") | AC43: ='01_CONFIG_GLOBAL'!$C$14 | AD43: =IFERROR(AB43*AC43,"") | AE43: =IFERROR(IF(AC43<1,AB43/(1-AC43),""),"") | AM43: =IFERROR(IF(AL43="","sem dados",IF(AE43<AL43*0.95,"abaixo",IF(AE43>AL43*1.05,"acima","em linha"))),"") | AN43: sim | AS43: =IF(AND(N43<>"",N43>1),A43&"-KIT"&N43,A43) | AT43: =IF(AND(N43<>"",N43>1),D43&" — Kit "&N43&" unidades",D43) | AU43: AGCO_ACX3473430-KIT40_ecommerce.png | AGCO_ACX3473430_ecommerce_2.png
A44: ACX329796A | B44: ACX329796A | C44: =IFERROR(LOWER(SUBSTITUTE(SUBSTITUTE(SUBSTITUTE(SUBSTITUTE(D44," ","-"),"/","-"),".",""),",","")),"") | D44: Defletor do Radiador - AGCO ACX329796A | E44: Peças Plásticas Injetadas | F44: APP | H44: active | I44: AGCO | J44: PLANTADEIRA | K44: =LOWER(CONCATENATE(E44," ",J44," ",D44)) | M44: 84329000 | N44: 1 | O44: 5 | P44: 1.85 | Q44: 14 | R44: 52.5 | S44: 52.5 | T44: =IFERROR(IF(AND(Q44>0,R44>0,S44>0),(Q44*R44*S44)/6000,""),"") | U44: =IFERROR(IF(AND(Q44>0,R44>0,S44>0),(Q44*R44*S44)/6000,""),"") | V44: =IFERROR(IF(AND(P44>0,U44>0),MAX(P44,U44),IF(P44>0,P44,IF(U44>0,U44,""))),"") | W44: 37.07 | X44: fornecedor | Y44: 85.45 | Z44: 0.2 | AA44: =IFERROR(Y44+W44,"") | AB44: =IFERROR(IF(Z44<1,AA44/(1-Z44),""),"") | AC44: ='01_CONFIG_GLOBAL'!$C$14 | AD44: =IFERROR(AB44*AC44,"") | AE44: =IFERROR(IF(AC44<1,AB44/(1-AC44),""),"") | AL44: =IFERROR(AVERAGE(AG44,AI44,AK44),"") | AM44: =IFERROR(IF(AL44="","sem dados",IF(AE44<AL44*0.95,"abaixo",IF(AE44>AL44*1.05,"acima","em linha"))),"") | AN44: sim | AR44: Fotos: assets/agco_ACX329796A_ecommerce.png | AS44: =IF(AND(N44<>"",N44>1),A44&"-KIT"&N44,A44) | AT44: =IF(AND(N44<>"",N44>1),D44&" — Kit "&N44&" unidades",D44) | AU44: agco_ACX329796A_ecommerce.png
A45: 33070004 | B45: 33070004 | C45: =IFERROR(LOWER(SUBSTITUTE(SUBSTITUTE(SUBSTITUTE(SUBSTITUTE(D45," ","-"),"/","-"),".",""),",","")),"") | D45: Condutor Reto de Sementes - AGCO 33070004 | E45: Peças Plásticas Injetadas | F45: APP | H45: active | I45: AGCO | J45: PLANTADEIRA | K45: =LOWER(CONCATENATE(E45," ",J45," ",D45)) | M45: 84329000 | N45: 1 | O45: 5 | P45: 0.14 | Q45: 6.7 | R45: 6.7 | S45: 47.5 | T45: =IFERROR(IF(AND(Q45>0,R45>0,S45>0),(Q45*R45*S45)/6000,""),"") | U45: =IFERROR(IF(AND(Q45>0,R45>0,S45>0),(Q45*R45*S45)/6000,""),"") | V45: =IFERROR(IF(AND(P45>0,U45>0),MAX(P45,U45),IF(P45>0,P45,IF(U45>0,U45,""))),"") | W45: 2.67 | X45: fornecedor | Y45: 6.44 | Z45: 0.2 | AA45: =IFERROR(Y45+W45,"") | AB45: =IFERROR(IF(Z45<1,AA45/(1-Z45),""),"") | AC45: ='01_CONFIG_GLOBAL'!$C$14 | AD45: =IFERROR(AB45*AC45,"") | AE45: =IFERROR(IF(AC45<1,AB45/(1-AC45),""),"") | AL45: =IFERROR(AVERAGE(AG45,AI45,AK45),"") | AM45: =IFERROR(IF(AL45="","sem dados",IF(AE45<AL45*0.95,"abaixo",IF(AE45>AL45*1.05,"acima","em linha"))),"") | AN45: sim | AR45: Fotos: assets/agco_33070004_ecommerce.png | AS45: =IF(AND(N45<>"",N45>1),A45&"-KIT"&N45,A45) | AT45: =IF(AND(N45<>"",N45>1),D45&" — Kit "&N45&" unidades",D45) | AU45: agco_33070004_ecommerce.png
A46: 33070004 | B46: 33070004 | C46: =IFERROR(LOWER(SUBSTITUTE(SUBSTITUTE(SUBSTITUTE(SUBSTITUTE(D46," ","-"),"/","-"),".",""),",","")),"") | D46: Condutor Reto de Sementes - Kit 25 Unidades - AGCO 33070004 | E46: Peças Plásticas Injetadas | F46: APP | H46: active | I46: AGCO | J46: PLANTADEIRA | K46: =LOWER(CONCATENATE(E46," ",J46," ",D46)) | M46: 84329000 | N46: 25 | O46: 5 | P46: =P45*N46 | Q46: 40 | R46: 40 | S46: 50 | T46: =IFERROR(IF(AND(Q46>0,R46>0,S46>0),(Q46*R46*S46)/6000,""),"") | U46: =IFERROR(IF(AND(Q46>0,R46>0,S46>0),(Q46*R46*S46)/6000,""),"") | V46: =IFERROR(IF(AND(P46>0,U46>0),MAX(P46,U46),IF(P46>0,P46,IF(U46>0,U46,""))),"") | W46: 66.85 | X46: fornecedor | Y46: =Y45*N46 | Z46: 0.2 | AA46: =IFERROR(Y46+W46,"") | AB46: =IFERROR(IF(Z46<1,AA46/(1-Z46),""),"") | AC46: ='01_CONFIG_GLOBAL'!$C$14 | AD46: =IFERROR(AB46*AC46,"") | AE46: =IFERROR(IF(AC46<1,AB46/(1-AC46),""),"") | AM46: =IFERROR(IF(AL46="","sem dados",IF(AE46<AL46*0.95,"abaixo",IF(AE46>AL46*1.05,"acima","em linha"))),"") | AN46: sim | AS46: =IF(AND(N46<>"",N46>1),A46&"-KIT"&N46,A46) | AT46: =IF(AND(N46<>"",N46>1),D46&" — Kit "&N46&" unidades",D46) | AU46: agco_33070004_ecommerce.png
A47: 6237989M1 | B47: 6237989M1 | D47: Corpo Bico 1 Polegada e Saídas - AGCO 6237989M1 | E47: Peças Plásticas Injetadas | F47: APP | H47: active | I47: AGCO | J47: PULVERIZADOR | L47: 6237989-242 | M47: 84329000 | N47: 1 | O47: 5 | P47: 0.132 | Q47: 10.9 | R47: 9.4 | S47: 9.2 | T47: =IFERROR(IF(AND(Q47>0,R47>0,S47>0),(Q47*R47*S47)/6000,""),"") | U47: =IFERROR(IF(AND(Q47>0,R47>0,S47>0),(Q47*R47*S47)/6000,""),"") | V47: =IFERROR(IF(AND(P47>0,U47>0),MAX(P47,U47),IF(P47>0,P47,IF(U47>0,U47,""))),"") | W47: 2.5 | X47: fornecedor | Y47: 26.46 | Z47: 0.2 | AA47: =IFERROR(Y47+W47,"") | AB47: =IFERROR(IF(Z47<1,AA47/(1-Z47),""),"") | AC47: ='01_CONFIG_GLOBAL'!$C$14 | AD47: =IFERROR(AB47*AC47,"") | AE47: =IFERROR(IF(AC47<1,AB47/(1-AC47),""),"") | AM47: =IFERROR(IF(AL47="","sem dados",IF(AE47<AL47*0.95,"abaixo",IF(AE47>AL47*1.05,"acima","em linha"))),"") | AN47: sim | AS47: =IF(AND(N47<>"",N47>1),A47&"-KIT"&N47,A47) | AT47: =IF(AND(N47<>"",N47>1),D47&" — Kit "&N47&" unidades",D47) | AU47: AGCO_6237989M1_ecommerce_1.png | AGCO_6237989M1_ecommerce_2.png
A48: 6237989M1 | B48: 6237989M1 | D48: Corpo Bico 1 Polegada e Saídas - Kit 10 Unidades - AGCO 6237989M1 | E48: Peças Plásticas Injetadas | F48: APP | H48: active | I48: AGCO | J48: PULVERIZADOR | L48: 6237989-242 | M48: 84329000 | N48: 10 | O48: 5 | P48: =P47*N48 | Q48: 17 | R48: 35 | S48: 22 | T48: =IFERROR(IF(AND(Q48>0,R48>0,S48>0),(Q48*R48*S48)/6000,""),"") | U48: =IFERROR(IF(AND(Q48>0,R48>0,S48>0),(Q48*R48*S48)/6000,""),"") | V48: =IFERROR(IF(AND(P48>0,U48>0),MAX(P48,U48),IF(P48>0,P48,IF(U48>0,U48,""))),"") | W48: 25.01 | X48: fornecedor | Y48: =Y47*N48 | Z48: 0.2 | AA48: =IFERROR(Y48+W48,"") | AB48: =IFERROR(IF(Z48<1,AA48/(1-Z48),""),"") | AC48: ='01_CONFIG_GLOBAL'!$C$14 | AD48: =IFERROR(AB48*AC48,"") | AE48: =IFERROR(IF(AC48<1,AB48/(1-AC48),""),"") | AM48: =IFERROR(IF(AL48="","sem dados",IF(AE48<AL48*0.95,"abaixo",IF(AE48>AL48*1.05,"acima","em linha"))),"") | AN48: sim | AS48: =IF(AND(N48<>"",N48>1),A48&"-KIT"&N48,A48) | AT48: =IF(AND(N48<>"",N48>1),D48&" — Kit "&N48&" unidades",D48) | AU48: AGCO_6237989M1_ecommerce_1.png | AGCO_6237989M1_ecommerce_2.png
A49: ACX363311C | B49: ACX363311C | C49: =IFERROR(LOWER(SUBSTITUTE(SUBSTITUTE(SUBSTITUTE(SUBSTITUTE(D49," ","-"),"/","-"),".",""),",","")),"") | D49: Copo Venturi C - Kit 25 Unidades - AGCO ACX363311C | E49: Peças Plásticas Injetadas | F49: APP | H49: active | I49: AGCO | J49: PLANTADEIRA | K49: =LOWER(CONCATENATE(E49," ",J49," ",D49)) | M49: 84329000 | N49: 25 | O49: 5 | P49: =P22*N49 | Q49: 45 | R49: 32 | S49: 7.5 | T49: =IFERROR(IF(AND(Q49>0,R49>0,S49>0),(Q49*R49*S49)/6000,""),"") | U49: =IFERROR(IF(AND(Q49>0,R49>0,S49>0),(Q49*R49*S49)/6000,""),"") | V49: =IFERROR(IF(AND(P49>0,U49>0),MAX(P49,U49),IF(P49>0,P49,IF(U49>0,U49,""))),"") | W49: 27.8 | X49: fornecedor | Y49: =Y22*N49 | Z49: 0.2 | AA49: =IFERROR(Y49+W49,"") | AB49: =IFERROR(IF(Z49<1,AA49/(1-Z49),""),"") | AC49: ='01_CONFIG_GLOBAL'!$C$14 | AD49: =IFERROR(AB49*AC49,"") | AE49: =IFERROR(IF(AC49<1,AB49/(1-AC49),""),"") | AL49: =IFERROR(AVERAGE(AG49,AI49,AK49),"") | AM49: =IFERROR(IF(AL49="","sem dados",IF(AE49<AL49*0.95,"abaixo",IF(AE49>AL49*1.05,"acima","em linha"))),"") | AN49: sim | AR49: Fotos: assets/agco_ACX363311C_ecommerce.png | AS49: =IF(AND(N49<>"",N49>1),A49&"-KIT"&N49,A49) | AT49: =IF(AND(N49<>"",N49>1),D49&" — Kit "&N49&" unidades",D49) | AU49: AGCO_ACX3601860_ecommerce_2.png
A50: ACX363311B | B50: ACX363311B | C50: =IFERROR(LOWER(SUBSTITUTE(SUBSTITUTE(SUBSTITUTE(SUBSTITUTE(D50," ","-"),"/","-"),".",""),",","")),"") | D50: Copo Venturi B - Kit 25 Unidades - AGCO ACX363311B | E50: Peças Plásticas Injetadas | F50: APP | H50: active | I50: AGCO | J50: PLANTADEIRA | K50: =LOWER(CONCATENATE(E50," ",J50," ",D50)) | M50: 84329000 | N50: 25 | O50: 5 | P50: =P24*N50 | Q50: 45 | R50: 32 | S50: 7.5 | T50: =IFERROR(IF(AND(Q50>0,R50>0,S50>0),(Q50*R50*S50)/6000,""),"") | U50: =IFERROR(IF(AND(Q50>0,R50>0,S50>0),(Q50*R50*S50)/6000,""),"") | V50: =IFERROR(IF(AND(P50>0,U50>0),MAX(P50,U50),IF(P50>0,P50,IF(U50>0,U50,""))),"") | W50: 27.8 | X50: fornecedor | Y50: =Y24*N50 | Z50: 0.2 | AA50: =IFERROR(Y50+W50,"") | AB50: =IFERROR(IF(Z50<1,AA50/(1-Z50),""),"") | AC50: ='01_CONFIG_GLOBAL'!$C$14 | AD50: =IFERROR(AB50*AC50,"") | AE50: =IFERROR(IF(AC50<1,AB50/(1-AC50),""),"") | AL50: =IFERROR(AVERAGE(AG50,AI50,AK50),"") | AM50: =IFERROR(IF(AL50="","sem dados",IF(AE50<AL50*0.95,"abaixo",IF(AE50>AL50*1.05,"acima","em linha"))),"") | AN50: sim | AR50: Fotos: assets/agco_ACX363311B_ecommerce.png | AS50: =IF(AND(N50<>"",N50>1),A50&"-KIT"&N50,A50) | AT50: =IF(AND(N50<>"",N50>1),D50&" — Kit "&N50&" unidades",D50) | AU50: AGCO_ACX3601860_ecommerce_1.png
A51: ACX3601860 | B51: ACX3601860 | C51: =IFERROR(LOWER(SUBSTITUTE(SUBSTITUTE(SUBSTITUTE(SUBSTITUTE(D51," ","-"),"/","-"),".",""),",","")),"") | D51: Copo Venturi - Kit 25 Unidades - AGCO ACX3601860 | E51: Peças Plásticas Injetadas | F51: APP | H51: active | I51: AGCO | J51: PLANTADEIRA | K51: =LOWER(CONCATENATE(E51," ",J51," ",D51)) | M51: 84329000 | N51: 25 | O51: 5 | P51: =P36*N51 | Q51: 30 | R51: 30 | S51: 18.8 | T51: =IFERROR(IF(AND(Q51>0,R51>0,S51>0),(Q51*R51*S51)/6000,""),"") | U51: =IFERROR(IF(AND(Q51>0,R51>0,S51>0),(Q51*R51*S51)/6000,""),"") | V51: =IFERROR(IF(AND(P51>0,U51>0),MAX(P51,U51),IF(P51>0,P51,IF(U51>0,U51,""))),"") | W51: 24.81 | X51: fornecedor | Y51: =Y36*N51 | Z51: 0.2 | AA51: =IFERROR(Y51+W51,"") | AB51: =IFERROR(IF(Z51<1,AA51/(1-Z51),""),"") | AC51: ='01_CONFIG_GLOBAL'!$C$14 | AD51: =IFERROR(AB51*AC51,"") | AE51: =IFERROR(IF(AC51<1,AB51/(1-AC51),""),"") | AL51: =IFERROR(AVERAGE(AG51,AI51,AK51),"") | AM51: =IFERROR(IF(AL51="","sem dados",IF(AE51<AL51*0.95,"abaixo",IF(AE51>AL51*1.05,"acima","em linha"))),"") | AN51: sim | AR51: Fotos: assets/AGCO_ACX3601860_ecommerce_1.png; assets/AGCO_ACX3601860_ecommerce_2.png | AS51: =IF(AND(N51<>"",N51>1),A51&"-KIT"&N51,A51) | AT51: =IF(AND(N51<>"",N51>1),D51&" — Kit "&N51&" unidades",D51) | AU51: AGCO_ACX3601860_ecommerce_1.png | AGCO_ACX3601860_ecommerce_2.png

Sheet 04_GRECO
A1: APP — Agro Peças Padrão | Master 04_GRECO
A2: Total de SKUs: | B2: =COUNTA(A6:A99996) | D2: Faltando embalagem: | E2: =COUNTIF(U6:U99996,"FALTA") | G2: Cadastrados Shopify: | H2: =COUNTIF(AK6:AK99996,"sim") | J2: Divergentes: | K2: =COUNTIF(AK6:AK99996,"divergente")
A4: IDENTIFICAÇÃO | I4: APLICAÇÃO TÉCNICA | N4: LOGÍSTICA E EMBALAGEM | V4: CUSTO E PRECIFICAÇÃO | AC4: PESQUISA DE MERCADO | AK4: WORKFLOW
A5: SKU / Código | B5: Part Number | C5: Handle (Shopify) | D5: Title (PT-BR) | E5: Product Type | F5: Vendor (Fabricante) | G5: Tags (vírgula) | H5: Status | I5: Montadora compatível | J5: Equipamento / Modelo | K5: Função / Aplicação | L5: Códigos cruzados | M5: Lead Time | N5: Peso (kg) | O5: Comprimento (cm) | P5: Largura (cm) | Q5: Altura (cm) | R5: Peso cubado (kg) | S5: Peso considerado (kg) | T5: Frete fábrica → eCom () | U5: Origem do dado embalagem | V5: Custo unitário () | W5: % Margem de lucro | X5: Custo + frete inbound () | Y5: Preço c/ margem () | Z5: Taxa Mercado Pago (%) | AA5: Taxa MP () | AB5: Preço final site () | AC5: Concorrente 1 — Nome | AD5: Concorrente 1 — Preço () | AE5: Concorrente 2 — Nome | AF5: Concorrente 2 — Preço () | AG5: Concorrente 3 — Nome | AH5: Concorrente 3 — Preço () | AI5: Preço médio concorrência () | AJ5: Posicionamento | AK5: Cadastrado Shopify? | AL5: Última atualização | AM5: Operador responsável | AN5: Observações | AO5: SKU Shopify (derivado) | AP5: Título Shopify (derivado) | AQ5: Imagens site (assets)
A6: GR141207 | B6: GR141207 | C6: =IFERROR(LOWER(SUBSTITUTE(SUBSTITUTE(SUBSTITUTE(SUBSTITUTE(D6," ","-"),"/","-"),".",""),",","")),"") | D6: GPS Agrícola GR200 - Greco Agro Tech | Navegação de Precisão | E6: Sensores Agrícolas | F6: GRECO | H6: active | I6: TODAS AS MARCAS | J6: PULVERZADOR | K6: SISTEMA POSSUI MODO RETO, CURVO E LIVRE DE TRABALHO, SALVA AS AREAS, PINTA TELA E BARRA DE LUZ PARA GUIA NA OPERAÇÃO. | M6: 7 | N6: 2.21 | O6: 58 | P6: 40 | Q6: 26.5 | R6: =IFERROR(IF(AND(O6>0,P6>0,Q6>0),(O6*P6*Q6)/6000,""),"") | S6: =IFERROR(IF(AND(N6>0,R6>0),MAX(N6,R6),IF(N6>0,N6,IF(R6>0,R6,""))),"") | T6: 77 | U6: fornecedor | V6: 4100 | W6: 0.2 | X6: =IFERROR(V6+T6,"") | Y6: =IFERROR(IF(W6<1,X6/(1-W6),""),"") | Z6: ='01_CONFIG_GLOBAL'!$C$14 | AA6: =IFERROR(Y6*Z6,"") | AB6: =IFERROR(IF(Z6<1,Y6/(1-Z6),""),"") | AI6: =IFERROR(AVERAGE(AD6,AF6,AH6),"") | AJ6: =IFERROR(IF(AI6="","sem dados",IF(AB6<AI6*0.95,"abaixo",IF(AB6>AI6*1.05,"acima","em linha"))),"") | AK6: sim | AN6: Fotos: assets/greco_GR141207_ecommerce.png | AO6: =A6 | AP6: =D6 | AQ6: greco_GR141207_ecommerce.png
A7: GR141165 | B7: GR141165 | C7: =IFERROR(LOWER(SUBSTITUTE(SUBSTITUTE(SUBSTITUTE(SUBSTITUTE(D7," ","-"),"/","-"),".",""),",","")),"") | D7: Kit de Iluminação Noturna Pulverização - Greco Agro Tech | E7: Sensores Agrícolas | F7: GRECO | H7: active | I7: TODAS AS MARCAS | J7: PULVERZADOR | K7: LUZ AZUL PARA PULVERIZAÇÃO. | M7: 7 | N7: 0.5 | O7: 58 | P7: 40 | Q7: 26.5 | R7: =IFERROR(IF(AND(O7>0,P7>0,Q7>0),(O7*P7*Q7)/6000,""),"") | S7: =IFERROR(IF(AND(N7>0,R7>0),MAX(N7,R7),IF(N7>0,N7,IF(R7>0,R7,""))),"") | T7: 60.69 | U7: fornecedor | V7: 890 | W7: 0.2 | X7: =IFERROR(V7+T7,"") | Y7: =IFERROR(IF(W7<1,X7/(1-W7),""),"") | Z7: ='01_CONFIG_GLOBAL'!$C$14 | AA7: =IFERROR(Y7*Z7,"") | AB7: =IFERROR(IF(Z7<1,Y7/(1-Z7),""),"") | AI7: =IFERROR(AVERAGE(AD7,AF7,AH7),"") | AJ7: =IFERROR(IF(AI7="","sem dados",IF(AB7<AI7*0.95,"abaixo",IF(AB7>AI7*1.05,"acima","em linha"))),"") | AK7: sim | AN7: Fotos: assets/greco_GR141165_ecommerce.png | AO7: =A7 | AP7: =D7 | AQ7: greco_GR141165_ecommerce.png
A8: GR140990 | B8: GR140990 | C8: =IFERROR(LOWER(SUBSTITUTE(SUBSTITUTE(SUBSTITUTE(SUBSTITUTE(D8," ","-"),"/","-"),".",""),",","")),"") | D8: KIT PONTA DE CERCA | E8: Sensores Agrícolas | F8: GRECO | H8: active | I8: TODAS AS MARCAS | J8: PULVERZADOR | K8: 30 METROS | M8: 7 | N8: 4.5 | O8: 58 | P8: 40 | Q8: 26.5 | R8: =IFERROR(IF(AND(O8>0,P8>0,Q8>0),(O8*P8*Q8)/6000,""),"") | S8: =IFERROR(IF(AND(N8>0,R8>0),MAX(N8,R8),IF(N8>0,N8,IF(R8>0,R8,""))),"") | T8: 62.4 | U8: fornecedor | V8: 1097 | W8: 0.2 | X8: =IFERROR(V8+T8,"") | Y8: =IFERROR(IF(W8<1,X8/(1-W8),""),"") | Z8: ='01_CONFIG_GLOBAL'!$C$14 | AA8: =IFERROR(Y8*Z8,"") | AB8: =IFERROR(IF(Z8<1,Y8/(1-Z8),""),"") | AI8: =IFERROR(AVERAGE(AD8,AF8,AH8),"") | AJ8: =IFERROR(IF(AI8="","sem dados",IF(AB8<AI8*0.95,"abaixo",IF(AB8>AI8*1.05,"acima","em linha"))),"") | AK8: não | AN8: Fotos: assets/greco_GR140990-20M_ecommerce.png; assets/greco_GR140990-30M_ecommerce.png | AO8: =A8 | AP8: =D8
A9: GR140682 | B9: GR140682 | C9: =IFERROR(LOWER(SUBSTITUTE(SUBSTITUTE(SUBSTITUTE(SUBSTITUTE(D9," ","-"),"/","-"),".",""),",","")),"") | D9: Sensor de Levante Haste - Greco Agro Tech | Precision Planting PM400 | E9: Sensores Agrícolas | F9: GRECO | H9: active | I9: TODAS AS MARCAS | J9: PULVERZADOR / PLANTADEIRA | K9: COMPATÍVEL COM PRECISION PLANTING – PM400 E COD AGCO PP727123 | M9: 7 | N9: 0.42 | O9: 31 | P9: 24 | Q9: 25 | R9: =IFERROR(IF(AND(O9>0,P9>0,Q9>0),(O9*P9*Q9)/6000,""),"") | S9: =IFERROR(IF(AND(N9>0,R9>0),MAX(N9,R9),IF(N9>0,N9,IF(R9>0,R9,""))),"") | T9: 29.27 | U9: fornecedor | V9: 590 | W9: 0.2 | X9: =IFERROR(V9+T9,"") | Y9: =IFERROR(IF(W9<1,X9/(1-W9),""),"") | Z9: ='01_CONFIG_GLOBAL'!$C$14 | AA9: =IFERROR(Y9*Z9,"") | AB9: =IFERROR(IF(Z9<1,Y9/(1-Z9),""),"") | AI9: =IFERROR(AVERAGE(AD9,AF9,AH9),"") | AJ9: =IFERROR(IF(AI9="","sem dados",IF(AB9<AI9*0.95,"abaixo",IF(AB9>AI9*1.05,"acima","em linha"))),"") | AK9: sim | AN9: Fotos: assets/greco_GR140682_ecommerce.png | AO9: =A9 | AP9: =D9 | AQ9: greco_GR140682_ecommerce.png
A10: GR140012 | B10: GR140012 | C10: =IFERROR(LOWER(SUBSTITUTE(SUBSTITUTE(SUBSTITUTE(SUBSTITUTE(D10," ","-"),"/","-"),".",""),",","")),"") | D10: Sensor de Levante Corrente - Greco Agro Tech | Precision Planting PM400 | E10: Sensores Agrícolas | F10: GRECO | H10: active | I10: TODAS AS MARCAS | J10: PULVERZADOR / PLANTADEIRA | K10: COMPATÍVEL COM PRECISION PLANTING – PM400 E COD AGCO PP726780 | M10: 7 | N10: 0.489 | O10: 31 | P10: 24 | Q10: 25 | R10: =IFERROR(IF(AND(O10>0,P10>0,Q10>0),(O10*P10*Q10)/6000,""),"") | S10: =IFERROR(IF(AND(N10>0,R10>0),MAX(N10,R10),IF(N10>0,N10,IF(R10>0,R10,""))),"") | T10: 28.45 | U10: fornecedor | V10: 490 | W10: 0.2 | X10: =IFERROR(V10+T10,"") | Y10: =IFERROR(IF(W10<1,X10/(1-W10),""),"") | Z10: ='01_CONFIG_GLOBAL'!$C$14 | AA10: =IFERROR(Y10*Z10,"") | AB10: =IFERROR(IF(Z10<1,Y10/(1-Z10),""),"") | AI10: =IFERROR(AVERAGE(AD10,AF10,AH10),"") | AJ10: =IFERROR(IF(AI10="","sem dados",IF(AB10<AI10*0.95,"abaixo",IF(AB10>AI10*1.05,"acima","em linha"))),"") | AK10: sim | AN10: Fotos: assets/greco_GR140012_ecommerce.png | AO10: =A10 | AP10: =D10 | AQ10: greco_GR140012_ecommerce.png
A11: GR142398 | B11: GR142398 | C11: =IFERROR(LOWER(SUBSTITUTE(SUBSTITUTE(SUBSTITUTE(SUBSTITUTE(D11," ","-"),"/","-"),".",""),",","")),"") | D11: Monitor de Fluxo de Sementes GR500 - Greco Agro Tech | E11: Sensores Agrícolas | F11: GRECO | H11: active | I11: TODAS AS MARCAS | J11: PLANTADEIRA | K11: KIT POSSUI CABO DE BATERIA, EXTENSÃO, CHICOTE PARA LIGAÇÃO DOS SENSORES E ECU. | M11: 7 | N11: 1.642 | O11: 31 | P11: 24 | Q11: 25 | R11: =IFERROR(IF(AND(O11>0,P11>0,Q11>0),(O11*P11*Q11)/6000,""),"") | S11: =IFERROR(IF(AND(N11>0,R11>0),MAX(N11,R11),IF(N11>0,N11,IF(R11>0,R11,""))),"") | T11: 39.11 | U11: fornecedor | V11: 7700 | W11: 0.2 | X11: =IFERROR(V11+T11,"") | Y11: =IFERROR(IF(W11<1,X11/(1-W11),""),"") | Z11: ='01_CONFIG_GLOBAL'!$C$14 | AA11: =IFERROR(Y11*Z11,"") | AB11: =IFERROR(IF(Z11<1,Y11/(1-Z11),""),"") | AI11: =IFERROR(AVERAGE(AD11,AF11,AH11),"") | AJ11: =IFERROR(IF(AI11="","sem dados",IF(AB11<AI11*0.95,"abaixo",IF(AB11>AI11*1.05,"acima","em linha"))),"") | AK11: sim | AN11: Fotos: assets/greco_GR142398_ecommerce.png | AO11: =A11 | AP11: =D11 | AQ11: greco_GR142398_ecommerce.png
A12: GR142226 | B12: GR142226 | C12: =IFERROR(LOWER(SUBSTITUTE(SUBSTITUTE(SUBSTITUTE(SUBSTITUTE(D12," ","-"),"/","-"),".",""),",","")),"") | D12: Sensor de Fluxo 25,4mm - Greco Agro Tech | Precision Planting PM400 | E12: Sensores Agrícolas | F12: GRECO | H12: active | I12: TODAS AS MARCAS | J12: PLANTADEIRA | K12: COMPATÍVEL COM PRECISION PLANTING – PM400 | M12: 7 | N12: 0.33 | O12: 31 | P12: 24 | Q12: 25 | R12: =IFERROR(IF(AND(O12>0,P12>0,Q12>0),(O12*P12*Q12)/6000,""),"") | S12: =IFERROR(IF(AND(N12>0,R12>0),MAX(N12,R12),IF(N12>0,N12,IF(R12>0,R12,""))),"") | T12: 26.8 | U12: fornecedor | V12: 290 | W12: 0.2 | X12: =IFERROR(V12+T12,"") | Y12: =IFERROR(IF(W12<1,X12/(1-W12),""),"") | Z12: ='01_CONFIG_GLOBAL'!$C$14 | AA12: =IFERROR(Y12*Z12,"") | AB12: =IFERROR(IF(Z12<1,Y12/(1-Z12),""),"") | AI12: =IFERROR(AVERAGE(AD12,AF12,AH12),"") | AJ12: =IFERROR(IF(AI12="","sem dados",IF(AB12<AI12*0.95,"abaixo",IF(AB12>AI12*1.05,"acima","em linha"))),"") | AK12: sim | AN12: Fotos: assets/greco_GR142226_ecommerce.png | AO12: =A12 | AP12: =D12 | AQ12: greco_GR142226_ecommerce.png
A13: GR142227 | B13: GR142227 | C13: =IFERROR(LOWER(SUBSTITUTE(SUBSTITUTE(SUBSTITUTE(SUBSTITUTE(D13," ","-"),"/","-"),".",""),",","")),"") | D13: Sensor de Fluxo 32mm - Greco Agro Tech | Precision Planting PM400 | E13: Sensores Agrícolas | F13: GRECO | H13: active | I13: TODAS AS MARCAS | J13: PLANTADEIRA | K13: COMPATÍVEL COM PRECISION PLANTING – PM400 E COD AGCO AXC3452630 | M13: 7 | N13: 0.29 | O13: 31 | P13: 24 | Q13: 25 | R13: =IFERROR(IF(AND(O13>0,P13>0,Q13>0),(O13*P13*Q13)/6000,""),"") | S13: =IFERROR(IF(AND(N13>0,R13>0),MAX(N13,R13),IF(N13>0,N13,IF(R13>0,R13,""))),"") | T13: 26.96 | U13: fornecedor | V13: 310 | W13: 0.2 | X13: =IFERROR(V13+T13,"") | Y13: =IFERROR(IF(W13<1,X13/(1-W13),""),"") | Z13: ='01_CONFIG_GLOBAL'!$C$14 | AA13: =IFERROR(Y13*Z13,"") | AB13: =IFERROR(IF(Z13<1,Y13/(1-Z13),""),"") | AI13: =IFERROR(AVERAGE(AD13,AF13,AH13),"") | AJ13: =IFERROR(IF(AI13="","sem dados",IF(AB13<AI13*0.95,"abaixo",IF(AB13>AI13*1.05,"acima","em linha"))),"") | AK13: sim | AN13: Fotos: assets/greco_GR142227_ecommerce.png | AO13: =A13 | AP13: =D13 | AQ13: greco_GR142227_ecommerce.png
A14: GR142228 | B14: GR142228 | C14: =IFERROR(LOWER(SUBSTITUTE(SUBSTITUTE(SUBSTITUTE(SUBSTITUTE(D14," ","-"),"/","-"),".",""),",","")),"") | D14: Sensor de Fluxo 50,8mm - Greco Agro Tech | Precision Planting PM400 | E14: Sensores Agrícolas | F14: GRECO | H14: active | I14: TODAS AS MARCAS | J14: PLANTADEIRA | K14: COMPATÍVEL COM PRECISION PLANTING – PM400 | M14: 7 | N14: 0.56 | O14: 31 | P14: 24 | Q14: 25 | R14: =IFERROR(IF(AND(O14>0,P14>0,Q14>0),(O14*P14*Q14)/6000,""),"") | S14: =IFERROR(IF(AND(N14>0,R14>0),MAX(N14,R14),IF(N14>0,N14,IF(R14>0,R14,""))),"") | T14: 27.37 | U14: fornecedor | V14: 360 | W14: 0.2 | X14: =IFERROR(V14+T14,"") | Y14: =IFERROR(IF(W14<1,X14/(1-W14),""),"") | Z14: ='01_CONFIG_GLOBAL'!$C$14 | AA14: =IFERROR(Y14*Z14,"") | AB14: =IFERROR(IF(Z14<1,Y14/(1-Z14),""),"") | AI14: =IFERROR(AVERAGE(AD14,AF14,AH14),"") | AJ14: =IFERROR(IF(AI14="","sem dados",IF(AB14<AI14*0.95,"abaixo",IF(AB14>AI14*1.05,"acima","em linha"))),"") | AK14: sim | AN14: Fotos: assets/greco_GR142228_ecommerce.png | AO14: =A14 | AP14: =D14 | AQ14: greco_GR142228_ecommerce.png
A15: GR142229 | B15: GR142229 | C15: =IFERROR(LOWER(SUBSTITUTE(SUBSTITUTE(SUBSTITUTE(SUBSTITUTE(D15," ","-"),"/","-"),".",""),",","")),"") | D15: Sensor de Semente - Greco Agro Tech | Precision Planting PM400 | E15: Sensores Agrícolas | F15: GRECO | H15: active | I15: TODAS AS MARCAS | J15: PLANTADEIRA | K15: COMPATÍVEL COM PRECISION PLANTING – PM400 E COD AGCO AXC3452830 | M15: 7 | N15: 0.011 | O15: 31 | P15: 24 | Q15: 25 | R15: =IFERROR(IF(AND(O15>0,P15>0,Q15>0),(O15*P15*Q15)/6000,""),"") | S15: =IFERROR(IF(AND(N15>0,R15>0),MAX(N15,R15),IF(N15>0,N15,IF(R15>0,R15,""))),"") | T15: 25.55 | U15: fornecedor | V15: 140 | W15: 0.2 | X15: =IFERROR(V15+T15,"") | Y15: =IFERROR(IF(W15<1,X15/(1-W15),""),"") | Z15: ='01_CONFIG_GLOBAL'!$C$14 | AA15: =IFERROR(Y15*Z15,"") | AB15: =IFERROR(IF(Z15<1,Y15/(1-Z15),""),"") | AI15: =IFERROR(AVERAGE(AD15,AF15,AH15),"") | AJ15: =IFERROR(IF(AI15="","sem dados",IF(AB15<AI15*0.95,"abaixo",IF(AB15>AI15*1.05,"acima","em linha"))),"") | AK15: sim | AN15: Fotos: assets/greco_GR142229_ecommerce.png | AO15: =A15 | AP15: =D15 | AQ15: greco_GR142229_ecommerce.png

Sheet 05_JOHN_DEERE
A1: Q
A2: Total de SKUs: | B2: =COUNTA(A6:A100014) | D2: Faltando embalagem: | E2: =COUNTIF(W6:W100014,"FALTA") | G2: Cadastrados Shopify: | H2: =COUNTIF(AM6:AM100014,"sim") | J2: Divergentes: | K2: =COUNTIF(AM6:AM100014,"divergente")
A4: IDENTIFICAÇÃO | I4: APLICAÇÃO TÉCNICA | O4: LOGÍSTICA E EMBALAGEM | X4: CUSTO E PRECIFICAÇÃO | AE4: PESQUISA DE MERCADO | AM4: WORKFLOW
A5: SKU / Código | B5: Part Number | C5: Handle (Shopify) | D5: Title (PT-BR) | E5: Product Type | F5: Vendor (Fabricante) | G5: Tags (vírgula) | H5: Status | I5: Montadora compatível | J5: Equipamento / Modelo | K5: Função / Aplicação | L5: Códigos cruzados | M5: Qtde Kit | N5: Lead Time | O5: Peso (kg) | P5: Comprimento (cm) | Q5: Largura (cm) | R5: Altura (cm) | S5: Peso cubado (kg) KIT | T5: Peso cubado (kg) | U5: Peso considerado (kg) | V5: Frete fábrica → eCom () | W5: Origem do dado embalagem | X5: Custo unitário () | Y5: % Margem de lucro | Z5: Custo + frete inbound () | AA5: Preço c/ margem () | AB5: Taxa Mercado Pago (%) | AC5: Taxa MP () | AD5: Preço final site () | AE5: Concorrente 1 — Nome | AF5: Concorrente 1 — Preço () | AG5: Concorrente 2 — Nome | AH5: Concorrente 2 — Preço () | AI5: Concorrente 3 — Nome | AJ5: Concorrente 3 — Preço () | AK5: Preço médio concorrência () | AL5: Posicionamento | AM5: Cadastrado Shopify? | AN5: Última atualização | AO5: Operador responsável | AP5: Observações | AQ5: SKU Shopify (derivado) | AR5: Título Shopify (derivado) | AS5: Imagens site (assets)
A6: H-102724 | B6: H-102724 | C6: dedo-retratil-jd-quadrado | D6: Dedo Retrátil Quadrado - John Deere H-102724 | Plataforma de Corte | E6: Peças Plásticas Injetadas | F6: APP | H6: active | I6: JOHN DEERE | J6: COLHEITADEIRA | K6: =LOWER(CONCATENATE("Peças Plastica para ",J6," ",D6)) | M6: 1 | N6: 5 | O6: 0.074 | P6: 26.5 | Q6: 2 | R6: 2 | S6: =IFERROR(IF(AND(P6>0,Q6>0,R6>0),(P6*Q6*R6)/6000,""),"") | T6: =IFERROR(IF(AND(P6>0,Q6>0,R6>0),(P6*Q6*R6)/6000,""),"") | U6: =IFERROR(IF(AND(O6>0,T6>0),MAX(O6,T6),IF(O6>0,O6,IF(T6>0,T6,""))),"") | V6: 0.53 | W6: fornecedor | X6: 5 | Y6: 0.3 | Z6: =IFERROR(X6+V6,"") | AA6: =IFERROR(IF(Y6<1,Z6/(1-Y6),""),"") | AB6: ='01_CONFIG_GLOBAL'!$C$14 | AC6: =IFERROR(AA6*AB6,"") | AD6: =IFERROR(IF(AB6<1,AA6/(1-AB6),""),"") | AM6: sim | AP6: Fotos: assets/JOHN_DEERE_H-102724_ecommerce.png | AQ6: =IF(AND(M6<>"",M6>1),A6&"-KIT"&M6,A6) | AR6: =IF(AND(M6<>"",M6>1),D6&" — Kit "&M6&" unidades",D6) | AS6: JOHN_DEERE_H-102724_ecommerce.png
A7: H-102724 | B7: H-102724 | C7: dedo-retratil-jd-quadrado | D7: Dedo Retrátil Quadrado - John Deere H-102724 | Plataforma de Corte | E7: Peças Plásticas Injetadas | F7: APP | H7: active | I7: JOHN DEERE | J7: COLHEITADEIRA | K7: =LOWER(CONCATENATE("Peças Plastica para ",J7," ",D7)) | M7: 50 | N7: 5 | O7: =0.074*M7 | P7: 30 | Q7: 22 | R7: 12 | S7: =IFERROR(IF(AND(P7>0,Q7>0,R7>0),(P7*Q7*R7)/6000,""),"") | T7: =IFERROR(IF(AND(P7>0,Q7>0,R7>0),(P7*Q7*R7)/6000,""),"") | U7: =IFERROR(IF(AND(O7>0,T7>0),MAX(O7,T7),IF(O7>0,O7,IF(T7>0,T7,""))),"") | V7: 26.47 | W7: fornecedor | X7: =X6*M7 | Y7: =Y6 | Z7: =IFERROR(X7+V7,"") | AA7: =IFERROR(IF(Y7<1,Z7/(1-Y7),""),"") | AB7: ='01_CONFIG_GLOBAL'!$C$14 | AC7: =IFERROR(AA7*AB7,"") | AD7: =IFERROR(IF(AB7<1,AA7/(1-AB7),""),"") | AM7: sim | AQ7: =IF(AND(M7<>"",M7>1),A7&"-KIT"&M7,A7) | AR7: =IF(AND(M7<>"",M7>1),D7&" — Kit "&M7&" unidades",D7) | AS7: JOHN_DEERE_H-102724_ecommerce.png
A8: H-169914 | B8: H-169914 | C8: dedo-retratil-jd | D8: Dedo Retrátil - John Deere H-169914 | Plataforma de Corte Séries 600/700 | E8: Peças Plásticas Injetadas | F8: APP | H8: active | I8: JOHN DEERE | J8: COLHEITADEIRA | K8: =LOWER(CONCATENATE("Peças Plastica para ",J8," ",D8)) | M8: 1 | N8: 5 | O8: 0.084 | P8: 28 | Q8: 1.5 | R8: 1.5 | S8: =IFERROR(IF(AND(P8>0,Q8>0,R8>0),(P8*Q8*R8)/6000,""),"") | T8: =IFERROR(IF(AND(P8>0,Q8>0,R8>0),(P8*Q8*R8)/6000,""),"") | U8: =IFERROR(IF(AND(O8>0,T8>0),MAX(O8,T8),IF(O8>0,O8,IF(T8>0,T8,""))),"") | V8: 0.56 | W8: fornecedor | X8: 5 | Y8: 0.3 | Z8: =IFERROR(X8+V8,"") | AA8: =IFERROR(IF(Y8<1,Z8/(1-Y8),""),"") | AB8: ='01_CONFIG_GLOBAL'!$C$14 | AC8: =IFERROR(AA8*AB8,"") | AD8: =IFERROR(IF(AB8<1,AA8/(1-AB8),""),"") | AM8: sim | AP8: Fotos: assets/JOHN_DEERE_H-169914_ecommerce.png | AQ8: =IF(AND(M8<>"",M8>1),A8&"-KIT"&M8,A8) | AR8: =IF(AND(M8<>"",M8>1),D8&" — Kit "&M8&" unidades",D8) | AS8: JOHN_DEERE_H-169914_ecommerce.png
A9: H-169914 | B9: H-169914 | C9: dedo-retratil-jd | D9: Dedo Retrátil - John Deere H-169914 | Plataforma de Corte Séries 600/700 | E9: Peças Plásticas Injetadas | F9: APP | H9: active | I9: JOHN DEERE | J9: COLHEITADEIRA | K9: =LOWER(CONCATENATE("Peças Plastica para ",J9," ",D9)) | M9: 50 | N9: 5 | O9: =0.084*M9 | P9: 30 | Q9: 22 | R9: 12 | S9: =IFERROR(IF(AND(P9>0,Q9>0,R9>0),(P9*Q9*R9)/6000,""),"") | T9: =IFERROR(IF(AND(P9>0,Q9>0,R9>0),(P9*Q9*R9)/6000,""),"") | U9: =IFERROR(IF(AND(O9>0,T9>0),MAX(O9,T9),IF(O9>0,O9,IF(T9>0,T9,""))),"") | V9: 28.15 | W9: fornecedor | X9: =X8*M9 | Y9: =Y8 | Z9: =IFERROR(X9+V9,"") | AA9: =IFERROR(IF(Y9<1,Z9/(1-Y9),""),"") | AB9: ='01_CONFIG_GLOBAL'!$C$14 | AC9: =IFERROR(AA9*AB9,"") | AD9: =IFERROR(IF(AB9<1,AA9/(1-AB9),""),"") | AM9: sim | AQ9: =IF(AND(M9<>"",M9>1),A9&"-KIT"&M9,A9) | AR9: =IF(AND(M9<>"",M9>1),D9&" — Kit "&M9&" unidades",D9) | AS9: JOHN_DEERE_H-169914_ecommerce.png
A10: H-175727 | B10: H-175727 | C10: suporte-do-molinete | D10: Suporte do Molinete - John Deere H-175727 | Plataforma de Corte | E10: Peças Plásticas Injetadas | F10: APP | H10: active | I10: JOHN DEERE | J10: COLHEITADEIRA | K10: =LOWER(CONCATENATE("Peças Plastica para ",J10," ",D10)) | M10: 1 | N10: 5 | O10: 0.02 | P10: 2.5 | Q10: 8.4 | R10: 3 | S10: =IFERROR(IF(AND(P10>0,Q10>0,R10>0),(P10*Q10*R10)/6000,""),"") | T10: =IFERROR(IF(AND(P10>0,Q10>0,R10>0),(P10*Q10*R10)/6000,""),"") | U10: =IFERROR(IF(AND(O10>0,T10>0),MAX(O10,T10),IF(O10>0,O10,IF(T10>0,T10,""))),"") | V10: 0.37 | W10: fornecedor | X10: 2.9 | Y10: 0.3 | Z10: =IFERROR(X10+V10,"") | AA10: =IFERROR(IF(Y10<1,Z10/(1-Y10),""),"") | AB10: ='01_CONFIG_GLOBAL'!$C$14 | AC10: =IFERROR(AA10*AB10,"") | AD10: =IFERROR(IF(AB10<1,AA10/(1-AB10),""),"") | AM10: sim | AP10: Fotos: assets/JOHN_DEERE_H-175727_ecommerce.png | AQ10: =IF(AND(M10<>"",M10>1),A10&"-KIT"&M10,A10) | AR10: =IF(AND(M10<>"",M10>1),D10&" — Kit "&M10&" unidades",D10) | AS10: JOHN_DEERE_H-175727_ecommerce.png
A11: H-175727 | B11: H-175727 | C11: suporte-do-molinete | D11: Suporte do Molinete - John Deere H-175727 | Plataforma de Corte | E11: Peças Plásticas Injetadas | F11: APP | H11: active | I11: JOHN DEERE | J11: COLHEITADEIRA | K11: =LOWER(CONCATENATE("Peças Plastica para ",J11," ",D11)) | M11: 50 | N11: 5 | O11: =0.02*M11 | P11: 30 | Q11: 10 | R11: 18 | S11: =IFERROR(IF(AND(P11>0,Q11>0,R11>0),(P11*Q11*R11)/6000,""),"") | T11: =IFERROR(IF(AND(P11>0,Q11>0,R11>0),(P11*Q11*R11)/6000,""),"") | U11: =IFERROR(IF(AND(O11>0,T11>0),MAX(O11,T11),IF(O11>0,O11,IF(T11>0,T11,""))),"") | V11: 18.26 | W11: fornecedor | X11: =X10*M11 | Y11: =Y10 | Z11: =IFERROR(X11+V11,"") | AA11: =IFERROR(IF(Y11<1,Z11/(1-Y11),""),"") | AB11: ='01_CONFIG_GLOBAL'!$C$14 | AC11: =IFERROR(AA11*AB11,"") | AD11: =IFERROR(IF(AB11<1,AA11/(1-AB11),""),"") | AM11: sim | AQ11: =IF(AND(M11<>"",M11>1),A11&"-KIT"&M11,A11) | AR11: =IF(AND(M11<>"",M11>1),D11&" — Kit "&M11&" unidades",D11) | AS11: JOHN_DEERE_H-175727_ecommerce.png
A12: KK31823 | B12: KK31823 | C12: dedo-recolhedor-algod-o-grande | D12: Dedo Recolhedor Algodão Grande - John Deere KK31823 | Colhedora de Algodão | E12: Peças Plásticas Injetadas | F12: APP | H12: active | I12: JOHN DEERE | J12: COLHEITADEIRA | K12: =LOWER(CONCATENATE("Peças Plastica para ",J12," ",D12)) | M12: 1 | N12: 5 | O12: =0.175*M12 | P12: 33.6 | Q12: 38 | R12: 1 | S12: =IFERROR(IF(AND(P12>0,Q12>0,R12>0),(P12*Q12*R12)/6000,""),"") | T12: =IFERROR(IF(AND(P12>0,Q12>0,R12>0),(P12*Q12*R12)/6000,""),"") | U12: =IFERROR(IF(AND(O12>0,T12>0),MAX(O12,T12),IF(O12>0,O12,IF(T12>0,T12,""))),"") | V12: 27.57 | W12: fornecedor | X12: 140 | Y12: 0.3 | Z12: =IFERROR(X12+V12,"") | AA12: =IFERROR(IF(Y12<1,Z12/(1-Y12),""),"") | AB12: ='01_CONFIG_GLOBAL'!$C$14 | AC12: =IFERROR(AA12*AB12,"") | AD12: =IFERROR(IF(AB12<1,AA12/(1-AB12),""),"") | AM12: sim | AP12: Fotos: assets/JOHN_DEERE_KK31823_ecommerce.png | AQ12: =IF(AND(M12<>"",M12>1),A12&"-KIT"&M12,A12) | AR12: =IF(AND(M12<>"",M12>1),D12&" — Kit "&M12&" unidades",D12) | AS12: JOHN_DEERE_KK31823_ecommerce.png
A13: KK31824 | B13: KK31824 | C13: dedo-recolhedor-algod-o-m-dio | D13: Dedo Recolhedor Algodão Médio - John Deere KK31824 | Colhedora 7760/CP690 | E13: Peças Plásticas Injetadas | F13: APP | H13: active | I13: JOHN DEERE | J13: COLHEITADEIRA | K13: =LOWER(CONCATENATE("Peças Plastica para ",J13," ",D13)) | M13: 1 | N13: 5 | O13: 0.127 | P13: 33.4 | Q13: 27 | R13: 4 | S13: =IFERROR(IF(AND(P13>0,Q13>0,R13>0),(P13*Q13*R13)/6000,""),"") | T13: =IFERROR(IF(AND(P13>0,Q13>0,R13>0),(P13*Q13*R13)/6000,""),"") | U13: =IFERROR(IF(AND(O13>0,T13>0),MAX(O13,T13),IF(O13>0,O13,IF(T13>0,T13,""))),"") | V13: 18.05 | W13: fornecedor | X13: 110 | Y13: 0.3 | Z13: =IFERROR(X13+V13,"") | AA13: =IFERROR(IF(Y13<1,Z13/(1-Y13),""),"") | AB13: ='01_CONFIG_GLOBAL'!$C$14 | AC13: =IFERROR(AA13*AB13,"") | AD13: =IFERROR(IF(AB13<1,AA13/(1-AB13),""),"") | AM13: sim | AP13: Fotos: assets/JOHN_DEERE_KK31824_ecommerce.png | CORRIGIDO 21/07: custo 120 é do lote de 25 — linha marcada kit=25 (duplica r38) | AQ13: =IF(AND(M13<>"",M13>1),A13&"-KIT"&M13,A13) | AR13: =IF(AND(M13<>"",M13>1),D13&" — Kit "&M13&" unidades",D13) | AS13: JOHN_DEERE_KK31824_ecommerce.png
A14: KK31825 | B14: KK31825 | C14: dedo-recolhedor-algod-o-pequeno | D14: Dedo Recolhedor Algodão Pequeno - John Deere KK31825 | Colhedora 7760/CP690 | E14: Peças Plásticas Injetadas | F14: APP | H14: active | I14: JOHN DEERE | J14: COLHEITADEIRA | K14: =LOWER(CONCATENATE("Peças Plastica para ",J14," ",D14)) | M14: 1 | N14: 5 | O14: 0.1 | P14: 33 | Q14: 16.2 | R14: 4 | S14: =IFERROR(IF(AND(P14>0,Q14>0,R14>0),(P14*Q14*R14)/6000,""),"") | T14: =IFERROR(IF(AND(P14>0,Q14>0,R14>0),(P14*Q14*R14)/6000,""),"") | U14: =IFERROR(IF(AND(O14>0,T14>0),MAX(O14,T14),IF(O14>0,O14,IF(T14>0,T14,""))),"") | V14: 16.74 | W14: fornecedor | X14: 90 | Y14: 0.3 | Z14: =IFERROR(X14+V14,"") | AA14: =IFERROR(IF(Y14<1,Z14/(1-Y14),""),"") | AB14: ='01_CONFIG_GLOBAL'!$C$14 | AC14: =IFERROR(AA14*AB14,"") | AD14: =IFERROR(IF(AB14<1,AA14/(1-AB14),""),"") | AM14: sim | AP14: Fotos: assets/JOHN_DEERE_KK31825_ecommerce.png | CORRIGIDO 21/07: custo 100 é do lote de 25 — linha marcada kit=25 (duplica r40) | AQ14: =IF(AND(M14<>"",M14>1),A14&"-KIT"&M14,A14) | AR14: =IF(AND(M14<>"",M14>1),D14&" — Kit "&M14&" unidades",D14) | AS14: JOHN_DEERE_KK31825_ecommerce.png
A15: KK31825 | B15: KK31825 | C15: dedo-recolhedor-algod-o-pequeno | D15: Dedo Recolhedor Algodão Pequeno - John Deere KK31825 | Colhedora 7760/CP690 | E15: Peças Plásticas Injetadas | F15: APP | H15: draft | I15: JOHN DEERE | J15: COLHEITADEIRA | K15: =LOWER(CONCATENATE("Peças Plastica para ",J15," ",D15)) | M15: 2 | N15: 5 | O15: =0.1*M15 | P15: 35 | Q15: 20 | R15: 1 | S15: =IFERROR(IF(AND(P15>0,Q15>0,R15>0),(P15*Q15*R15)/6000,""),"") | T15: =IFERROR(IF(AND(P15>0,Q15>0,R15>0),(P15*Q15*R15)/6000,""),"") | U15: =IFERROR(IF(AND(O15>0,T15>0),MAX(O15,T15),IF(O15>0,O15,IF(T15>0,T15,""))),"") | W15: fornecedor | X15: =X14*M15 | Y15: =Y14 | Z15: =IFERROR(X15+V15,"") | AA15: =IFERROR(IF(Y15<1,Z15/(1-Y15),""),"") | AB15: ='01_CONFIG_GLOBAL'!$C$14 | AC15: =IFERROR(AA15*AB15,"") | AD15: =IFERROR(IF(AB15<1,AA15/(1-AB15),""),"") | AM15: sim | AP15: PENDÊNCIA: custo inconsistente (kit=2 a R$200 vs kit=25 a R$100) — revisar com fornecedor | AQ15: =IF(AND(M15<>"",M15>1),A15&"-KIT"&M15,A15) | AR15: =IF(AND(M15<>"",M15>1),D15&" — Kit "&M15&" unidades",D15) | AS15: JOHN_DEERE_KK31825_ecommerce.png
A16: N276747 | B16: N276747 | C16: tampa-algod-o | D16: Tampa Algodão - John Deere N276747 | Colhedora de Algodão | E16: Peças Plásticas Injetadas | F16: APP | H16: active | I16: JOHN DEERE | J16: COLHEITADEIRA | K16: =LOWER(CONCATENATE("Peças Plastica para ",J16," ",D16)) | M16: 1 | N16: 5 | O16: 0.047 | P16: 7.9 | Q16: 8.6 | R16: 7.9 | S16: =IFERROR(IF(AND(P16>0,Q16>0,R16>0),(P16*Q16*R16)/6000,""),"") | T16: =IFERROR(IF(AND(P16>0,Q16>0,R16>0),(P16*Q16*R16)/6000,""),"") | U16: =IFERROR(IF(AND(O16>0,T16>0),MAX(O16,T16),IF(O16>0,O16,IF(T16>0,T16,""))),"") | V16: 1.06 | W16: fornecedor | X16: 9.9 | Y16: 0.3 | Z16: =IFERROR(X16+V16,"") | AA16: =IFERROR(IF(Y16<1,Z16/(1-Y16),""),"") | AB16: ='01_CONFIG_GLOBAL'!$C$14 | AC16: =IFERROR(AA16*AB16,"") | AD16: =IFERROR(IF(AB16<1,AA16/(1-AB16),""),"") | AM16: sim | AP16: Fotos: assets/JOHN_DEERE_N276747_ecommerce.png | AQ16: =IF(AND(M16<>"",M16>1),A16&"-KIT"&M16,A16) | AR16: =IF(AND(M16<>"",M16>1),D16&" — Kit "&M16&" unidades",D16) | AS16: JOHN_DEERE_N276747_ecommerce.png
A17: N276747 | B17: N276747 | C17: tampa-algod-o | D17: Tampa Algodão - John Deere N276747 | Colhedora de Algodão | E17: Peças Plásticas Injetadas | F17: APP | H17: active | I17: JOHN DEERE | J17: COLHEITADEIRA | K17: =LOWER(CONCATENATE("Peças Plastica para ",J17," ",D17)) | M17: 25 | N17: 5 | O17: =0.047*M17 | P17: 45 | Q17: 10 | R17: 45 | S17: =IFERROR(IF(AND(P17>0,Q17>0,R17>0),(P17*Q17*R17)/6000,""),"") | T17: =IFERROR(IF(AND(P17>0,Q17>0,R17>0),(P17*Q17*R17)/6000,""),"") | U17: =IFERROR(IF(AND(O17>0,T17>0),MAX(O17,T17),IF(O17>0,O17,IF(T17>0,T17,""))),"") | V17: 26.44 | W17: fornecedor | X17: =X16*M17 | Y17: =Y16 | Z17: =IFERROR(X17+V17,"") | AA17: =IFERROR(IF(Y17<1,Z17/(1-Y17),""),"") | AB17: ='01_CONFIG_GLOBAL'!$C$14 | AC17: =IFERROR(AA17*AB17,"") | AD17: =IFERROR(IF(AB17<1,AA17/(1-AB17),""),"") | AM17: sim | AQ17: =IF(AND(M17<>"",M17>1),A17&"-KIT"&M17,A17) | AR17: =IF(AND(M17<>"",M17>1),D17&" — Kit "&M17&" unidades",D17) | AS17: JOHN_DEERE_N276747_ecommerce.png
A18: A56254 | B18: A56254 | C18: aro-tampa-reservatorio-central-de-sementes | D18: Aro da Tampa do Reservatório Central de Sementes - John Deere A56254 | Plantadeira | E18: Peças Plásticas Injetadas | F18: APP | H18: active | I18: JOHN DEERE | J18: PLANTADEIRA | K18: =LOWER(CONCATENATE("Peças Plastica para ",J18," ",D18)) | M18: 1 | N18: 5 | O18: 0.22 | P18: 61.9 | Q18: 61.9 | R18: 4.1 | S18: =IFERROR(IF(AND(P18>0,Q18>0,R18>0),(P18*Q18*R18)/6000,""),"") | T18: =IFERROR(IF(AND(P18>0,Q18>0,R18>0),(P18*Q18*R18)/6000,""),"") | U18: =IFERROR(IF(AND(O18>0,T18>0),MAX(O18,T18),IF(O18>0,O18,IF(T18>0,T18,""))),"") | V18: 23.66 | W18: fornecedor | X18: 50 | Y18: 0.3 | Z18: =IFERROR(X18+V18,"") | AA18: =IFERROR(IF(Y18<1,Z18/(1-Y18),""),"") | AB18: ='01_CONFIG_GLOBAL'!$C$14 | AC18: =IFERROR(AA18*AB18,"") | AD18: =IFERROR(IF(AB18<1,AA18/(1-AB18),""),"") | AM18: sim | AP18: Fotos: assets/JOHN_DEERE_A56254_ecommerce.png | AQ18: =IF(AND(M18<>"",M18>1),A18&"-KIT"&M18,A18) | AR18: =IF(AND(M18<>"",M18>1),D18&" — Kit "&M18&" unidades",D18) | AS18: JOHN_DEERE_A56254_ecommerce.png
A19: CQ59313 | B19: CQ59313 | C19: caixa-de-sementes-mini-hooper | D19: Caixa de Sementes Mini Hopper - John Deere CQ59313 | Plantadeira a Vácuo | E19: Peças Plásticas Injetadas | F19: APP | H19: active | I19: JOHN DEERE | J19: PLANTADEIRA | K19: =LOWER(CONCATENATE("Peças Plastica para ",J19," ",D19)) | M19: 1 | N19: 5 | O19: 0.26 | P19: 11.2 | Q19: 20 | R19: 13.6 | S19: =IFERROR(IF(AND(P19>0,Q19>0,R19>0),(P19*Q19*R19)/6000,""),"") | T19: =IFERROR(IF(AND(P19>0,Q19>0,R19>0),(P19*Q19*R19)/6000,""),"") | U19: =IFERROR(IF(AND(O19>0,T19>0),MAX(O19,T19),IF(O19>0,O19,IF(T19>0,T19,""))),"") | V19: 17.89 | W19: fornecedor | X19: 27 | Y19: 0.3 | Z19: =IFERROR(X19+V19,"") | AA19: =IFERROR(IF(Y19<1,Z19/(1-Y19),""),"") | AB19: ='01_CONFIG_GLOBAL'!$C$14 | AC19: =IFERROR(AA19*AB19,"") | AD19: =IFERROR(IF(AB19<1,AA19/(1-AB19),""),"") | AM19: sim | AP19: Fotos: assets/JOHN_DEERE_CQ59313_ecommerce.png | AQ19: =IF(AND(M19<>"",M19>1),A19&"-KIT"&M19,A19) | AR19: =IF(AND(M19<>"",M19>1),D19&" — Kit "&M19&" unidades",D19) | AS19: JOHN_DEERE_CQ59313_ecommerce.png
A20: CQ65827 | B20: CQ65827 | C20: condutor-jd | D20: Condutor de Adubo - John Deere CQ65827 | Plantadeiras Séries 1100/2100 | E20: Peças Plásticas Injetadas | F20: APP | H20: active | I20: JOHN DEERE | J20: PLANTADEIRA | K20: =LOWER(CONCATENATE("Peças Plastica para ",J20," ",D20)) | M20: 1 | N20: 5 | O20: 0.09 | P20: 9 | Q20: 33 | R20: 6.5 | S20: =IFERROR(IF(AND(P20>0,Q20>0,R20>0),(P20*Q20*R20)/6000,""),"") | T20: =IFERROR(IF(AND(P20>0,Q20>0,R20>0),(P20*Q20*R20)/6000,""),"") | U20: =IFERROR(IF(AND(O20>0,T20>0),MAX(O20,T20),IF(O20>0,O20,IF(T20>0,T20,""))),"") | V20: 1.96 | W20: fornecedor | X20: 4.1 | Y20: 0.3 | Z20: =IFERROR(X20+V20,"") | AA20: =IFERROR(IF(Y20<1,Z20/(1-Y20),""),"") | AB20: ='01_CONFIG_GLOBAL'!$C$14 | AC20: =IFERROR(AA20*AB20,"") | AD20: =IFERROR(IF(AB20<1,AA20/(1-AB20),""),"") | AM20: sim | AP20: Fotos: assets/JOHN_DEERE_CQ65827_ecommerce.png | AQ20: =IF(AND(M20<>"",M20>1),A20&"-KIT"&M20,A20) | AR20: =IF(AND(M20<>"",M20>1),D20&" — Kit "&M20&" unidades",D20) | AS20: JOHN_DEERE_CQ65827_ecommerce.png
A21: CQ65827 | B21: CQ65827 | C21: condutor-jd | D21: Condutor de Adubo - John Deere CQ65827 | Plantadeiras Séries 1100/2100 | E21: Peças Plásticas Injetadas | F21: APP | H21: active | I21: JOHN DEERE | J21: PLANTADEIRA | K21: =LOWER(CONCATENATE("Peças Plastica para ",J21," ",D21)) | M21: 50 | N21: 5 | O21: =0.09*M21 | P21: 50 | Q21: 35 | R21: 70 | S21: =IFERROR(IF(AND(P21>0,Q21>0,R21>0),(P21*Q21*R21)/6000,""),"") | T21: =IFERROR(IF(AND(P21>0,Q21>0,R21>0),(P21*Q21*R21)/6000,""),"") | U21: =IFERROR(IF(AND(O21>0,T21>0),MAX(O21,T21),IF(O21>0,O21,IF(T21>0,T21,""))),"") | V21: 98.23 | W21: fornecedor | X21: =X20*M21 | Y21: =Y20 | Z21: =IFERROR(X21+V21,"") | AA21: =IFERROR(IF(Y21<1,Z21/(1-Y21),""),"") | AB21: ='01_CONFIG_GLOBAL'!$C$14 | AC21: =IFERROR(AA21*AB21,"") | AD21: =IFERROR(IF(AB21<1,AA21/(1-AB21),""),"") | AM21: sim | AQ21: =IF(AND(M21<>"",M21>1),A21&"-KIT"&M21,A21) | AR21: =IF(AND(M21<>"",M21>1),D21&" — Kit "&M21&" unidades",D21) | AS21: JOHN_DEERE_CQ65827_ecommerce.png
A22: CQ54137 | B22: CQ54137 | C22: condutor-john-deere | D22: Condutor de Sementes em S - John Deere CQ54137 | Plantadeira | E22: Peças Plásticas Injetadas | F22: APP | H22: active | I22: JOHN DEERE | J22: PLANTADEIRA | K22: =LOWER(CONCATENATE("Peças Plastica para ",J22," ",D22)) | M22: 1 | N22: 5 | O22: 0.075 | P22: 22 | Q22: 7 | R22: 6 | S22: =IFERROR(IF(AND(P22>0,Q22>0,R22>0),(P22*Q22*R22)/6000,""),"") | T22: =IFERROR(IF(AND(P22>0,Q22>0,R22>0),(P22*Q22*R22)/6000,""),"") | U22: =IFERROR(IF(AND(O22>0,T22>0),MAX(O22,T22),IF(O22>0,O22,IF(T22>0,T22,""))),"") | V22: 1.19 | W22: fornecedor | X22: 4.5 | Y22: 0.3 | Z22: =IFERROR(X22+V22,"") | AA22: =IFERROR(IF(Y22<1,Z22/(1-Y22),""),"") | AB22: ='01_CONFIG_GLOBAL'!$C$14 | AC22: =IFERROR(AA22*AB22,"") | AD22: =IFERROR(IF(AB22<1,AA22/(1-AB22),""),"") | AM22: sim | AP22: Fotos: assets/JOHN_DEERE_CQ54137_ecommerce.png | AQ22: =IF(AND(M22<>"",M22>1),A22&"-KIT"&M22,A22) | AR22: =IF(AND(M22<>"",M22>1),D22&" — Kit "&M22&" unidades",D22) | AS22: JOHN_DEERE_CQ54137_ecommerce.png
A23: CQ54137 | B23: CQ54137 | C23: condutor-john-deere | D23: Condutor de Sementes em S - John Deere CQ54137 | Plantadeira | E23: Peças Plásticas Injetadas | F23: APP | H23: active | I23: JOHN DEERE | J23: PLANTADEIRA | K23: =LOWER(CONCATENATE("Peças Plastica para ",J23," ",D23)) | M23: 50 | N23: 5 | O23: =0.075*M23 | P23: 50 | Q23: 40 | R23: 35 | S23: =IFERROR(IF(AND(P23>0,Q23>0,R23>0),(P23*Q23*R23)/6000,""),"") | T23: =IFERROR(IF(AND(P23>0,Q23>0,R23>0),(P23*Q23*R23)/6000,""),"") | U23: =IFERROR(IF(AND(O23>0,T23>0),MAX(O23,T23),IF(O23>0,O23,IF(T23>0,T23,""))),"") | V23: 59.27 | W23: fornecedor | X23: =X22*M23 | Y23: =Y22 | Z23: =IFERROR(X23+V23,"") | AA23: =IFERROR(IF(Y23<1,Z23/(1-Y23),""),"") | AB23: ='01_CONFIG_GLOBAL'!$C$14 | AC23: =IFERROR(AA23*AB23,"") | AD23: =IFERROR(IF(AB23<1,AA23/(1-AB23),""),"") | AM23: sim | AQ23: =IF(AND(M23<>"",M23>1),A23&"-KIT"&M23,A23) | AR23: =IF(AND(M23<>"",M23>1),D23&" — Kit "&M23&" unidades",D23) | AS23: JOHN_DEERE_CQ54137_ecommerce.png
A24: AA67780 | B24: AA67780 | C24: condutor-john-deere-acrilico | D24: Condutor de Sementes em Acrílico - John Deere AA67780 | Plantadeira MaxEmerge | E24: Peças Plásticas Injetadas | F24: APP | H24: active | I24: JOHN DEERE | J24: PLANTADEIRA | K24: =LOWER(CONCATENATE("Peças Plastica para ",J24," ",D24)) | M24: 1 | N24: 5 | O24: =0.204 | P24: 12 | Q24: 5 | R24: 50 | S24: =IFERROR(IF(AND(P24>0,Q24>0,R24>0),(P24*Q24*R24)/6000,""),"") | T24: =IFERROR(IF(AND(P24>0,Q24>0,R24>0),(P24*Q24*R24)/6000,""),"") | U24: =IFERROR(IF(AND(O24>0,T24>0),MAX(O24,T24),IF(O24>0,O24,IF(T24>0,T24,""))),"") | V24: 3.49 | W24: fornecedor | X24: 19.5 | Y24: 0.3 | Z24: =IFERROR(X24+V24,"") | AA24: =IFERROR(IF(Y24<1,Z24/(1-Y24),""),"") | AB24: ='01_CONFIG_GLOBAL'!$C$14 | AC24: =IFERROR(AA24*AB24,"") | AD24: =IFERROR(IF(AB24<1,AA24/(1-AB24),""),"") | AM24: sim | AP24: Fotos: assets/JOHN_DEERE_AA67780_ecommerce.png | AQ24: =IF(AND(M24<>"",M24>1),A24&"-KIT"&M24,A24) | AR24: =IF(AND(M24<>"",M24>1),D24&" — Kit "&M24&" unidades",D24) | AS24: JOHN_DEERE_AA67780_ecommerce.png
A25: AA67780 | B25: AA67780 | C25: condutor-john-deere-acrilico | D25: Condutor de Sementes em Acrílico - John Deere AA67780 | Plantadeira MaxEmerge | E25: Peças Plásticas Injetadas | F25: APP | H25: active | I25: JOHN DEERE | J25: PLANTADEIRA | K25: =LOWER(CONCATENATE("Peças Plastica para ",J25," ",D25)) | M25: 10 | N25: 5 | O25: =0.204*M25 | P25: 12 | Q25: 50 | R25: 50 | S25: =IFERROR(IF(AND(P25>0,Q25>0,R25>0),(P25*Q25*R25)/6000,""),"") | T25: =IFERROR(IF(AND(P25>0,Q25>0,R25>0),(P25*Q25*R25)/6000,""),"") | U25: =IFERROR(IF(AND(O25>0,T25>0),MAX(O25,T25),IF(O25>0,O25,IF(T25>0,T25,""))),"") | V25: 34.89 | W25: fornecedor | X25: =X24*M25 | Y25: =Y24 | Z25: =IFERROR(X25+V25,"") | AA25: =IFERROR(IF(Y25<1,Z25/(1-Y25),""),"") | AB25: ='01_CONFIG_GLOBAL'!$C$14 | AC25: =IFERROR(AA25*AB25,"") | AD25: =IFERROR(IF(AB25<1,AA25/(1-AB25),""),"") | AM25: sim | AQ25: =IF(AND(M25<>"",M25>1),A25&"-KIT"&M25,A25) | AR25: =IF(AND(M25<>"",M25>1),D25&" — Kit "&M25&" unidades",D25) | AS25: JOHN_DEERE_AA67780_ecommerce.png
A26: CQ73378 | B26: CQ73378 | C26: condutor-plantadeira-john-deere | D26: Condutor de Sementes - John Deere CQ73378 | Plantadeira | E26: Peças Plásticas Injetadas | F26: APP | H26: active | I26: JOHN DEERE | J26: PLANTADEIRA | K26: =LOWER(CONCATENATE("Peças Plastica para ",J26," ",D26)) | M26: 30 | N26: 5 | O26: =0.145*M26 | P26: 38 | Q26: 30 | R26: 60 | S26: =IFERROR(IF(AND(P26>0,Q26>0,R26>0),(P26*Q26*R26)/6000,""),"") | T26: =IFERROR(IF(AND(P26>0,Q26>0,R26>0),(P26*Q26*R26)/6000,""),"") | U26: =IFERROR(IF(AND(O26>0,T26>0),MAX(O26,T26),IF(O26>0,O26,IF(T26>0,T26,""))),"") | V26: 58.56 | W26: fornecedor | X26: =4.67*M26 | Y26: 0.3 | Z26: =IFERROR(X26+V26,"") | AA26: =IFERROR(IF(Y26<1,Z26/(1-Y26),""),"") | AB26: ='01_CONFIG_GLOBAL'!$C$14 | AC26: =IFERROR(AA26*AB26,"") | AD26: =IFERROR(IF(AB26<1,AA26/(1-AB26),""),"") | AM26: sim | AP26: Fotos: assets/JOHN_DEERE_CQ73378_ecommerce.png | AQ26: =IF(AND(M26<>"",M26>1),A26&"-KIT"&M26,A26) | AR26: =IF(AND(M26<>"",M26>1),D26&" — Kit "&M26&" unidades",D26) | AS26: JOHN_DEERE_CQ73378_ecommerce.png
A27: A75169 | B27: A75169 | C27: conex-o-pipoqueira-jd | D27: Conexão Pipoqueira - John Deere A75169 | Plantadeira a Vácuo | E27: Peças Plásticas Injetadas | F27: APP | H27: active | I27: JOHN DEERE | J27: PLANTADEIRA | K27: =LOWER(CONCATENATE("Peças Plastica para ",J27," ",D27)) | M27: 1 | N27: 5 | O27: 0.045 | P27: 6 | Q27: 7 | R27: 6 | S27: =IFERROR(IF(AND(P27>0,Q27>0,R27>0),(P27*Q27*R27)/6000,""),"") | T27: =IFERROR(IF(AND(P27>0,Q27>0,R27>0),(P27*Q27*R27)/6000,""),"") | U27: =IFERROR(IF(AND(O27>0,T27>0),MAX(O27,T27),IF(O27>0,O27,IF(T27>0,T27,""))),"") | V27: 0.53 | W27: fornecedor | X27: 4.5 | Y27: 0.3 | Z27: =IFERROR(X27+V27,"") | AA27: =IFERROR(IF(Y27<1,Z27/(1-Y27),""),"") | AB27: ='01_CONFIG_GLOBAL'!$C$14 | AC27: =IFERROR(AA27*AB27,"") | AD27: =IFERROR(IF(AB27<1,AA27/(1-AB27),""),"") | AM27: sim | AP27: Fotos: assets/JOHN_DEERE_A75169_ecommerce.png | AQ27: =IF(AND(M27<>"",M27>1),A27&"-KIT"&M27,A27) | AR27: =IF(AND(M27<>"",M27>1),D27&" — Kit "&M27&" unidades",D27) | AS27: JOHN_DEERE_A75169_ecommerce.png
A28: A75169 | B28: A75169 | C28: conex-o-pipoqueira-jd | D28: Conexão Pipoqueira - John Deere A75169 | Plantadeira a Vácuo | E28: Peças Plásticas Injetadas | F28: APP | H28: active | I28: JOHN DEERE | J28: PLANTADEIRA | K28: =LOWER(CONCATENATE("Peças Plastica para ",J28," ",D28)) | M28: 50 | N28: 5 | O28: =0.045*M28 | P28: 35 | Q28: 16 | R28: 35 | S28: =IFERROR(IF(AND(P28>0,Q28>0,R28>0),(P28*Q28*R28)/6000,""),"") | T28: =IFERROR(IF(AND(P28>0,Q28>0,R28>0),(P28*Q28*R28)/6000,""),"") | U28: =IFERROR(IF(AND(O28>0,T28>0),MAX(O28,T28),IF(O28>0,O28,IF(T28>0,T28,""))),"") | V28: 26.26 | W28: fornecedor | X28: =X27*M28 | Y28: =Y27 | Z28: =IFERROR(X28+V28,"") | AA28: =IFERROR(IF(Y28<1,Z28/(1-Y28),""),"") | AB28: ='01_CONFIG_GLOBAL'!$C$14 | AC28: =IFERROR(AA28*AB28,"") | AD28: =IFERROR(IF(AB28<1,AA28/(1-AB28),""),"") | AM28: sim | AQ28: =IF(AND(M28<>"",M28>1),A28&"-KIT"&M28,A28) | AR28: =IF(AND(M28<>"",M28>1),D28&" — Kit "&M28&" unidades",D28) | AS28: JOHN_DEERE_A75169_ecommerce.png
A29: A71321 | B29: A71321 | C29: engate-condutor-jd | D29: Engate do Condutor - John Deere A71321 | Plantadeira a Vácuo | E29: Peças Plásticas Injetadas | F29: APP | H29: active | I29: JOHN DEERE | J29: PLANTADEIRA | K29: =LOWER(CONCATENATE("Peças Plastica para ",J29," ",D29)) | M29: 1 | N29: 5 | O29: 0.039 | P29: 9.5 | Q29: 7.5 | R29: 7.5 | S29: =IFERROR(IF(AND(P29>0,Q29>0,R29>0),(P29*Q29*R29)/6000,""),"") | T29: =IFERROR(IF(AND(P29>0,Q29>0,R29>0),(P29*Q29*R29)/6000,""),"") | U29: =IFERROR(IF(AND(O29>0,T29>0),MAX(O29,T29),IF(O29>0,O29,IF(T29>0,T29,""))),"") | V29: 0.64 | W29: fornecedor | X29: 4.5 | Y29: 0.3 | Z29: =IFERROR(X29+V29,"") | AA29: =IFERROR(IF(Y29<1,Z29/(1-Y29),""),"") | AB29: ='01_CONFIG_GLOBAL'!$C$14 | AC29: =IFERROR(AA29*AB29,"") | AD29: =IFERROR(IF(AB29<1,AA29/(1-AB29),""),"") | AM29: sim | AP29: Fotos: assets/JOHN_DEERE_A71321_ecommerce.png | AQ29: =IF(AND(M29<>"",M29>1),A29&"-KIT"&M29,A29) | AR29: =IF(AND(M29<>"",M29>1),D29&" — Kit "&M29&" unidades",D29) | AS29: JOHN_DEERE_A71321_ecommerce.png
A30: A71321 | B30: A71321 | C30: engate-condutor-jd | D30: Engate do Condutor - John Deere A71321 | Plantadeira a Vácuo | E30: Peças Plásticas Injetadas | F30: APP | H30: active | I30: JOHN DEERE | J30: PLANTADEIRA | K30: =LOWER(CONCATENATE("Peças Plastica para ",J30," ",D30)) | M30: 50 | N30: 5 | O30: =0.039*M30 | P30: 20 | Q30: 40 | R30: 40 | S30: =IFERROR(IF(AND(P30>0,Q30>0,R30>0),(P30*Q30*R30)/6000,""),"") | T30: =IFERROR(IF(AND(P30>0,Q30>0,R30>0),(P30*Q30*R30)/6000,""),"") | U30: =IFERROR(IF(AND(O30>0,T30>0),MAX(O30,T30),IF(O30>0,O30,IF(T30>0,T30,""))),"") | V30: 31.99 | W30: fornecedor | X30: =X29*M30 | Y30: =Y29 | Z30: =IFERROR(X30+V30,"") | AA30: =IFERROR(IF(Y30<1,Z30/(1-Y30),""),"") | AB30: ='01_CONFIG_GLOBAL'!$C$14 | AC30: =IFERROR(AA30*AB30,"") | AD30: =IFERROR(IF(AB30<1,AA30/(1-AB30),""),"") | AM30: sim | AQ30: =IF(AND(M30<>"",M30>1),A30&"-KIT"&M30,A30) | AR30: =IF(AND(M30<>"",M30>1),D30&" — Kit "&M30&" unidades",D30) | AS30: JOHN_DEERE_A71321_ecommerce.png
A31: A72758 | B31: A72758 | C31: peneira-mini-hooper | D31: Peneira Mini Hopper - John Deere A72758 | Plantadeira a Vácuo | E31: Peças Plásticas Injetadas | F31: APP | H31: active | I31: JOHN DEERE | J31: PLANTADEIRA | K31: =LOWER(CONCATENATE("Peças Plastica para ",J31," ",D31)) | M31: 1 | N31: 5 | O31: 0.019 | P31: 7 | Q31: 10 | R31: 1.5 | S31: =IFERROR(IF(AND(P31>0,Q31>0,R31>0),(P31*Q31*R31)/6000,""),"") | T31: =IFERROR(IF(AND(P31>0,Q31>0,R31>0),(P31*Q31*R31)/6000,""),"") | U31: =IFERROR(IF(AND(O31>0,T31>0),MAX(O31,T31),IF(O31>0,O31,IF(T31>0,T31,""))),"") | V31: 0.43 | W31: fornecedor | X31: 5.6 | Y31: 0.3 | Z31: =IFERROR(X31+V31,"") | AA31: =IFERROR(IF(Y31<1,Z31/(1-Y31),""),"") | AB31: ='01_CONFIG_GLOBAL'!$C$14 | AC31: =IFERROR(AA31*AB31,"") | AD31: =IFERROR(IF(AB31<1,AA31/(1-AB31),""),"") | AM31: sim | AP31: Fotos: assets/JOHN_DEERE_A72758_ecommerce.png | AQ31: =IF(AND(M31<>"",M31>1),A31&"-KIT"&M31,A31) | AR31: =IF(AND(M31<>"",M31>1),D31&" — Kit "&M31&" unidades",D31) | AS31: JOHN_DEERE_A72758_ecommerce.png
A32: A72758 | B32: A72758 | C32: peneira-mini-hooper | D32: Peneira Mini Hopper - John Deere A72758 | Plantadeira a Vácuo | E32: Peças Plásticas Injetadas | F32: APP | H32: active | I32: JOHN DEERE | J32: PLANTADEIRA | K32: =LOWER(CONCATENATE("Peças Plastica para ",J32," ",D32)) | M32: 50 | N32: 5 | O32: =0.019*M32 | P32: 15 | Q32: 12 | R32: 40 | S32: =IFERROR(IF(AND(P32>0,Q32>0,R32>0),(P32*Q32*R32)/6000,""),"") | T32: =IFERROR(IF(AND(P32>0,Q32>0,R32>0),(P32*Q32*R32)/6000,""),"") | U32: =IFERROR(IF(AND(O32>0,T32>0),MAX(O32,T32),IF(O32>0,O32,IF(T32>0,T32,""))),"") | V32: 21.43 | W32: fornecedor | X32: =X31*M32 | Y32: =Y31 | Z32: =IFERROR(X32+V32,"") | AA32: =IFERROR(IF(Y32<1,Z32/(1-Y32),""),"") | AB32: ='01_CONFIG_GLOBAL'!$C$14 | AC32: =IFERROR(AA32*AB32,"") | AD32: =IFERROR(IF(AB32<1,AA32/(1-AB32),""),"") | AM32: sim | AQ32: =IF(AND(M32<>"",M32>1),A32&"-KIT"&M32,A32) | AR32: =IF(AND(M32<>"",M32>1),D32&" — Kit "&M32&" unidades",D32) | AS32: JOHN_DEERE_A72758_ecommerce.png
